Workbook

Sheet Summary
A1: 07K ZN6 Turbo Swap — Cost Summary
A2: All prices in CAD (USD × 1.42, GBP × 1.85 at Oct 4, 2026), before HST. Low/High = estimate range. WORKING = your actual price where you've entered one, otherwise the midpoint of the estimate. Have = Y lines count $0.
A4: Assumptions
B5: Currency | C5: CAD per unit | D5: Source
B6: CAD | C6: 1 | D6: —
B7: USD | C7: 1.42 | D7: Rate from the Oct 4, 2026 notes. Update.
B8: GBP | C8: 1.85 | D8: Estimate — update before ordering from the UK.
B10: Contingency on unconfirmed lines | C10: 0.25 | D10: Applied only to lines where you have NOT entered an actual price. Falls as you confirm prices.
B11: Gearbox route | C11: RX-8 | D11: RX-8 = RX-8 gearbox + your adapter. ZN6 TL70 = keep the car's gearbox with a custom adapter. Lines tagged for the other route turn orange and drop out.
A13: Totals by system
B14: Group | C14: Low (CAD) | D14: High (CAD) | E14: WORKING (CAD)
B15: Donors | C15: =SUMIFS(BOM!$U$5:$U$247,BOM!$L$5:$L$247,$B15) -> 11995 | D15: =SUMIFS(BOM!$V$5:$V$247,BOM!$L$5:$L$247,$B15) -> 23250 | E15: =SUMIFS(BOM!$I$5:$I$247,BOM!$L$5:$L$247,$B15) -> 17622.5
B16: Engine prep | C16: =SUMIFS(BOM!$U$5:$U$247,BOM!$L$5:$L$247,$B16) -> 1144 | D16: =SUMIFS(BOM!$V$5:$V$247,BOM!$L$5:$L$247,$B16) -> 2874 | E16: =SUMIFS(BOM!$I$5:$I$247,BOM!$L$5:$L$247,$B16) -> 2009
B17: Gearbox: RX-8 | C17: =SUMIFS(BOM!$U$5:$U$247,BOM!$L$5:$L$247,$B17) -> 2260 | D17: =SUMIFS(BOM!$V$5:$V$247,BOM!$L$5:$L$247,$B17) -> 5613 | E17: =SUMIFS(BOM!$I$5:$I$247,BOM!$L$5:$L$247,$B17) -> 3936.5
B18: Gearbox: ZN6 TL70 | C18: =SUMIFS(BOM!$U$5:$U$247,BOM!$L$5:$L$247,$B18) -> 0 | D18: =SUMIFS(BOM!$V$5:$V$247,BOM!$L$5:$L$247,$B18) -> 0 | E18: =SUMIFS(BOM!$I$5:$I$247,BOM!$L$5:$L$247,$B18) -> 0
B19: Driveline | C19: =SUMIFS(BOM!$U$5:$U$247,BOM!$L$5:$L$247,$B19) -> 724 | D19: =SUMIFS(BOM!$V$5:$V$247,BOM!$L$5:$L$247,$B19) -> 1315 | E19: =SUMIFS(BOM!$I$5:$I$247,BOM!$L$5:$L$247,$B19) -> 1019.5
B20: Mounts & chassis | C20: =SUMIFS(BOM!$U$5:$U$247,BOM!$L$5:$L$247,$B20) -> 295 | D20: =SUMIFS(BOM!$V$5:$V$247,BOM!$L$5:$L$247,$B20) -> 895 | E20: =SUMIFS(BOM!$I$5:$I$247,BOM!$L$5:$L$247,$B20) -> 595
B21: Turbo | C21: =SUMIFS(BOM!$U$5:$U$247,BOM!$L$5:$L$247,$B21) -> 4933 | D21: =SUMIFS(BOM!$V$5:$V$247,BOM!$L$5:$L$247,$B21) -> 8511 | E21: =SUMIFS(BOM!$I$5:$I$247,BOM!$L$5:$L$247,$B21) -> 6722
B22: Intake manifold (custom) | C22: =SUMIFS(BOM!$U$5:$U$247,BOM!$L$5:$L$247,$B22) -> 393 | D22: =SUMIFS(BOM!$V$5:$V$247,BOM!$L$5:$L$247,$B22) -> 680 | E22: =SUMIFS(BOM!$I$5:$I$247,BOM!$L$5:$L$247,$B22) -> 536.5
B23: Fuel | C23: =SUMIFS(BOM!$U$5:$U$247,BOM!$L$5:$L$247,$B23) -> 1078 | D23: =SUMIFS(BOM!$V$5:$V$247,BOM!$L$5:$L$247,$B23) -> 2305 | E23: =SUMIFS(BOM!$I$5:$I$247,BOM!$L$5:$L$247,$B23) -> 1691.5
B24: ECU / electronics | C24: =SUMIFS(BOM!$U$5:$U$247,BOM!$L$5:$L$247,$B24) -> 1083 | D24: =SUMIFS(BOM!$V$5:$V$247,BOM!$L$5:$L$247,$B24) -> 3553 | E24: =SUMIFS(BOM!$I$5:$I$247,BOM!$L$5:$L$247,$B24) -> 2318
B25: Cooling | C25: =SUMIFS(BOM!$U$5:$U$247,BOM!$L$5:$L$247,$B25) -> 623 | D25: =SUMIFS(BOM!$V$5:$V$247,BOM!$L$5:$L$247,$B25) -> 1340 | E25: =SUMIFS(BOM!$I$5:$I$247,BOM!$L$5:$L$247,$B25) -> 981.5
B26: Oil system | C26: =SUMIFS(BOM!$U$5:$U$247,BOM!$L$5:$L$247,$B26) -> 482 | D26: =SUMIFS(BOM!$V$5:$V$247,BOM!$L$5:$L$247,$B26) -> 1010 | E26: =SUMIFS(BOM!$I$5:$I$247,BOM!$L$5:$L$247,$B26) -> 746
... B29: Credit | C29: =SUMIFS(BOM!$U$5:$U$247,BOM!$L$5:$L$247,$B29) -> 0 | D29: =SUMIFS(BOM!$V$5:$V$247,BOM!$L$5:$L$247,$B29) -> 0 | E29: =SUMIFS(BOM!$I$5:$I$247,BOM!$L$5:$L$247,$B29) -> 0
A31: Totals by phase
B32: Group | C32: Low (CAD) | D32: High (CAD) | E32: WORKING (CAD)
B33: 0 Donors | C33: =SUMIFS(BOM!$U$5:$U$247,BOM!$S$5:$S$247,$B33) -> 12015 | D33: =SUMIFS(BOM!$V$5:$V$247,BOM!$S$5:$S$247,$B33) -> 23335 | E33: =SUMIFS(BOM!$I$5:$I$247,BOM!$S$5:$S$247,$B33) -> 17675
B34: 1 Bench / run stand | C34: =SUMIFS(BOM!$U$5:$U$247,BOM!$S$5:$S$247,$B34) -> 860 | D34: =SUMIFS(BOM!$V$5:$V$247,BOM!$S$5:$S$247,$B34) -> 1940 | E34: =SUMIFS(BOM!$I$5:$I$247,BOM!$S$5:$S$247,$B34) -> 1400
B35: 2 NA swap | C35: =SUMIFS(BOM!$U$5:$U$247,BOM!$S$5:$S$247,$B35) -> 5635 | D35: =SUMIFS(BOM!$V$5:$V$247,BOM!$S$5:$S$247,$B35) -> 13370 | E35: =SUMIFS(BOM!$I$5:$I$247,BOM!$S$5:$S$247,$B35) -> 9502.5
B36: 3 Turbo | C36: =SUMIFS(BOM!$U$5:$U$247,BOM!$S$5:$S$247,$B36) -> 7190 | D36: =SUMIFS(BOM!$V$5:$V$247,BOM!$S$5:$S$247,$B36) -> 14016 | E36: =SUMIFS(BOM!$I$5:$I$247,BOM!$S$5:$S$247,$B36) -> 10603
B37: Tools | C37: =SUMIFS(BOM!$U$5:$U$247,BOM!$S$5:$S$247,$B37) -> 85 | D37: =SUMIFS(BOM!$V$5:$V$247,BOM!$S$5:$S$247,$B37) -> 495 | E37: =SUMIFS(BOM!$I$5:$I$247,BOM!$S$5:$S$247,$B37) -> 290
A39: Totals by source
B40: Group | C40: Low (CAD) | D40: High (CAD) | E40: WORKING (CAD)
B41: Buy | C41: =SUMIFS(BOM!$U$5:$U$247,BOM!$Q$5:$Q$247,$B41) -> 24758 | D41: =SUMIFS(BOM!$V$5:$V$247,BOM!$Q$5:$Q$247,$B41) -> 50596 | E41: =SUMIFS(BOM!$I$5:$I$247,BOM!$Q$5:$Q$247,$B41) -> 37677
B42: Make | C42: =SUMIFS(BOM!$U$5:$U$247,BOM!$Q$5:$Q$247,$B42) -> 1027 | D42: =SUMIFS(BOM!$V$5:$V$247,BOM!$Q$5:$Q$247,$B42) -> 2560 | E42: =SUMIFS(BOM!$I$5:$I$247,BOM!$Q$5:$Q$247,$B42) -> 1793.5
B43: Have | C43: =SUMIFS(BOM!$U$5:$U$247,BOM!$Q$5:$Q$247,$B43) -> 0 | D43: =SUMIFS(BOM!$V$5:$V$247,BOM!$Q$5:$Q$247,$B43) -> 0 | E43: =SUMIFS(BOM!$I$5:$I$247,BOM!$Q$5:$Q$247,$B43) -> 0
B44: Sell | C44: =SUMIFS(BOM!$U$5:$U$247,BOM!$Q$5:$Q$247,$B44) -> 0 | D44: =SUMIFS(BOM!$V$5:$V$247,BOM!$Q$5:$Q$247,$B44) -> 0 | E44: =SUMIFS(BOM!$I$5:$I$247,BOM!$Q$5:$Q$247,$B44) -> 0
A46: Budget
B47: Group | C47: Low (CAD) | D47: High (CAD) | E47: WORKING (CAD)
B48: Donor car (D01) | C48: =SUMIFS(BOM!$U$5:$U$247,BOM!$A$5:$A$247,"D01") -> 11500 | D48: =SUMIFS(BOM!$V$5:$V$247,BOM!$A$5:$A$247,"D01") -> 21000 | E48: =SUMIFS(BOM!$I$5:$I$247,BOM!$A$5:$A$247,"D01") -> 16250
B49: Build parts (everything except the car) | C49: =SUM(BOM!$U$5:$U$247)-C48 -> 14285 | D49: =SUM(BOM!$V$5:$V$247)-D48 -> 32156 | E49: =SUM(BOM!$I$5:$I$247)-E48 -> 23220.5
B50: of which: confirmed (actual price entered) | C50: =SUMIFS(BOM!$U$5:$U$247,BOM!$H$5:$H$247,"<>")-SUMIFS(BOM!$U$5:$U$247,BOM!$A$5:$A$247,"D01",BOM!$H$5:$H$247,"<>") -> 0 | D50: =SUMIFS(BOM!$V$5:$V$247,BOM!$H$5:$H$247,"<>")-SUMIFS(BOM!$V$5:$V$247,BOM!$A$5:$A$247,"D01",BOM!$H$5:$H$247,"<>") -> 0 | E50: =SUMIFS(BOM!$I$5:$I$247,BOM!$H$5:$H$247,"<>")-SUMIFS(BOM!$I$5:$I$247,BOM!$A$5:$A$247,"D01",BOM!$H$5:$H$247,"<>") -> 0
B51: of which: still estimated | C51: =C49-C50 -> 14285 | D51: =D49-D50 -> 32156 | E51: =E49-E50 -> 23220.5
B52: Contingency (on the estimated part only) | C52: =C51*$C$10 -> 3571.25 | D52: =D51*$C$10 -> 8039 | E52: =E51*$C$10 -> 5805.125
B53: Build parts + contingency | C53: =C49+C52 -> 17856.25 | D53: =D49+D52 -> 40195 | E53: =E49+E52 -> 29025.625
B54: ALL-IN (car + parts + contingency) | C54: =C48+C53 -> 29356.25 | D54: =D48+D53 -> 61195 | E54: =E48+E53 -> 45275.625
A56: Progress
B57: Lines in the list (active, this route) | C57: =COUNTIFS(BOM!$K$5:$K$247,"Y")-COUNTIFS(BOM!$K$5:$K$247,"Y",BOM!$T$5:$T$247,"<>",BOM!$T$5:$T$247,"<>"&$C$11) -> 212
B58: Lines with an actual price entered | C58: =COUNTIFS(BOM!$K$5:$K$247,"Y",BOM!$H$5:$H$247,"<>") -> 0
B59: Lines marked Have | C59: =COUNTIFS(BOM!$K$5:$K$247,"Y",BOM!$F$5:$F$247,"Y") -> 15
B60: Lines marked Make | C60: =COUNTIFS(BOM!$K$5:$K$247,"Y",BOM!$G$5:$G$247,"Y") -> 35
B61: Lines still 'To decide' | C61: =COUNTIFS(BOM!$K$5:$K$247,"Y",BOM!$J$5:$J$247,"To decide") -> 29
B63: Notes
B64: • Defaults: RX-8 gearbox route with the adapter plate, CSC adapter and spacers machined by you (material cost only); turbo Option B (custom manifold + Garrett G25); custom oil pan; A/C deleted; tools you can borrow are off; selling the FA20/TL70 is off.
B65: • Basis column: Verified = seen on the vendor page or a listing; Notes = from the Oct 4 planning notes; Estimate = rough street price — these are the ones to check.
B66: • HST (13%), labour, insurance, registration and safety are not included.
A68: CNC mill (CNC tab) — separate from the car build, NOT in ALL-IN above
B69: Group | C69: Low (CAD) | D69: High (CAD) | E69: WORKING (CAD)
B70: CNC mill parts (priced lines only) | C70: =SUM(CNC!$U$5:$U$50) -> 349.98 | D70: =SUM(CNC!$V$5:$V$50) -> 349.98 | E70: =SUM(CNC!$I$5:$I$50) -> 349.98
B71: of which: confirmed (actual price entered) | C71: =SUMIFS(CNC!$U$5:$U$50,CNC!$H$5:$H$50,"<>") -> 349.98 | D71: =SUMIFS(CNC!$V$5:$V$50,CNC!$H$5:$H$50,"<>") -> 349.98 | E71: =SUMIFS(CNC!$I$5:$I$50,CNC!$H$5:$H$50,"<>") -> 349.98
B72: of which: still estimated | C72: =C70-C71 -> 0 | D72: =D70-D71 -> 0 | E72: =E70-E71 -> 0
B73: Contingency (on the estimated part only) | C73: =C72*$C$10 -> 0 | D73: =D72*$C$10 -> 0 | E73: =E72*$C$10 -> 0
B74: CNC mill + contingency | C74: =C70+C73 -> 349.98 | D74: =D70+D73 -> 349.98 | E74: =E70+E73 -> 349.98
B76: Progress — CNC
B77: Lines in the list (included) | C77: =COUNTIFS(CNC!$K$5:$K$50,"Y") -> 42
B78: Lines with a real price entered | C78: =COUNTIFS(CNC!$K$5:$K$50,"Y",CNC!$H$5:$H$50,"<>") -> 3
B79: Lines marked Have | C79: =COUNTIFS(CNC!$K$5:$K$50,"Y",CNC!$F$5:$F$50,"Y") -> 2
B80: Lines with NO price yet (undecided) | C80: =COUNTIFS(CNC!$K$5:$K$50,"Y",CNC!$F$5:$F$50,"<>Y",CNC!$H$5:$H$50,"",CNC!$D$5:$D$50,"",CNC!$E$5:$E$50,"") -> 37
B81: Lines still 'To decide' | C81: =COUNTIFS(CNC!$K$5:$K$50,"Y",CNC!$J$5:$J$50,"To decide") -> 2
B83: • The CNC tab totals only lines that have a price. 'NO price yet' lines are the ones still to source; they add nothing to the totals until you fill D/E or H.

Sheet BOM
A1: 07K ZN6 Turbo Swap — Detailed BOM
A2: Fill the blue columns: Have? (Y = own it → $0), Make? (Y = you make it), MY cost (real price, CAD → overrides the estimate). Columns L–X (notes, vendor, phase, links) are hidden — click the + above column L to show them. Use the filter arrows to view one System at a time.
A4: ID | B4: Part | C4: Qty | D4: Est. low | E4: Est. high | F4: Have? | G4: Make? | H4: MY cost | I4: Working (CAD) | J4: Status | K4: Incl. | L4: System | M4: Sub-assembly | N4: Spec / notes | O4: Unit | P4: Cur | Q4: Source | R4: Vendor / ref | S4: Phase | T4: Route | U4: Ext low (CAD) | V4: Ext high (CAD) | W4: Basis | X4: Link
A5: D01 | B5: ZN6 FR-S / BRZ / 86, manual, RUNNING | C5: 1 | D5: 11500 | E5: 21000 | F5: N | G5: N | I5: =IF(AND($K5="Y",$F5<>"Y",OR($T5="",$T5=Summary!$C$11)),$C5*IF($H5<>"",$H5,($D5+$E5)/2)*INDEX(Summary!$C$6:$C$8,MATCH($P5,Summary!$B$6:$B$8,0)),0) -> 16250 | J5: Need | K5: Y | L5: Donors | M5: Car | N5: Must run so the stock CAN bus can be logged before the FA20 comes out. Clean shell > low km. | O5: ea | P5: CAD | Q5: Buy | R5: Kijiji / CarGurus | S5: 0 Donors | U5: =IF(AND($K5="Y",$F5<>"Y",OR($T5="",$T5=Summary!$C$11)),$C5*IF($H5<>"",$H5,$D5)*INDEX(Summary!$C$6:$C$8,MATCH($P5,Summary!$B$6:$B$8,0)),0) -> 11500 | V5: =IF(AND($K5="Y",$F5<>"Y",OR($T5="",$T5=Summary!$C$11)),$C5*IF($H5<>"",$H5,$E5)*INDEX(Summary!$C$6:$C$8,MATCH($P5,Summary!$B$6:$B$8,0)),0) -> 21000 | W5: Notes | X5: https://www.cargurus.ca/Cars/l-Used-Scion-FR-S-Toronto-d2140_L414276
A6: D02 | B6: 07K 2.5 engine, 2005–08 (ME7.1.1, MAF), with ECU + engine harness | C6: 1 | D6: 425 | E6: 1635 | F6: N | G6: N | I6: =IF(AND($K6="Y",$F6<>"Y",OR($T6="",$T6=Summary!$C$11)),$C6*IF($H6<>"",$H6,($D6+$E6)/2)*INDEX(Summary!$C$6:$C$8,MATCH($P6,Summary!$B$6:$B$8,0)),0) -> 1030 | J6: Need | K6: Y | L6: Donors | M6: Engine | N6: Confirm it comes with ECU, harness, coils, injectors, alternator, intake manifold, oil pan, flywheel-end cover. 6- vs 8-bolt crank flange. | O6: ea | P6: CAD | Q6: Buy | R6: eBay / junkyard / Marketplace | S6: 0 Donors | U6: =IF(AND($K6="Y",$F6<>"Y",OR($T6="",$T6=Summary!$C$11)),$C6*IF($H6<>"",$H6,$D6)*INDEX(Summary!$C$6:$C$8,MATCH($P6,Summary!$B$6:$B$8,0)),0) -> 425 | V6: =IF(AND($K6="Y",$F6<>"Y",OR($T6="",$T6=Summary!$C$11)),$C6*IF($H6<>"",$H6,$E6)*INDEX(Summary!$C$6:$C$8,MATCH($P6,Summary!$B$6:$B$8,0)),0) -> 1635 | W6: Notes | X6: https://www.ebay.com/itm/355614546913
A7: D03 | B7: Engine freight / pickup | C7: 1 | D7: 0 | E7: 400 | F7: N | G7: N | I7: =IF(AND($K7="Y",$F7<>"Y",OR($T7="",$T7=Summary!$C$11)),$C7*IF($H7<>"",$H7,($D7+$E7)/2)*INDEX(Summary!$C$6:$C$8,MATCH($P7,Summary!$B$6:$B$8,0)),0) -> 200 | J7: Need | K7: Y | L7: Donors | M7: Engine | N7: Pallet freight or a trailer trip. | O7: ea | P7: CAD | Q7: Buy | R7: — | S7: 0 Donors | U7: =IF(AND($K7="Y",$F7<>"Y",OR($T7="",$T7=Summary!$C$11)),$C7*IF($H7<>"",$H7,$D7)*INDEX(Summary!$C$6:$C$8,MATCH($P7,Summary!$B$6:$B$8,0)),0) -> 0 | V7: =IF(AND($K7="Y",$F7<>"Y",OR($T7="",$T7=Summary!$C$11)),$C7*IF($H7<>"",$H7,$E7)*INDEX(Summary!$C$6:$C$8,MATCH($P7,Summary!$B$6:$B$8,0)),0) -> 400 | W7: Estimate
A8: D04 | B8: Junk 02J bellhousing (VW 4-cyl pattern) | C8: 1 | D8: 70 | E8: 215 | F8: N | G8: N | I8: =IF(AND($K8="Y",$F8<>"Y",OR($T8="",$T8=Summary!$C$11)),$C8*IF($H8<>"",$H8,($D8+$E8)/2)*INDEX(Summary!$C$6:$C$8,MATCH($P8,Summary!$B$6:$B$8,0)),0) -> 142.5 | J8: Need | K8: Y | L8: Donors | M8: Measurement | N8: Only for measuring the 07K bolt/dowel pattern on the mill. Resell after. | O8: ea | P8: CAD | Q8: Buy | R8: Junkyard | S8: 0 Donors | U8: =IF(AND($K8="Y",$F8<>"Y",OR($T8="",$T8=Summary!$C$11)),$C8*IF($H8<>"",$H8,$D8)*INDEX(Summary!$C$6:$C$8,MATCH($P8,Summary!$B$6:$B$8,0)),0) -> 70 | V8: =IF(AND($K8="Y",$F8<>"Y",OR($T8="",$T8=Summary!$C$11)),$C8*IF($H8<>"",$H8,$E8)*INDEX(Summary!$C$6:$C$8,MATCH($P8,Summary!$B$6:$B$8,0)),0) -> 215 | W8: Estimate
A9: D05 | B9: Spare 07K cylinder head (scrap) — manifold welding fixture | C9: 1 | D9: 140 | E9: 425 | F9: N | G9: N | I9: =IF(AND($K9="Y",$F9<>"Y",OR($T9="",$T9=Summary!$C$11)),$C9*IF($H9<>"",$H9,($D9+$E9)/2)*INDEX(Summary!$C$6:$C$8,MATCH($P9,Summary!$B$6:$B$8,0)),0) -> 0 | J9: Optional | K9: N | L9: Donors | M9: Measurement | N9: Optional. A 1/2 in steel plate drilled to the port pattern also works. | O9: ea | P9: CAD | Q9: Buy | R9: Junkyard | S9: 0 Donors | U9: =IF(AND($K9="Y",$F9<>"Y",OR($T9="",$T9=Summary!$C$11)),$C9*IF($H9<>"",$H9,$D9)*INDEX(Summary!$C$6:$C$8,MATCH($P9,Summary!$B$6:$B$8,0)),0) -> 0 | V9: =IF(AND($K9="Y",$F9<>"Y",OR($T9="",$T9=Summary!$C$11)),$C9*IF($H9<>"",$H9,$E9)*INDEX(Summary!$C$6:$C$8,MATCH($P9,Summary!$B$6:$B$8,0)),0) -> 0 | W9: Estimate
A10: E01 | B10: Rear main seal (crank, flywheel end) | C10: 1 | D10: 30 | E10: 65 | F10: N | G10: N | I10: =IF(AND($K10="Y",$F10<>"Y",OR($T10="",$T10=Summary!$C$11)),$C10*IF($H10<>"",$H10,($D10+$E10)/2)*INDEX(Summary!$C$6:$C$8,MATCH($P10,Summary!$B$6:$B$8,0)),0) -> 47.5 | J10: Need | K10: Y | L10: Engine prep | M10: Seals | N10: Do it while the flywheel is off — it's behind the adapter plate forever after. | O10: ea | P10: CAD | Q10: Buy | R10: ECS / Das Parts | S10: 2 NA swap | U10: =IF(AND($K10="Y",$F10<>"Y",OR($T10="",$T10=Summary!$C$11)),$C10*IF($H10<>"",$H10,$D10)*INDEX(Summary!$C$6:$C$8,MATCH($P10,Summary!$B$6:$B$8,0)),0) -> 30 | V10: =IF(AND($K10="Y",$F10<>"Y",OR($T10="",$T10=Summary!$C$11)),$C10*IF($H10<>"",$H10,$E10)*INDEX(Summary!$C$6:$C$8,MATCH($P10,Summary!$B$6:$B$8,0)),0) -> 65 | W10: Estimate
A11: E02 | B11: Front crank seal | C11: 1 | D11: 14 | E11: 35 | F11: N | G11: N | I11: =IF(AND($K11="Y",$F11<>"Y",OR($T11="",$T11=Summary!$C$11)),$C11*IF($H11<>"",$H11,($D11+$E11)/2)*INDEX(Summary!$C$6:$C$8,MATCH($P11,Summary!$B$6:$B$8,0)),0) -> 24.5 | J11: Need | K11: Y | L11: Engine prep | M11: Seals | O11: ea | P11: CAD | Q11: Buy | R11: ECS / Das Parts | S11: 2 NA swap | U11: =IF(AND($K11="Y",$F11<>"Y",OR($T11="",$T11=Summary!$C$11)),$C11*IF($H11<>"",$H11,$D11)*INDEX(Summary!$C$6:$C$8,MATCH($P11,Summary!$B$6:$B$8,0)),0) -> 14 | V11: =IF(AND($K11="Y",$F11<>"Y",OR($T11="",$T11=Summary!$C$11)),$C11*IF($H11<>"",$H11,$E11)*INDEX(Summary!$C$6:$C$8,MATCH($P11,Summary!$B$6:$B$8,0)),0) -> 35 | W11: Estimate
A12: E03 | B12: Valve cover gasket | C12: 1 | D12: 35 | E12: 70 | F12: N | G12: N | I12: =IF(AND($K12="Y",$F12<>"Y",OR($T12="",$T12=Summary!$C$11)),$C12*IF($H12<>"",$H12,($D12+$E12)/2)*INDEX(Summary!$C$6:$C$8,MATCH($P12,Summary!$B$6:$B$8,0)),0) -> 52.5 | J12: Need | K12: Y | L12: Engine prep | M12: Seals | O12: ea | P12: CAD | Q12: Buy | R12: ECS / Das Parts | S12: 2 NA swap | U12: =IF(AND($K12="Y",$F12<>"Y",OR($T12="",$T12=Summary!$C$11)),$C12*IF($H12<>"",$H12,$D12)*INDEX(Summary!$C$6:$C$8,MATCH($P12,Summary!$B$6:$B$8,0)),0) -> 35 | V12: =IF(AND($K12="Y",$F12<>"Y",OR($T12="",$T12=Summary!$C$11)),$C12*IF($H12<>"",$H12,$E12)*INDEX(Summary!$C$6:$C$8,MATCH($P12,Summary!$B$6:$B$8,0)),0) -> 70 | W12: Estimate
A13: E04 | B13: Cam adjuster / cam plug seals | C13: 1 | D13: 20 | E13: 55 | F13: N | G13: N | I13: =IF(AND($K13="Y",$F13<>"Y",OR($T13="",$T13=Summary!$C$11)),$C13*IF($H13<>"",$H13,($D13+$E13)/2)*INDEX(Summary!$C$6:$C$8,MATCH($P13,Summary!$B$6:$B$8,0)),0) -> 37.5 | J13: Need | K13: Y | L13: Engine prep | M13: Seals | N13: Common 07K leak point. | O13: set | P13: CAD | Q13: Buy | R13: ECS / Das Parts | S13: 2 NA swap | U13: =IF(AND($K13="Y",$F13<>"Y",OR($T13="",$T13=Summary!$C$11)),$C13*IF($H13<>"",$H13,$D13)*INDEX(Summary!$C$6:$C$8,MATCH($P13,Summary!$B$6:$B$8,0)),0) -> 20 | V13: =IF(AND($K13="Y",$F13<>"Y",OR($T13="",$T13=Summary!$C$11)),$C13*IF($H13<>"",$H13,$E13)*INDEX(Summary!$C$6:$C$8,MATCH($P13,Summary!$B$6:$B$8,0)),0) -> 55 | W13: Estimate
A14: E05 | B14: Oil filter housing gasket / O-rings | C14: 1 | D14: 14 | E14: 35 | F14: N | G14: N | I14: =IF(AND($K14="Y",$F14<>"Y",OR($T14="",$T14=Summary!$C$11)),$C14*IF($H14<>"",$H14,($D14+$E14)/2)*INDEX(Summary!$C$6:$C$8,MATCH($P14,Summary!$B$6:$B$8,0)),0) -> 24.5 | J14: Need | K14: Y | L14: Engine prep | M14: Seals | O14: set | P14: CAD | Q14: Buy | R14: ECS / Das Parts | S14: 2 NA swap | U14: =IF(AND($K14="Y",$F14<>"Y",OR($T14="",$T14=Summary!$C$11)),$C14*IF($H14<>"",$H14,$D14)*INDEX(Summary!$C$6:$C$8,MATCH($P14,Summary!$B$6:$B$8,0)),0) -> 14 | V14: =IF(AND($K14="Y",$F14<>"Y",OR($T14="",$T14=Summary!$C$11)),$C14*IF($H14<>"",$H14,$E14)*INDEX(Summary!$C$6:$C$8,MATCH($P14,Summary!$B$6:$B$8,0)),0) -> 35 | W14: Estimate
A15: E06 | B15: Intake manifold gaskets (5) | C15: 1 | D15: 20 | E15: 50 | F15: N | G15: N | I15: =IF(AND($K15="Y",$F15<>"Y",OR($T15="",$T15=Summary!$C$11)),$C15*IF($H15<>"",$H15,($D15+$E15)/2)*INDEX(Summary!$C$6:$C$8,MATCH($P15,Summary!$B$6:$B$8,0)),0) -> 35 | J15: Need | K15: Y | L15: Engine prep | M15: Seals | O15: set | P15: CAD | Q15: Buy | R15: ECS / Das Parts | S15: 2 NA swap | U15: =IF(AND($K15="Y",$F15<>"Y",OR($T15="",$T15=Summary!$C$11)),$C15*IF($H15<>"",$H15,$D15)*INDEX(Summary!$C$6:$C$8,MATCH($P15,Summary!$B$6:$B$8,0)),0) -> 20 | V15: =IF(AND($K15="Y",$F15<>"Y",OR($T15="",$T15=Summary!$C$11)),$C15*IF($H15<>"",$H15,$E15)*INDEX(Summary!$C$6:$C$8,MATCH($P15,Summary!$B$6:$B$8,0)),0) -> 50 | W15: Estimate
A16: E07 | B16: Exhaust manifold gasket (OEM, for your custom flange) | C16: 1 | D16: 14 | E16: 35 | F16: N | G16: N | I16: =IF(AND($K16="Y",$F16<>"Y",OR($T16="",$T16=Summary!$C$11)),$C16*IF($H16<>"",$H16,($D16+$E16)/2)*INDEX(Summary!$C$6:$C$8,MATCH($P16,Summary!$B$6:$B$8,0)),0) -> 24.5 | J16: Need | K16: Y | L16: Engine prep | M16: Seals | O16: ea | P16: CAD | Q16: Buy | R16: ECS / Das Parts | S16: 3 Turbo | U16: =IF(AND($K16="Y",$F16<>"Y",OR($T16="",$T16=Summary!$C$11)),$C16*IF($H16<>"",$H16,$D16)*INDEX(Summary!$C$6:$C$8,MATCH($P16,Summary!$B$6:$B$8,0)),0) -> 14 | V16: =IF(AND($K16="Y",$F16<>"Y",OR($T16="",$T16=Summary!$C$11)),$C16*IF($H16<>"",$H16,$E16)*INDEX(Summary!$C$6:$C$8,MATCH($P16,Summary!$B$6:$B$8,0)),0) -> 35 | W16: Estimate
A17: E08 | B17: RTV sealant (oil pan, timing cover, upper pan) | C17: 2 | D17: 17 | E17: 35 | F17: N | G17: N | I17: =IF(AND($K17="Y",$F17<>"Y",OR($T17="",$T17=Summary!$C$11)),$C17*IF($H17<>"",$H17,($D17+$E17)/2)*INDEX(Summary!$C$6:$C$8,MATCH($P17,Summary!$B$6:$B$8,0)),0) -> 52 | J17: Need | K17: Y | L17: Engine prep | M17: Seals | N17: VW D176404A2 or Permatex Ultra Grey. 2 tubes. | O17: ea | P17: CAD | Q17: Buy | R17: Any | S17: 2 NA swap | U17: =IF(AND($K17="Y",$F17<>"Y",OR($T17="",$T17=Summary!$C$11)),$C17*IF($H17<>"",$H17,$D17)*INDEX(Summary!$C$6:$C$8,MATCH($P17,Summary!$B$6:$B$8,0)),0) -> 34 | V17: =IF(AND($K17="Y",$F17<>"Y",OR($T17="",$T17=Summary!$C$11)),$C17*IF($H17<>"",$H17,$E17)*INDEX(Summary!$C$6:$C$8,MATCH($P17,Summary!$B$6:$B$8,0)),0) -> 70 | W17: Estimate
A18: E09 | B18: Water pump | C18: 1 | D18: 85 | E18: 170 | F18: N | G18: N | I18: =IF(AND($K18="Y",$F18<>"Y",OR($T18="",$T18=Summary!$C$11)),$C18*IF($H18<>"",$H18,($D18+$E18)/2)*INDEX(Summary!$C$6:$C$8,MATCH($P18,Summary!$B$6:$B$8,0)),0) -> 127.5 | J18: Need | K18: Y | L18: Engine prep | M18: Cooling | O18: ea | P18: CAD | Q18: Buy | R18: ECS / Das Parts | S18: 2 NA swap | U18: =IF(AND($K18="Y",$F18<>"Y",OR($T18="",$T18=Summary!$C$11)),$C18*IF($H18<>"",$H18,$D18)*INDEX(Summary!$C$6:$C$8,MATCH($P18,Summary!$B$6:$B$8,0)),0) -> 85 | V18: =IF(AND($K18="Y",$F18<>"Y",OR($T18="",$T18=Summary!$C$11)),$C18*IF($H18<>"",$H18,$E18)*INDEX(Summary!$C$6:$C$8,MATCH($P18,Summary!$B$6:$B$8,0)),0) -> 170 | W18: Estimate
A19: E10 | B19: Thermostat + housing O-ring | C19: 1 | D19: 30 | E19: 65 | F19: N | G19: N | I19: =IF(AND($K19="Y",$F19<>"Y",OR($T19="",$T19=Summary!$C$11)),$C19*IF($H19<>"",$H19,($D19+$E19)/2)*INDEX(Summary!$C$6:$C$8,MATCH($P19,Summary!$B$6:$B$8,0)),0) -> 47.5 | J19: Need | K19: Y | L19: Engine prep | M19: Cooling | O19: ea | P19: CAD | Q19: Buy | R19: ECS / Das Parts | S19: 2 NA swap | U19: =IF(AND($K19="Y",$F19<>"Y",OR($T19="",$T19=Summary!$C$11)),$C19*IF($H19<>"",$H19,$D19)*INDEX(Summary!$C$6:$C$8,MATCH($P19,Summary!$B$6:$B$8,0)),0) -> 30 | V19: =IF(AND($K19="Y",$F19<>"Y",OR($T19="",$T19=Summary!$C$11)),$C19*IF($H19<>"",$H19,$E19)*INDEX(Summary!$C$6:$C$8,MATCH($P19,Summary!$B$6:$B$8,0)),0) -> 65 | W19: Estimate
A20: E11 | B20: Timing chain kit (chains, guides, tensioners) — inspect first | C20: 1 | D20: 0 | E20: 570 | F20: N | G20: N | I20: =IF(AND($K20="Y",$F20<>"Y",OR($T20="",$T20=Summary!$C$11)),$C20*IF($H20<>"",$H20,($D20+$E20)/2)*INDEX(Summary!$C$6:$C$8,MATCH($P20,Summary!$B$6:$B$8,0)),0) -> 285 | J20: To decide | K20: Y | L20: Engine prep | M20: Timing | N20: Chains are on the flywheel end; engine-out is the only time to do this. $0 if they look fine. | O20: kit | P20: CAD | Q20: Buy | R20: ECS / Das Parts | S20: 2 NA swap | U20: =IF(AND($K20="Y",$F20<>"Y",OR($T20="",$T20=Summary!$C$11)),$C20*IF($H20<>"",$H20,$D20)*INDEX(Summary!$C$6:$C$8,MATCH($P20,Summary!$B$6:$B$8,0)),0) -> 0 | V20: =IF(AND($K20="Y",$F20<>"Y",OR($T20="",$T20=Summary!$C$11)),$C20*IF($H20<>"",$H20,$E20)*INDEX(Summary!$C$6:$C$8,MATCH($P20,Summary!$B$6:$B$8,0)),0) -> 570 | W20: Estimate
A21: E12 | B21: Timing cover seal (crank side) + bolts | C21: 1 | D21: 14 | E21: 45 | F21: N | G21: N | I21: =IF(AND($K21="Y",$F21<>"Y",OR($T21="",$T21=Summary!$C$11)),$C21*IF($H21<>"",$H21,($D21+$E21)/2)*INDEX(Summary!$C$6:$C$8,MATCH($P21,Summary!$B$6:$B$8,0)),0) -> 29.5 | J21: Need | K21: Y | L21: Engine prep | M21: Timing | O21: set | P21: CAD | Q21: Buy | R21: ECS / Das Parts | S21: 2 NA swap | U21: =IF(AND($K21="Y",$F21<>"Y",OR($T21="",$T21=Summary!$C$11)),$C21*IF($H21<>"",$H21,$D21)*INDEX(Summary!$C$6:$C$8,MATCH($P21,Summary!$B$6:$B$8,0)),0) -> 14 | V21: =IF(AND($K21="Y",$F21<>"Y",OR($T21="",$T21=Summary!$C$11)),$C21*IF($H21<>"",$H21,$E21)*INDEX(Summary!$C$6:$C$8,MATCH($P21,Summary!$B$6:$B$8,0)),0) -> 45 | W21: Estimate
A22: E13 | B22: Oil filter (cartridge) | C22: 2 | D22: 11 | E22: 20 | F22: N | G22: N | I22: =IF(AND($K22="Y",$F22<>"Y",OR($T22="",$T22=Summary!$C$11)),$C22*IF($H22<>"",$H22,($D22+$E22)/2)*INDEX(Summary!$C$6:$C$8,MATCH($P22,Summary!$B$6:$B$8,0)),0) -> 31 | J22: Need | K22: Y | L22: Engine prep | M22: Service | N22: One for the first start, one for the 500 km change. | O22: ea | P22: CAD | Q22: Buy | R22: Any | S22: 2 NA swap | U22: =IF(AND($K22="Y",$F22<>"Y",OR($T22="",$T22=Summary!$C$11)),$C22*IF($H22<>"",$H22,$D22)*INDEX(Summary!$C$6:$C$8,MATCH($P22,Summary!$B$6:$B$8,0)),0) -> 22 | V22: =IF(AND($K22="Y",$F22<>"Y",OR($T22="",$T22=Summary!$C$11)),$C22*IF($H22<>"",$H22,$E22)*INDEX(Summary!$C$6:$C$8,MATCH($P22,Summary!$B$6:$B$8,0)),0) -> 40 | W22: Estimate
A23: E14 | B23: Engine oil 5W-40 (6 L) | C23: 2 | D23: 50 | E23: 85 | F23: N | G23: N | I23: =IF(AND($K23="Y",$F23<>"Y",OR($T23="",$T23=Summary!$C$11)),$C23*IF($H23<>"",$H23,($D23+$E23)/2)*INDEX(Summary!$C$6:$C$8,MATCH($P23,Summary!$B$6:$B$8,0)),0) -> 135 | J23: Need | K23: Y | L23: Engine prep | M23: Service | N23: Two fills: run stand + first change. | O23: fill | P23: CAD | Q23: Buy | R23: Any | S23: 1 Bench / run stand | U23: =IF(AND($K23="Y",$F23<>"Y",OR($T23="",$T23=Summary!$C$11)),$C23*IF($H23<>"",$H23,$D23)*INDEX(Summary!$C$6:$C$8,MATCH($P23,Summary!$B$6:$B$8,0)),0) -> 100 | V23: =IF(AND($K23="Y",$F23<>"Y",OR($T23="",$T23=Summary!$C$11)),$C23*IF($H23<>"",$H23,$E23)*INDEX(Summary!$C$6:$C$8,MATCH($P23,Summary!$B$6:$B$8,0)),0) -> 170 | W23: Estimate
A24: E15 | B24: Spark plugs (5), one step colder for turbo | C24: 5 | D24: 9 | E24: 17 | F24: N | G24: N | I24: =IF(AND($K24="Y",$F24<>"Y",OR($T24="",$T24=Summary!$C$11)),$C24*IF($H24<>"",$H24,($D24+$E24)/2)*INDEX(Summary!$C$6:$C$8,MATCH($P24,Summary!$B$6:$B$8,0)),0) -> 65 | J24: Need | K24: Y | L24: Engine prep | M24: Service | N24: NGK BKR7E-style for boost. | O24: ea | P24: CAD | Q24: Buy | R24: Any | S24: 2 NA swap | U24: =IF(AND($K24="Y",$F24<>"Y",OR($T24="",$T24=Summary!$C$11)),$C24*IF($H24<>"",$H24,$D24)*INDEX(Summary!$C$6:$C$8,MATCH($P24,Summary!$B$6:$B$8,0)),0) -> 45 | V24: =IF(AND($K24="Y",$F24<>"Y",OR($T24="",$T24=Summary!$C$11)),$C24*IF($H24<>"",$H24,$E24)*INDEX(Summary!$C$6:$C$8,MATCH($P24,Summary!$B$6:$B$8,0)),0) -> 85 | W24: Estimate
A25: E16 | B25: Ignition coils (5) | C25: 5 | D25: 30 | E25: 55 | F25: N | G25: N | I25: =IF(AND($K25="Y",$F25<>"Y",OR($T25="",$T25=Summary!$C$11)),$C25*IF($H25<>"",$H25,($D25+$E25)/2)*INDEX(Summary!$C$6:$C$8,MATCH($P25,Summary!$B$6:$B$8,0)),0) -> 212.5 | J25: To decide | K25: Y | L25: Engine prep | M25: Service | N25: Usually come with the engine. Set Have = Y if they do. | O25: ea | P25: CAD | Q25: Buy | R25: ECS / junkyard | S25: 2 NA swap | U25: =IF(AND($K25="Y",$F25<>"Y",OR($T25="",$T25=Summary!$C$11)),$C25*IF($H25<>"",$H25,$D25)*INDEX(Summary!$C$6:$C$8,MATCH($P25,Summary!$B$6:$B$8,0)),0) -> 150 | V25: =IF(AND($K25="Y",$F25<>"Y",OR($T25="",$T25=Summary!$C$11)),$C25*IF($H25<>"",$H25,$E25)*INDEX(Summary!$C$6:$C$8,MATCH($P25,Summary!$B$6:$B$8,0)),0) -> 275 | W25: Estimate
A26: E17 | B26: Serpentine belt + tensioner | C26: 1 | D26: 55 | E26: 140 | F26: N | G26: N | I26: =IF(AND($K26="Y",$F26<>"Y",OR($T26="",$T26=Summary!$C$11)),$C26*IF($H26<>"",$H26,($D26+$E26)/2)*INDEX(Summary!$C$6:$C$8,MATCH($P26,Summary!$B$6:$B$8,0)),0) -> 97.5 | J26: Need | K26: Y | L26: Engine prep | M26: Service | N26: Belt length changes if you delete A/C or move the alternator. | O26: set | P26: CAD | Q26: Buy | R26: ECS / Das Parts | S26: 2 NA swap | U26: =IF(AND($K26="Y",$F26<>"Y",OR($T26="",$T26=Summary!$C$11)),$C26*IF($H26<>"",$H26,$D26)*INDEX(Summary!$C$6:$C$8,MATCH($P26,Summary!$B$6:$B$8,0)),0) -> 55 | V26: =IF(AND($K26="Y",$F26<>"Y",OR($T26="",$T26=Summary!$C$11)),$C26*IF($H26<>"",$H26,$E26)*INDEX(Summary!$C$6:$C$8,MATCH($P26,Summary!$B$6:$B$8,0)),0) -> 140 | W26: Estimate
A27: E18 | B27: SAI (secondary air) block-off plates + gaskets | C27: 1 | D27: 30 | E27: 85 | F27: N | G27: N | I27: =IF(AND($K27="Y",$F27<>"Y",OR($T27="",$T27=Summary!$C$11)),$C27*IF($H27<>"",$H27,($D27+$E27)/2)*INDEX(Summary!$C$6:$C$8,MATCH($P27,Summary!$B$6:$B$8,0)),0) -> 57.5 | J27: Need | K27: Y | L27: Engine prep | M27: Deletes | N27: Software delete is in the RevMap file; plates seal the ports. | O27: set | P27: CAD | Q27: Buy | R27: Various | S27: 2 NA swap | U27: =IF(AND($K27="Y",$F27<>"Y",OR($T27="",$T27=Summary!$C$11)),$C27*IF($H27<>"",$H27,$D27)*INDEX(Summary!$C$6:$C$8,MATCH($P27,Summary!$B$6:$B$8,0)),0) -> 30 | V27: =IF(AND($K27="Y",$F27<>"Y",OR($T27="",$T27=Summary!$C$11)),$C27*IF($H27<>"",$H27,$E27)*INDEX(Summary!$C$6:$C$8,MATCH($P27,Summary!$B$6:$B$8,0)),0) -> 85 | W27: Estimate
A28: E19 | B28: Vacuum pump block-off — MAKE (6061 round bar 3 in × 2 in + O-ring) | C28: 1 | D28: 14 | E28: 35 | F28: N | G28: Y | I28: =IF(AND($K28="Y",$F28<>"Y",OR($T28="",$T28=Summary!$C$11)),$C28*IF($H28<>"",$H28,($D28+$E28)/2)*INDEX(Summary!$C$6:$C$8,MATCH($P28,Summary!$B$6:$B$8,0)),0) -> 0 | J28: Optional | K28: N | L28: Engine prep | M28: Deletes | N28: Flange + collar into the pump bore, O-ring sealed. Only if the pump hits the clutch setup. | O28: ea | P28: CAD | Q28: Make | R28: Metal supplier | S28: 2 NA swap | U28: =IF(AND($K28="Y",$F28<>"Y",OR($T28="",$T28=Summary!$C$11)),$C28*IF($H28<>"",$H28,$D28)*INDEX(Summary!$C$6:$C$8,MATCH($P28,Summary!$B$6:$B$8,0)),0) -> 0 | V28: =IF(AND($K28="Y",$F28<>"Y",OR($T28="",$T28=Summary!$C$11)),$C28*IF($H28<>"",$H28,$E28)*INDEX(Summary!$C$6:$C$8,MATCH($P28,Summary!$B$6:$B$8,0)),0) -> 0 | W28: Estimate | X28: https://performancebyie.com/products/ie-vacuum-pump-blockoff-vw-25l-5cyl
A29: E20 | B29: Vacuum pump O-ring (if keeping the pump) | C29: 1 | D29: 7 | E29: 14 | F29: N | G29: N | I29: =IF(AND($K29="Y",$F29<>"Y",OR($T29="",$T29=Summary!$C$11)),$C29*IF($H29<>"",$H29,($D29+$E29)/2)*INDEX(Summary!$C$6:$C$8,MATCH($P29,Summary!$B$6:$B$8,0)),0) -> 10.5 | J29: Need | K29: Y | L29: Engine prep | M29: Deletes | O29: ea | P29: CAD | Q29: Buy | R29: ECS | S29: 2 NA swap | U29: =IF(AND($K29="Y",$F29<>"Y",OR($T29="",$T29=Summary!$C$11)),$C29*IF($H29<>"",$H29,$D29)*INDEX(Summary!$C$6:$C$8,MATCH($P29,Summary!$B$6:$B$8,0)),0) -> 7 | V29: =IF(AND($K29="Y",$F29<>"Y",OR($T29="",$T29=Summary!$C$11)),$C29*IF($H29<>"",$H29,$E29)*INDEX(Summary!$C$6:$C$8,MATCH($P29,Summary!$B$6:$B$8,0)),0) -> 14 | W29: Estimate
A30: E21 | B30: Oil catch can + 2 hoses + fittings (PCV) | C30: 1 | D30: 55 | E30: 170 | F30: N | G30: N | I30: =IF(AND($K30="Y",$F30<>"Y",OR($T30="",$T30=Summary!$C$11)),$C30*IF($H30<>"",$H30,($D30+$E30)/2)*INDEX(Summary!$C$6:$C$8,MATCH($P30,Summary!$B$6:$B$8,0)),0) -> 112.5 | J30: Need | K30: Y | L30: Engine prep | M30: Breather | N30: Turbo engines push more blow-by; keep oil out of the intercooler. | O30: ea | P30: CAD | Q30: Buy | R30: Various | S30: 3 Turbo | U30: =IF(AND($K30="Y",$F30<>"Y",OR($T30="",$T30=Summary!$C$11)),$C30*IF($H30<>"",$H30,$D30)*INDEX(Summary!$C$6:$C$8,MATCH($P30,Summary!$B$6:$B$8,0)),0) -> 55 | V30: =IF(AND($K30="Y",$F30<>"Y",OR($T30="",$T30=Summary!$C$11)),$C30*IF($H30<>"",$H30,$E30)*INDEX(Summary!$C$6:$C$8,MATCH($P30,Summary!$B$6:$B$8,0)),0) -> 170 | W30: Estimate
A31: E22 | B31: Head gasket (MLS, OEM) | C31: 1 | D31: 85 | E31: 170 | F31: N | G31: N | I31: =IF(AND($K31="Y",$F31<>"Y",OR($T31="",$T31=Summary!$C$11)),$C31*IF($H31<>"",$H31,($D31+$E31)/2)*INDEX(Summary!$C$6:$C$8,MATCH($P31,Summary!$B$6:$B$8,0)),0) -> 127.5 | J31: Need | K31: Y | L31: Engine prep | M31: Head | N31: Turbo phase, or if the head comes off for inspection. | O31: ea | P31: CAD | Q31: Buy | R31: ECS / Das Parts | S31: 3 Turbo | U31: =IF(AND($K31="Y",$F31<>"Y",OR($T31="",$T31=Summary!$C$11)),$C31*IF($H31<>"",$H31,$D31)*INDEX(Summary!$C$6:$C$8,MATCH($P31,Summary!$B$6:$B$8,0)),0) -> 85 | V31: =IF(AND($K31="Y",$F31<>"Y",OR($T31="",$T31=Summary!$C$11)),$C31*IF($H31<>"",$H31,$E31)*INDEX(Summary!$C$6:$C$8,MATCH($P31,Summary!$B$6:$B$8,0)),0) -> 170 | W31: Estimate
A32: E23 | B32: ARP head studs, 07K | C32: 1 | D32: 255 | E32: 400 | F32: N | G32: N | I32: =IF(AND($K32="Y",$F32<>"Y",OR($T32="",$T32=Summary!$C$11)),$C32*IF($H32<>"",$H32,($D32+$E32)/2)*INDEX(Summary!$C$6:$C$8,MATCH($P32,Summary!$B$6:$B$8,0)),0) -> 327.5 | J32: Need | K32: Y | L32: Engine prep | M32: Head | O32: kit | P32: CAD | Q32: Buy | R32: ARP / 034 | S32: 3 Turbo | U32: =IF(AND($K32="Y",$F32<>"Y",OR($T32="",$T32=Summary!$C$11)),$C32*IF($H32<>"",$H32,$D32)*INDEX(Summary!$C$6:$C$8,MATCH($P32,Summary!$B$6:$B$8,0)),0) -> 255 | V32: =IF(AND($K32="Y",$F32<>"Y",OR($T32="",$T32=Summary!$C$11)),$C32*IF($H32<>"",$H32,$E32)*INDEX(Summary!$C$6:$C$8,MATCH($P32,Summary!$B$6:$B$8,0)),0) -> 400 | W32: Estimate
A33: E24 | B33: Head bolts (OEM TTY) — alternative to studs | C33: 1 | D33: 55 | E33: 100 | F33: N | G33: N | I33: =IF(AND($K33="Y",$F33<>"Y",OR($T33="",$T33=Summary!$C$11)),$C33*IF($H33<>"",$H33,($D33+$E33)/2)*INDEX(Summary!$C$6:$C$8,MATCH($P33,Summary!$B$6:$B$8,0)),0) -> 0 | J33: Option | K33: N | L33: Engine prep | M33: Head | N33: Pick E23 or E24. | O33: set | P33: CAD | Q33: Buy | R33: ECS | S33: 3 Turbo | U33: =IF(AND($K33="Y",$F33<>"Y",OR($T33="",$T33=Summary!$C$11)),$C33*IF($H33<>"",$H33,$D33)*INDEX(Summary!$C$6:$C$8,MATCH($P33,Summary!$B$6:$B$8,0)),0) -> 0 | V33: =IF(AND($K33="Y",$F33<>"Y",OR($T33="",$T33=Summary!$C$11)),$C33*IF($H33<>"",$H33,$E33)*INDEX(Summary!$C$6:$C$8,MATCH($P33,Summary!$B$6:$B$8,0)),0) -> 0 | W33: Estimate
A34: E25 | B34: Degreaser, brushes, engine paint | C34: 1 | D34: 30 | E34: 60 | F34: N | G34: N | I34: =IF(AND($K34="Y",$F34<>"Y",OR($T34="",$T34=Summary!$C$11)),$C34*IF($H34<>"",$H34,($D34+$E34)/2)*INDEX(Summary!$C$6:$C$8,MATCH($P34,Summary!$B$6:$B$8,0)),0) -> 45 | J34: Need | K34: Y | L34: Engine prep | M34: Clean | O34: lot | P34: CAD | Q34: Buy | R34: Canadian Tire | S34: 2 NA swap | U34: =IF(AND($K34="Y",$F34<>"Y",OR($T34="",$T34=Summary!$C$11)),$C34*IF($H34<>"",$H34,$D34)*INDEX(Summary!$C$6:$C$8,MATCH($P34,Summary!$B$6:$B$8,0)),0) -> 30 | V34: =IF(AND($K34="Y",$F34<>"Y",OR($T34="",$T34=Summary!$C$11)),$C34*IF($H34<>"",$H34,$E34)*INDEX(Summary!$C$6:$C$8,MATCH($P34,Summary!$B$6:$B$8,0)),0) -> 60 | W34: Estimate
A35: G01 | B35: Mazda RX-8 6-speed manual (Aisin AZ6), used | C35: 1 | D35: 605 | E35: 1415 | F35: N | G35: N | I35: =IF(AND($K35="Y",$F35<>"Y",OR($T35="",$T35=Summary!$C$11)),$C35*IF($H35<>"",$H35,($D35+$E35)/2)*INDEX(Summary!$C$6:$C$8,MATCH($P35,Summary!$B$6:$B$8,0)),0) -> 1010 | J35: Need | K35: Y | L35: Gearbox: RX-8 | M35: Gearbox | N35: S1 2004–08. Comes with its slave, release bearing, shifter, flange. Ask for the shifter and bolts. | O35: ea | P35: CAD | Q35: Buy | R35: eBay / JDM importer | S35: 2 NA swap | T35: RX-8 | U35: =IF(AND($K35="Y",$F35<>"Y",OR($T35="",$T35=Summary!$C$11)),$C35*IF($H35<>"",$H35,$D35)*INDEX(Summary!$C$6:$C$8,MATCH($P35,Summary!$B$6:$B$8,0)),0) -> 605 | V35: =IF(AND($K35="Y",$F35<>"Y",OR($T35="",$T35=Summary!$C$11)),$C35*IF($H35<>"",$H35,$E35)*INDEX(Summary!$C$6:$C$8,MATCH($P35,Summary!$B$6:$B$8,0)),0) -> 1415 | W35: Verified | X35: https://www.ebay.com/b/Complete-Manual-Transmissions-for-Mazda-RX-8/171117/bn_1435951
A36: G02 | B36: Gearbox freight | C36: 1 | D36: 215 | E36: 495 | F36: N | G36: N | I36: =IF(AND($K36="Y",$F36<>"Y",OR($T36="",$T36=Summary!$C$11)),$C36*IF($H36<>"",$H36,($D36+$E36)/2)*INDEX(Summary!$C$6:$C$8,MATCH($P36,Summary!$B$6:$B$8,0)),0) -> 355 | J36: Need | K36: Y | L36: Gearbox: RX-8 | M36: Gearbox | O36: ea | P36: CAD | Q36: Buy | R36: — | S36: 2 NA swap | T36: RX-8 | U36: =IF(AND($K36="Y",$F36<>"Y",OR($T36="",$T36=Summary!$C$11)),$C36*IF($H36<>"",$H36,$D36)*INDEX(Summary!$C$6:$C$8,MATCH($P36,Summary!$B$6:$B$8,0)),0) -> 215 | V36: =IF(AND($K36="Y",$F36<>"Y",OR($T36="",$T36=Summary!$C$11)),$C36*IF($H36<>"",$H36,$E36)*INDEX(Summary!$C$6:$C$8,MATCH($P36,Summary!$B$6:$B$8,0)),0) -> 495 | W36: Verified
A37: G03 | B37: Gear oil 75W-90 GL-4 (2 L) | C37: 1 | D37: 35 | E37: 70 | F37: N | G37: N | I37: =IF(AND($K37="Y",$F37<>"Y",OR($T37="",$T37=Summary!$C$11)),$C37*IF($H37<>"",$H37,($D37+$E37)/2)*INDEX(Summary!$C$6:$C$8,MATCH($P37,Summary!$B$6:$B$8,0)),0) -> 52.5 | J37: Need | K37: Y | L37: Gearbox: RX-8 | M37: Gearbox | O37: ea | P37: CAD | Q37: Buy | R37: Any | S37: 2 NA swap | T37: RX-8 | U37: =IF(AND($K37="Y",$F37<>"Y",OR($T37="",$T37=Summary!$C$11)),$C37*IF($H37<>"",$H37,$D37)*INDEX(Summary!$C$6:$C$8,MATCH($P37,Summary!$B$6:$B$8,0)),0) -> 35 | V37: =IF(AND($K37="Y",$F37<>"Y",OR($T37="",$T37=Summary!$C$11)),$C37*IF($H37<>"",$H37,$E37)*INDEX(Summary!$C$6:$C$8,MATCH($P37,Summary!$B$6:$B$8,0)),0) -> 70 | W37: Estimate
A38: G04 | B38: Shift knob + boot | C38: 1 | D38: 0 | E38: 55 | F38: N | G38: N | I38: =IF(AND($K38="Y",$F38<>"Y",OR($T38="",$T38=Summary!$C$11)),$C38*IF($H38<>"",$H38,($D38+$E38)/2)*INDEX(Summary!$C$6:$C$8,MATCH($P38,Summary!$B$6:$B$8,0)),0) -> 27.5 | J38: To decide | K38: Y | L38: Gearbox: RX-8 | M38: Gearbox | N38: Stock RX-8 knob is M10×1.25 — ZN6 knob fits? check. | O38: ea | P38: CAD | Q38: Buy | R38: — | S38: 2 NA swap | T38: RX-8 | U38: =IF(AND($K38="Y",$F38<>"Y",OR($T38="",$T38=Summary!$C$11)),$C38*IF($H38<>"",$H38,$D38)*INDEX(Summary!$C$6:$C$8,MATCH($P38,Summary!$B$6:$B$8,0)),0) -> 0 | V38: =IF(AND($K38="Y",$F38<>"Y",OR($T38="",$T38=Summary!$C$11)),$C38*IF($H38<>"",$H38,$E38)*INDEX(Summary!$C$6:$C$8,MATCH($P38,Summary!$B$6:$B$8,0)),0) -> 55 | W38: Estimate
A39: G05 | B39: MAKE: 6061-T6 plate blank, ~16 × 16 in × 1 in | C39: 1 | D39: 215 | E39: 425 | F39: N | G39: Y | I39: =IF(AND($K39="Y",$F39<>"Y",OR($T39="",$T39=Summary!$C$11)),$C39*IF($H39<>"",$H39,($D39+$E39)/2)*INDEX(Summary!$C$6:$C$8,MATCH($P39,Summary!$B$6:$B$8,0)),0) -> 320 | J39: Need | K39: Y | L39: Gearbox: RX-8 | M39: Adapter plate | N39: Thickness T comes from the stack-up (§13). 1 in blank, faced down. Metal Supermarkets Ottawa or online. | O39: ea | P39: CAD | Q39: Make | R39: Metal Supermarkets / OnlineMetals | S39: 2 NA swap | T39: RX-8 | U39: =IF(AND($K39="Y",$F39<>"Y",OR($T39="",$T39=Summary!$C$11)),$C39*IF($H39<>"",$H39,$D39)*INDEX(Summary!$C$6:$C$8,MATCH($P39,Summary!$B$6:$B$8,0)),0) -> 215 | V39: =IF(AND($K39="Y",$F39<>"Y",OR($T39="",$T39=Summary!$C$11)),$C39*IF($H39<>"",$H39,$E39)*INDEX(Summary!$C$6:$C$8,MATCH($P39,Summary!$B$6:$B$8,0)),0) -> 425 | W39: Estimate | X39: https://www.onlinemetals.com/en/buy/aluminum-sheet-plate-6061
A40: G06 | B40: Dowel pins, hardened — VW block side (2) | C40: 2 | D40: 6 | E40: 14 | F40: N | G40: N | I40: =IF(AND($K40="Y",$F40<>"Y",OR($T40="",$T40=Summary!$C$11)),$C40*IF($H40<>"",$H40,($D40+$E40)/2)*INDEX(Summary!$C$6:$C$8,MATCH($P40,Summary!$B$6:$B$8,0)),0) -> 20 | J40: Need | K40: Y | L40: Gearbox: RX-8 | M40: Adapter plate | N40: Match the 07K/02J dowel diameter (measure). | O40: ea | P40: CAD | Q40: Buy | R40: McMaster / Fastenal | S40: 2 NA swap | T40: RX-8 | U40: =IF(AND($K40="Y",$F40<>"Y",OR($T40="",$T40=Summary!$C$11)),$C40*IF($H40<>"",$H40,$D40)*INDEX(Summary!$C$6:$C$8,MATCH($P40,Summary!$B$6:$B$8,0)),0) -> 12 | V40: =IF(AND($K40="Y",$F40<>"Y",OR($T40="",$T40=Summary!$C$11)),$C40*IF($H40<>"",$H40,$E40)*INDEX(Summary!$C$6:$C$8,MATCH($P40,Summary!$B$6:$B$8,0)),0) -> 28 | W40: Estimate
A41: G07 | B41: Dowel pins, hardened — RX-8 bell side (2) | C41: 2 | D41: 6 | E41: 14 | F41: N | G41: N | I41: =IF(AND($K41="Y",$F41<>"Y",OR($T41="",$T41=Summary!$C$11)),$C41*IF($H41<>"",$H41,($D41+$E41)/2)*INDEX(Summary!$C$6:$C$8,MATCH($P41,Summary!$B$6:$B$8,0)),0) -> 20 | J41: Need | K41: Y | L41: Gearbox: RX-8 | M41: Adapter plate | N41: Match the RX-8 bellhousing dowel diameter (measure). | O41: ea | P41: CAD | Q41: Buy | R41: McMaster / Fastenal | S41: 2 NA swap | T41: RX-8 | U41: =IF(AND($K41="Y",$F41<>"Y",OR($T41="",$T41=Summary!$C$11)),$C41*IF($H41<>"",$H41,$D41)*INDEX(Summary!$C$6:$C$8,MATCH($P41,Summary!$B$6:$B$8,0)),0) -> 12 | V41: =IF(AND($K41="Y",$F41<>"Y",OR($T41="",$T41=Summary!$C$11)),$C41*IF($H41<>"",$H41,$E41)*INDEX(Summary!$C$6:$C$8,MATCH($P41,Summary!$B$6:$B$8,0)),0) -> 28 | W41: Estimate
A42: G08 | B42: Offset dowels (contingency, if runout > 0.005 in) | C42: 1 | D42: 0 | E42: 55 | F42: N | G42: N | I42: =IF(AND($K42="Y",$F42<>"Y",OR($T42="",$T42=Summary!$C$11)),$C42*IF($H42<>"",$H42,($D42+$E42)/2)*INDEX(Summary!$C$6:$C$8,MATCH($P42,Summary!$B$6:$B$8,0)),0) -> 27.5 | J42: Optional | K42: Y | L42: Gearbox: RX-8 | M42: Adapter plate | O42: set | P42: CAD | Q42: Buy | R42: Summit / RobbMc | S42: 2 NA swap | T42: RX-8 | U42: =IF(AND($K42="Y",$F42<>"Y",OR($T42="",$T42=Summary!$C$11)),$C42*IF($H42<>"",$H42,$D42)*INDEX(Summary!$C$6:$C$8,MATCH($P42,Summary!$B$6:$B$8,0)),0) -> 0 | V42: =IF(AND($K42="Y",$F42<>"Y",OR($T42="",$T42=Summary!$C$11)),$C42*IF($H42<>"",$H42,$E42)*INDEX(Summary!$C$6:$C$8,MATCH($P42,Summary!$B$6:$B$8,0)),0) -> 55 | W42: Estimate | X42: https://americanpowertrain.com/general-bellhousing-alignment-instructions/
A43: G09 | B43: Chucking reamer(s) for the dowel sizes | C43: 2 | D43: 0 | E43: 50 | F43: N | G43: N | I43: =IF(AND($K43="Y",$F43<>"Y",OR($T43="",$T43=Summary!$C$11)),$C43*IF($H43<>"",$H43,($D43+$E43)/2)*INDEX(Summary!$C$6:$C$8,MATCH($P43,Summary!$B$6:$B$8,0)),0) -> 50 | J43: To decide | K43: Y | L43: Gearbox: RX-8 | M43: Adapter plate | N43: Check if Brunsfield has them. $0 if so. | O43: ea | P43: CAD | Q43: Buy | R43: KBC / McMaster | S43: Tools | T43: RX-8 | U43: =IF(AND($K43="Y",$F43<>"Y",OR($T43="",$T43=Summary!$C$11)),$C43*IF($H43<>"",$H43,$D43)*INDEX(Summary!$C$6:$C$8,MATCH($P43,Summary!$B$6:$B$8,0)),0) -> 0 | V43: =IF(AND($K43="Y",$F43<>"Y",OR($T43="",$T43=Summary!$C$11)),$C43*IF($H43<>"",$H43,$E43)*INDEX(Summary!$C$6:$C$8,MATCH($P43,Summary!$B$6:$B$8,0)),0) -> 100 | W43: Estimate
A44: G10 | B44: Bolts block→plate: M10 or M12 10.9 socket cap, with washers (~8) | C44: 8 | D44: 3 | E44: 7 | F44: N | G44: N | I44: =IF(AND($K44="Y",$F44<>"Y",OR($T44="",$T44=Summary!$C$11)),$C44*IF($H44<>"",$H44,($D44+$E44)/2)*INDEX(Summary!$C$6:$C$8,MATCH($P44,Summary!$B$6:$B$8,0)),0) -> 40 | J44: Need | K44: Y | L44: Gearbox: RX-8 | M44: Adapter plate | N44: Lengths depend on T. | O44: ea | P44: CAD | Q44: Buy | R44: Fastenal / McMaster | S44: 2 NA swap | T44: RX-8 | U44: =IF(AND($K44="Y",$F44<>"Y",OR($T44="",$T44=Summary!$C$11)),$C44*IF($H44<>"",$H44,$D44)*INDEX(Summary!$C$6:$C$8,MATCH($P44,Summary!$B$6:$B$8,0)),0) -> 24 | V44: =IF(AND($K44="Y",$F44<>"Y",OR($T44="",$T44=Summary!$C$11)),$C44*IF($H44<>"",$H44,$E44)*INDEX(Summary!$C$6:$C$8,MATCH($P44,Summary!$B$6:$B$8,0)),0) -> 56 | W44: Estimate
A45: G11 | B45: Bolts bell→plate: M10 10.9 cap + nyloc nuts (~8) | C45: 8 | D45: 3 | E45: 7 | F45: N | G45: N | I45: =IF(AND($K45="Y",$F45<>"Y",OR($T45="",$T45=Summary!$C$11)),$C45*IF($H45<>"",$H45,($D45+$E45)/2)*INDEX(Summary!$C$6:$C$8,MATCH($P45,Summary!$B$6:$B$8,0)),0) -> 40 | J45: Need | K45: Y | L45: Gearbox: RX-8 | M45: Adapter plate | N45: Through-bolts with nuts avoid tapping the plate. | O45: ea | P45: CAD | Q45: Buy | R45: Fastenal / McMaster | S45: 2 NA swap | T45: RX-8 | U45: =IF(AND($K45="Y",$F45<>"Y",OR($T45="",$T45=Summary!$C$11)),$C45*IF($H45<>"",$H45,$D45)*INDEX(Summary!$C$6:$C$8,MATCH($P45,Summary!$B$6:$B$8,0)),0) -> 24 | V45: =IF(AND($K45="Y",$F45<>"Y",OR($T45="",$T45=Summary!$C$11)),$C45*IF($H45<>"",$H45,$E45)*INDEX(Summary!$C$6:$C$8,MATCH($P45,Summary!$B$6:$B$8,0)),0) -> 56 | W45: Estimate
A46: G12 | B46: Test plate: acrylic or MDF sheet for the CEED laser (24 × 18 in) | C46: 1 | D46: 15 | E46: 40 | F46: N | G46: Y | I46: =IF(AND($K46="Y",$F46<>"Y",OR($T46="",$T46=Summary!$C$11)),$C46*IF($H46<>"",$H46,($D46+$E46)/2)*INDEX(Summary!$C$6:$C$8,MATCH($P46,Summary!$B$6:$B$8,0)),0) -> 27.5 | J46: Need | K46: Y | L46: Gearbox: RX-8 | M46: Adapter plate | N46: Prove both bolt patterns and the starter position before cutting aluminium. | O46: ea | P46: CAD | Q46: Make | R46: CEED Makerstore | S46: 2 NA swap | T46: RX-8 | U46: =IF(AND($K46="Y",$F46<>"Y",OR($T46="",$T46=Summary!$C$11)),$C46*IF($H46<>"",$H46,$D46)*INDEX(Summary!$C$6:$C$8,MATCH($P46,Summary!$B$6:$B$8,0)),0) -> 15 | V46: =IF(AND($K46="Y",$F46<>"Y",OR($T46="",$T46=Summary!$C$11)),$C46*IF($H46<>"",$H46,$E46)*INDEX(Summary!$C$6:$C$8,MATCH($P46,Summary!$B$6:$B$8,0)),0) -> 40 | W46: Estimate
A47: G13 | B47: ALT: buy RX8 Gearbox Adapters plate RX8002 (upright) | C47: 1 | D47: 260 | E47: 260 | F47: N | G47: N | I47: =IF(AND($K47="Y",$F47<>"Y",OR($T47="",$T47=Summary!$C$11)),$C47*IF($H47<>"",$H47,($D47+$E47)/2)*INDEX(Summary!$C$6:$C$8,MATCH($P47,Summary!$B$6:$B$8,0)),0) -> 0 | J47: Option | K47: N | L47: Gearbox: RX-8 | M47: Adapter plate | N47: Proven on a 07K. Off because you're making your own. | O47: ea | P47: CAD | Q47: Buy | R47: RX8 Gearbox Adapters | S47: 2 NA swap | T47: RX-8 | U47: =IF(AND($K47="Y",$F47<>"Y",OR($T47="",$T47=Summary!$C$11)),$C47*IF($H47<>"",$H47,$D47)*INDEX(Summary!$C$6:$C$8,MATCH($P47,Summary!$B$6:$B$8,0)),0) -> 0 | V47: =IF(AND($K47="Y",$F47<>"Y",OR($T47="",$T47=Summary!$C$11)),$C47*IF($H47<>"",$H47,$E47)*INDEX(Summary!$C$6:$C$8,MATCH($P47,Summary!$B$6:$B$8,0)),0) -> 0 | W47: Verified | X47: https://www.rx8gearboxadapters.com/product-page/vw-pd-1-8t-20v-vertically-mounted
A48: G14 | B48: ALT: their bolt kit RX8027 | C48: 1 | D48: 65 | E48: 65 | F48: N | G48: N | I48: =IF(AND($K48="Y",$F48<>"Y",OR($T48="",$T48=Summary!$C$11)),$C48*IF($H48<>"",$H48,($D48+$E48)/2)*INDEX(Summary!$C$6:$C$8,MATCH($P48,Summary!$B$6:$B$8,0)),0) -> 0 | J48: Option | K48: N | L48: Gearbox: RX-8 | M48: Adapter plate | O48: ea | P48: CAD | Q48: Buy | R48: RX8 Gearbox Adapters | S48: 2 NA swap | T48: RX-8 | U48: =IF(AND($K48="Y",$F48<>"Y",OR($T48="",$T48=Summary!$C$11)),$C48*IF($H48<>"",$H48,$D48)*INDEX(Summary!$C$6:$C$8,MATCH($P48,Summary!$B$6:$B$8,0)),0) -> 0 | V48: =IF(AND($K48="Y",$F48<>"Y",OR($T48="",$T48=Summary!$C$11)),$C48*IF($H48<>"",$H48,$E48)*INDEX(Summary!$C$6:$C$8,MATCH($P48,Summary!$B$6:$B$8,0)),0) -> 0 | W48: Verified | X48: https://www.rx8gearboxadapters.com/product-page/vw-pd-1-8t-bolt-kit-rx8027
A49: G15 | B49: Valeo single-mass flywheel conversion kit, Audi B5/B6 A4 1.8T 5-spd (228 mm) | C49: 1 | D49: 570 | E49: 1030 | F49: N | G49: N | I49: =IF(AND($K49="Y",$F49<>"Y",OR($T49="",$T49=Summary!$C$11)),$C49*IF($H49<>"",$H49,($D49+$E49)/2)*INDEX(Summary!$C$6:$C$8,MATCH($P49,Summary!$B$6:$B$8,0)),0) -> 800 | J49: Need | K49: Y | L49: Gearbox: RX-8 | M49: Flywheel / clutch | N49: Flywheel + pressure plate + bolts. The kit's own disc has the Audi spline and is NOT used. 07K shares the 1.8T flywheel pattern. | O49: kit | P49: CAD | Q49: Buy | R49: ECS / Europa Parts | S49: 2 NA swap | T49: RX-8 | U49: =IF(AND($K49="Y",$F49<>"Y",OR($T49="",$T49=Summary!$C$11)),$C49*IF($H49<>"",$H49,$D49)*INDEX(Summary!$C$6:$C$8,MATCH($P49,Summary!$B$6:$B$8,0)),0) -> 570 | V49: =IF(AND($K49="Y",$F49<>"Y",OR($T49="",$T49=Summary!$C$11)),$C49*IF($H49<>"",$H49,$E49)*INDEX(Summary!$C$6:$C$8,MATCH($P49,Summary!$B$6:$B$8,0)),0) -> 1030 | W49: Verified | X49: https://www.ecstuning.com/b-ecs-parts/ra4-single-mass-flywheel-kit/ecs212321b5kt/
A50: G16 | B50: Flywheel-to-crank bolts (TTY, new) — if not in the kit | C50: 6 | D50: 4 | E50: 9 | F50: N | G50: N | I50: =IF(AND($K50="Y",$F50<>"Y",OR($T50="",$T50=Summary!$C$11)),$C50*IF($H50<>"",$H50,($D50+$E50)/2)*INDEX(Summary!$C$6:$C$8,MATCH($P50,Summary!$B$6:$B$8,0)),0) -> 39 | J50: To decide | K50: Y | L50: Gearbox: RX-8 | M50: Flywheel / clutch | O50: ea | P50: CAD | Q50: Buy | R50: ECS | S50: 2 NA swap | T50: RX-8 | U50: =IF(AND($K50="Y",$F50<>"Y",OR($T50="",$T50=Summary!$C$11)),$C50*IF($H50<>"",$H50,$D50)*INDEX(Summary!$C$6:$C$8,MATCH($P50,Summary!$B$6:$B$8,0)),0) -> 24 | V50: =IF(AND($K50="Y",$F50<>"Y",OR($T50="",$T50=Summary!$C$11)),$C50*IF($H50<>"",$H50,$E50)*INDEX(Summary!$C$6:$C$8,MATCH($P50,Summary!$B$6:$B$8,0)),0) -> 54 | W50: Estimate
A51: G17 | B51: Pressure plate bolts (if not in kit) | C51: 6 | D51: 1 | E51: 4 | F51: N | G51: N | I51: =IF(AND($K51="Y",$F51<>"Y",OR($T51="",$T51=Summary!$C$11)),$C51*IF($H51<>"",$H51,($D51+$E51)/2)*INDEX(Summary!$C$6:$C$8,MATCH($P51,Summary!$B$6:$B$8,0)),0) -> 15 | J51: To decide | K51: Y | L51: Gearbox: RX-8 | M51: Flywheel / clutch | O51: ea | P51: CAD | Q51: Buy | R51: ECS | S51: 2 NA swap | T51: RX-8 | U51: =IF(AND($K51="Y",$F51<>"Y",OR($T51="",$T51=Summary!$C$11)),$C51*IF($H51<>"",$H51,$D51)*INDEX(Summary!$C$6:$C$8,MATCH($P51,Summary!$B$6:$B$8,0)),0) -> 6 | V51: =IF(AND($K51="Y",$F51<>"Y",OR($T51="",$T51=Summary!$C$11)),$C51*IF($H51<>"",$H51,$E51)*INDEX(Summary!$C$6:$C$8,MATCH($P51,Summary!$B$6:$B$8,0)),0) -> 24 | W51: Estimate
A52: G18 | B52: Clutch disc 228 mm, 1 in × 23-spline (Ford spline), HD organic | C52: 1 | D52: 110 | E52: 280 | F52: N | G52: N | I52: =IF(AND($K52="Y",$F52<>"Y",OR($T52="",$T52=Summary!$C$11)),$C52*IF($H52<>"",$H52,($D52+$E52)/2)*INDEX(Summary!$C$6:$C$8,MATCH($P52,Summary!$B$6:$B$8,0)),0) -> 195 | J52: Need | K52: Y | L52: Gearbox: RX-8 | M52: Flywheel / clutch | N52: Fits the RX-8 input shaft. | O52: ea | P52: CAD | Q52: Buy | R52: QED Motorsport / Summit (Ford 23-spline) | S52: 2 NA swap | T52: RX-8 | U52: =IF(AND($K52="Y",$F52<>"Y",OR($T52="",$T52=Summary!$C$11)),$C52*IF($H52<>"",$H52,$D52)*INDEX(Summary!$C$6:$C$8,MATCH($P52,Summary!$B$6:$B$8,0)),0) -> 110 | V52: =IF(AND($K52="Y",$F52<>"Y",OR($T52="",$T52=Summary!$C$11)),$C52*IF($H52<>"",$H52,$E52)*INDEX(Summary!$C$6:$C$8,MATCH($P52,Summary!$B$6:$B$8,0)),0) -> 280 | W52: Estimate | X52: https://qedmotorsport.co.uk/product/clutch-plate-228mm-1-x-23-spline-ford-box-heavy-duty-organic-helix/
A53: G19 | B53: Spigot (pilot) bearing for the RX-8 input shaft nose | C53: 1 | D53: 18 | E53: 18 | F53: N | G53: N | I53: =IF(AND($K53="Y",$F53<>"Y",OR($T53="",$T53=Summary!$C$11)),$C53*IF($H53<>"",$H53,($D53+$E53)/2)*INDEX(Summary!$C$6:$C$8,MATCH($P53,Summary!$B$6:$B$8,0)),0) -> 18 | J53: Need | K53: Y | L53: Gearbox: RX-8 | M53: Flywheel / clutch | N53: RX8 Gearbox Adapters RX8017 (£10) or the same bearing by size locally. | O53: ea | P53: CAD | Q53: Buy | R53: RX8 Gearbox Adapters / bearing shop | S53: 2 NA swap | T53: RX-8 | U53: =IF(AND($K53="Y",$F53<>"Y",OR($T53="",$T53=Summary!$C$11)),$C53*IF($H53<>"",$H53,$D53)*INDEX(Summary!$C$6:$C$8,MATCH($P53,Summary!$B$6:$B$8,0)),0) -> 18 | V53: =IF(AND($K53="Y",$F53<>"Y",OR($T53="",$T53=Summary!$C$11)),$C53*IF($H53<>"",$H53,$E53)*INDEX(Summary!$C$6:$C$8,MATCH($P53,Summary!$B$6:$B$8,0)),0) -> 18 | W53: Verified | X53: https://www.rx8gearboxadapters.com/product-page/rx8-spigot-bearing-rx8017
A54: G20 | B54: Clutch alignment tool — 3D print (VW pilot dia / 23-spline) | C54: 1 | D54: 0 | E54: 5 | F54: N | G54: Y | I54: =IF(AND($K54="Y",$F54<>"Y",OR($T54="",$T54=Summary!$C$11)),$C54*IF($H54<>"",$H54,($D54+$E54)/2)*INDEX(Summary!$C$6:$C$8,MATCH($P54,Summary!$B$6:$B$8,0)),0) -> 2.5 | J54: Need | K54: Y | L54: Gearbox: RX-8 | M54: Flywheel / clutch | O54: ea | P54: CAD | Q54: Make | R54: X1C | S54: 2 NA swap | T54: RX-8 | U54: =IF(AND($K54="Y",$F54<>"Y",OR($T54="",$T54=Summary!$C$11)),$C54*IF($H54<>"",$H54,$D54)*INDEX(Summary!$C$6:$C$8,MATCH($P54,Summary!$B$6:$B$8,0)),0) -> 0 | V54: =IF(AND($K54="Y",$F54<>"Y",OR($T54="",$T54=Summary!$C$11)),$C54*IF($H54<>"",$H54,$E54)*INDEX(Summary!$C$6:$C$8,MATCH($P54,Summary!$B$6:$B$8,0)),0) -> 5 | W54: Estimate
A55: G21 | B55: Flywheel balance (shop) — optional | C55: 1 | D55: 0 | E55: 120 | F55: N | G55: N | I55: =IF(AND($K55="Y",$F55<>"Y",OR($T55="",$T55=Summary!$C$11)),$C55*IF($H55<>"",$H55,($D55+$E55)/2)*INDEX(Summary!$C$6:$C$8,MATCH($P55,Summary!$B$6:$B$8,0)),0) -> 0 | J55: Optional | K55: N | L55: Gearbox: RX-8 | M55: Flywheel / clutch | N55: Valeo kit is balanced; only if you machine the flywheel. | O55: ea | P55: CAD | Q55: Buy | R55: Balance shop | S55: 2 NA swap | T55: RX-8 | U55: =IF(AND($K55="Y",$F55<>"Y",OR($T55="",$T55=Summary!$C$11)),$C55*IF($H55<>"",$H55,$D55)*INDEX(Summary!$C$6:$C$8,MATCH($P55,Summary!$B$6:$B$8,0)),0) -> 0 | V55: =IF(AND($K55="Y",$F55<>"Y",OR($T55="",$T55=Summary!$C$11)),$C55*IF($H55<>"",$H55,$E55)*INDEX(Summary!$C$6:$C$8,MATCH($P55,Summary!$B$6:$B$8,0)),0) -> 0 | W55: Estimate
A56: G22 | B56: Starter: Audi A4 B6 1.9 TDI 5-spd manual (068911024F) | C56: 1 | D56: 75 | E56: 270 | F56: N | G56: N | I56: =IF(AND($K56="Y",$F56<>"Y",OR($T56="",$T56=Summary!$C$11)),$C56*IF($H56<>"",$H56,($D56+$E56)/2)*INDEX(Summary!$C$6:$C$8,MATCH($P56,Summary!$B$6:$B$8,0)),0) -> 172.5 | J56: Need | K56: Y | L56: Gearbox: RX-8 | M56: Starter | N56: Mounts on the adapter plate. Used → new aftermarket. | O56: ea | P56: CAD | Q56: Buy | R56: eBay / Autodoc / Rock Auto | S56: 2 NA swap | T56: RX-8 | U56: =IF(AND($K56="Y",$F56<>"Y",OR($T56="",$T56=Summary!$C$11)),$C56*IF($H56<>"",$H56,$D56)*INDEX(Summary!$C$6:$C$8,MATCH($P56,Summary!$B$6:$B$8,0)),0) -> 75 | V56: =IF(AND($K56="Y",$F56<>"Y",OR($T56="",$T56=Summary!$C$11)),$C56*IF($H56<>"",$H56,$E56)*INDEX(Summary!$C$6:$C$8,MATCH($P56,Summary!$B$6:$B$8,0)),0) -> 270 | W56: Verified | X56: https://www.ebay.co.uk/p/1509332173
A57: G23 | B57: Starter bolts (M10 10.9) + spacer if needed | C57: 2 | D57: 3 | E57: 7 | F57: N | G57: N | I57: =IF(AND($K57="Y",$F57<>"Y",OR($T57="",$T57=Summary!$C$11)),$C57*IF($H57<>"",$H57,($D57+$E57)/2)*INDEX(Summary!$C$6:$C$8,MATCH($P57,Summary!$B$6:$B$8,0)),0) -> 10 | J57: Need | K57: Y | L57: Gearbox: RX-8 | M57: Starter | O57: ea | P57: CAD | Q57: Buy | R57: Fastenal | S57: 2 NA swap | T57: RX-8 | U57: =IF(AND($K57="Y",$F57<>"Y",OR($T57="",$T57=Summary!$C$11)),$C57*IF($H57<>"",$H57,$D57)*INDEX(Summary!$C$6:$C$8,MATCH($P57,Summary!$B$6:$B$8,0)),0) -> 6 | V57: =IF(AND($K57="Y",$F57<>"Y",OR($T57="",$T57=Summary!$C$11)),$C57*IF($H57<>"",$H57,$E57)*INDEX(Summary!$C$6:$C$8,MATCH($P57,Summary!$B$6:$B$8,0)),0) -> 14 | W57: Estimate
A58: G24 | B58: Starter cable 2 AWG + lugs + solenoid trigger wire | C58: 1 | D58: 35 | E58: 85 | F58: N | G58: N | I58: =IF(AND($K58="Y",$F58<>"Y",OR($T58="",$T58=Summary!$C$11)),$C58*IF($H58<>"",$H58,($D58+$E58)/2)*INDEX(Summary!$C$6:$C$8,MATCH($P58,Summary!$B$6:$B$8,0)),0) -> 60 | J58: Need | K58: Y | L58: Gearbox: RX-8 | M58: Starter | N58: Battery is in the ZN6 bay; short run. | O58: lot | P58: CAD | Q58: Buy | R58: Any | S58: 2 NA swap | T58: RX-8 | U58: =IF(AND($K58="Y",$F58<>"Y",OR($T58="",$T58=Summary!$C$11)),$C58*IF($H58<>"",$H58,$D58)*INDEX(Summary!$C$6:$C$8,MATCH($P58,Summary!$B$6:$B$8,0)),0) -> 35 | V58: =IF(AND($K58="Y",$F58<>"Y",OR($T58="",$T58=Summary!$C$11)),$C58*IF($H58<>"",$H58,$E58)*INDEX(Summary!$C$6:$C$8,MATCH($P58,Summary!$B$6:$B$8,0)),0) -> 85 | W58: Estimate
A59: G25 | B59: Concentric slave cylinder (CSC) unit | C59: 1 | D59: 115 | E59: 655 | F59: N | G59: N | I59: =IF(AND($K59="Y",$F59<>"Y",OR($T59="",$T59=Summary!$C$11)),$C59*IF($H59<>"",$H59,($D59+$E59)/2)*INDEX(Summary!$C$6:$C$8,MATCH($P59,Summary!$B$6:$B$8,0)),0) -> 385 | J59: To decide | K59: Y | L59: Gearbox: RX-8 | M59: Clutch release | N59: Cheap OE-style CSC whose bore clears the RX-8 snout, or Tilton 6100/1000 universal (US$370–460). | O59: ea | P59: CAD | Q59: Buy | R59: Rock Auto / Tilton / Summit | S59: 2 NA swap | T59: RX-8 | U59: =IF(AND($K59="Y",$F59<>"Y",OR($T59="",$T59=Summary!$C$11)),$C59*IF($H59<>"",$H59,$D59)*INDEX(Summary!$C$6:$C$8,MATCH($P59,Summary!$B$6:$B$8,0)),0) -> 115 | V59: =IF(AND($K59="Y",$F59<>"Y",OR($T59="",$T59=Summary!$C$11)),$C59*IF($H59<>"",$H59,$E59)*INDEX(Summary!$C$6:$C$8,MATCH($P59,Summary!$B$6:$B$8,0)),0) -> 655 | W59: Estimate | X59: https://www.speedwaymotors.com/Tilton-60-6100-Flat-Face-Hydraulic-Release-Bearing-Universal,413901.html
A60: G26 | B60: MAKE: CSC mounting adapter — 6061 round bar 5 in × 2 in | C60: 1 | D60: 45 | E60: 85 | F60: N | G60: Y | I60: =IF(AND($K60="Y",$F60<>"Y",OR($T60="",$T60=Summary!$C$11)),$C60*IF($H60<>"",$H60,($D60+$E60)/2)*INDEX(Summary!$C$6:$C$8,MATCH($P60,Summary!$B$6:$B$8,0)),0) -> 65 | J60: Need | K60: Y | L60: Gearbox: RX-8 | M60: Clutch release | N60: Lathe: bore over the input snout + CSC seat in one chucking; mill the M8/M6 patterns. | O60: ea | P60: CAD | Q60: Make | R60: Metal Supermarkets | S60: 2 NA swap | T60: RX-8 | U60: =IF(AND($K60="Y",$F60<>"Y",OR($T60="",$T60=Summary!$C$11)),$C60*IF($H60<>"",$H60,$D60)*INDEX(Summary!$C$6:$C$8,MATCH($P60,Summary!$B$6:$B$8,0)),0) -> 45 | V60: =IF(AND($K60="Y",$F60<>"Y",OR($T60="",$T60=Summary!$C$11)),$C60*IF($H60<>"",$H60,$E60)*INDEX(Summary!$C$6:$C$8,MATCH($P60,Summary!$B$6:$B$8,0)),0) -> 85 | W60: Estimate
A61: G27 | B61: MAKE: CSC spacer shims — 6061 sheet 1 / 2 / 3 mm | C61: 1 | D61: 14 | E61: 35 | F61: N | G61: Y | I61: =IF(AND($K61="Y",$F61<>"Y",OR($T61="",$T61=Summary!$C$11)),$C61*IF($H61<>"",$H61,($D61+$E61)/2)*INDEX(Summary!$C$6:$C$8,MATCH($P61,Summary!$B$6:$B$8,0)),0) -> 24.5 | J61: Need | K61: Y | L61: Gearbox: RX-8 | M61: Clutch release | N61: Set bearing-to-finger gap. Measure, don't guess. | O61: lot | P61: CAD | Q61: Make | R61: Metal Supermarkets | S61: 2 NA swap | T61: RX-8 | U61: =IF(AND($K61="Y",$F61<>"Y",OR($T61="",$T61=Summary!$C$11)),$C61*IF($H61<>"",$H61,$D61)*INDEX(Summary!$C$6:$C$8,MATCH($P61,Summary!$B$6:$B$8,0)),0) -> 14 | V61: =IF(AND($K61="Y",$F61<>"Y",OR($T61="",$T61=Summary!$C$11)),$C61*IF($H61<>"",$H61,$E61)*INDEX(Summary!$C$6:$C$8,MATCH($P61,Summary!$B$6:$B$8,0)),0) -> 35 | W61: Estimate
A62: G28 | B62: ALT: RX8 Gearbox Adapters 6-spd CSC kit RX8032 (CSC + adapter + shims) | C62: 1 | D62: 425 | E62: 425 | F62: N | G62: N | I62: =IF(AND($K62="Y",$F62<>"Y",OR($T62="",$T62=Summary!$C$11)),$C62*IF($H62<>"",$H62,($D62+$E62)/2)*INDEX(Summary!$C$6:$C$8,MATCH($P62,Summary!$B$6:$B$8,0)),0) -> 0 | J62: Option | K62: N | L62: Gearbox: RX-8 | M62: Clutch release | N62: £230 for everything in G25–G27. Off because you're making it — but compare against your CSC price. | O62: ea | P62: CAD | Q62: Buy | R62: RX8 Gearbox Adapters | S62: 2 NA swap | T62: RX-8 | U62: =IF(AND($K62="Y",$F62<>"Y",OR($T62="",$T62=Summary!$C$11)),$C62*IF($H62<>"",$H62,$D62)*INDEX(Summary!$C$6:$C$8,MATCH($P62,Summary!$B$6:$B$8,0)),0) -> 0 | V62: =IF(AND($K62="Y",$F62<>"Y",OR($T62="",$T62=Summary!$C$11)),$C62*IF($H62<>"",$H62,$E62)*INDEX(Summary!$C$6:$C$8,MATCH($P62,Summary!$B$6:$B$8,0)),0) -> 0 | W62: Verified | X62: https://www.rx8gearboxadapters.com/product-page/rx8-6-speed-concentric-slave-cylinder-set-up
A63: G29 | B63: Clutch hydraulic line: -3 AN PTFE hose, 1.5 m | C63: 1 | D63: 35 | E63: 65 | F63: N | G63: N | I63: =IF(AND($K63="Y",$F63<>"Y",OR($T63="",$T63=Summary!$C$11)),$C63*IF($H63<>"",$H63,($D63+$E63)/2)*INDEX(Summary!$C$6:$C$8,MATCH($P63,Summary!$B$6:$B$8,0)),0) -> 50 | J63: Need | K63: Y | L63: Gearbox: RX-8 | M63: Clutch release | N63: CSC → ZN6 clutch master. | O63: ea | P63: CAD | Q63: Buy | R63: AN supplier | S63: 2 NA swap | T63: RX-8 | U63: =IF(AND($K63="Y",$F63<>"Y",OR($T63="",$T63=Summary!$C$11)),$C63*IF($H63<>"",$H63,$D63)*INDEX(Summary!$C$6:$C$8,MATCH($P63,Summary!$B$6:$B$8,0)),0) -> 35 | V63: =IF(AND($K63="Y",$F63<>"Y",OR($T63="",$T63=Summary!$C$11)),$C63*IF($H63<>"",$H63,$E63)*INDEX(Summary!$C$6:$C$8,MATCH($P63,Summary!$B$6:$B$8,0)),0) -> 65 | W63: Estimate
A64: G30 | B64: -3 AN hose ends (2) + adapter to the ZN6 master (M10×1.0 bubble flare → -3) | C64: 1 | D64: 30 | E64: 65 | F64: N | G64: N | I64: =IF(AND($K64="Y",$F64<>"Y",OR($T64="",$T64=Summary!$C$11)),$C64*IF($H64<>"",$H64,($D64+$E64)/2)*INDEX(Summary!$C$6:$C$8,MATCH($P64,Summary!$B$6:$B$8,0)),0) -> 47.5 | J64: Need | K64: Y | L64: Gearbox: RX-8 | M64: Clutch release | O64: set | P64: CAD | Q64: Buy | R64: AN supplier | S64: 2 NA swap | T64: RX-8 | U64: =IF(AND($K64="Y",$F64<>"Y",OR($T64="",$T64=Summary!$C$11)),$C64*IF($H64<>"",$H64,$D64)*INDEX(Summary!$C$6:$C$8,MATCH($P64,Summary!$B$6:$B$8,0)),0) -> 30 | V64: =IF(AND($K64="Y",$F64<>"Y",OR($T64="",$T64=Summary!$C$11)),$C64*IF($H64<>"",$H64,$E64)*INDEX(Summary!$C$6:$C$8,MATCH($P64,Summary!$B$6:$B$8,0)),0) -> 65 | W64: Estimate
A65: G31 | B65: Remote bleeder + bulkhead fitting | C65: 1 | D65: 20 | E65: 45 | F65: N | G65: N | I65: =IF(AND($K65="Y",$F65<>"Y",OR($T65="",$T65=Summary!$C$11)),$C65*IF($H65<>"",$H65,($D65+$E65)/2)*INDEX(Summary!$C$6:$C$8,MATCH($P65,Summary!$B$6:$B$8,0)),0) -> 32.5 | J65: Need | K65: Y | L65: Gearbox: RX-8 | M65: Clutch release | N65: CSC is inside the bell; bleed from outside. | O65: ea | P65: CAD | Q65: Buy | R65: AN supplier | S65: 2 NA swap | T65: RX-8 | U65: =IF(AND($K65="Y",$F65<>"Y",OR($T65="",$T65=Summary!$C$11)),$C65*IF($H65<>"",$H65,$D65)*INDEX(Summary!$C$6:$C$8,MATCH($P65,Summary!$B$6:$B$8,0)),0) -> 20 | V65: =IF(AND($K65="Y",$F65<>"Y",OR($T65="",$T65=Summary!$C$11)),$C65*IF($H65<>"",$H65,$E65)*INDEX(Summary!$C$6:$C$8,MATCH($P65,Summary!$B$6:$B$8,0)),0) -> 45 | W65: Estimate
A66: G32 | B66: Clutch master cylinder: ZN6 stock | C66: 1 | D66: 0 | E66: 0 | F66: Y | G66: N | I66: =IF(AND($K66="Y",$F66<>"Y",OR($T66="",$T66=Summary!$C$11)),$C66*IF($H66<>"",$H66,($D66+$E66)/2)*INDEX(Summary!$C$6:$C$8,MATCH($P66,Summary!$B$6:$B$8,0)),0) -> 0 | J66: Have | K66: Y | L66: Gearbox: RX-8 | M66: Clutch release | N66: Check throw vs CSC stroke; a 3/4 in master was needed on a similar swap. | O66: ea | P66: CAD | Q66: Have | R66: — | S66: 2 NA swap | T66: RX-8 | U66: =IF(AND($K66="Y",$F66<>"Y",OR($T66="",$T66=Summary!$C$11)),$C66*IF($H66<>"",$H66,$D66)*INDEX(Summary!$C$6:$C$8,MATCH($P66,Summary!$B$6:$B$8,0)),0) -> 0 | V66: =IF(AND($K66="Y",$F66<>"Y",OR($T66="",$T66=Summary!$C$11)),$C66*IF($H66<>"",$H66,$E66)*INDEX(Summary!$C$6:$C$8,MATCH($P66,Summary!$B$6:$B$8,0)),0) -> 0 | W66: Estimate
A67: G33 | B67: ALT: larger clutch master (Wilwood 3/4 in) if throw is short | C67: 1 | D67: 85 | E67: 155 | F67: N | G67: N | I67: =IF(AND($K67="Y",$F67<>"Y",OR($T67="",$T67=Summary!$C$11)),$C67*IF($H67<>"",$H67,($D67+$E67)/2)*INDEX(Summary!$C$6:$C$8,MATCH($P67,Summary!$B$6:$B$8,0)),0) -> 0 | J67: Option | K67: N | L67: Gearbox: RX-8 | M67: Clutch release | O67: ea | P67: CAD | Q67: Buy | R67: Wilwood | S67: 2 NA swap | T67: RX-8 | U67: =IF(AND($K67="Y",$F67<>"Y",OR($T67="",$T67=Summary!$C$11)),$C67*IF($H67<>"",$H67,$D67)*INDEX(Summary!$C$6:$C$8,MATCH($P67,Summary!$B$6:$B$8,0)),0) -> 0 | V67: =IF(AND($K67="Y",$F67<>"Y",OR($T67="",$T67=Summary!$C$11)),$C67*IF($H67<>"",$H67,$E67)*INDEX(Summary!$C$6:$C$8,MATCH($P67,Summary!$B$6:$B$8,0)),0) -> 0 | W67: Estimate
A68: G34 | B68: Dial indicator + magnetic base (bellhousing runout check) | C68: 1 | D68: 0 | E68: 60 | F68: N | G68: N | I68: =IF(AND($K68="Y",$F68<>"Y",OR($T68="",$T68=Summary!$C$11)),$C68*IF($H68<>"",$H68,($D68+$E68)/2)*INDEX(Summary!$C$6:$C$8,MATCH($P68,Summary!$B$6:$B$8,0)),0) -> 30 | J68: To decide | K68: Y | L68: Gearbox: RX-8 | M68: Measuring | N68: Brunsfield should have one → Have. | O68: ea | P68: CAD | Q68: Buy | R68: Princess Auto | S68: Tools | T68: RX-8 | U68: =IF(AND($K68="Y",$F68<>"Y",OR($T68="",$T68=Summary!$C$11)),$C68*IF($H68<>"",$H68,$D68)*INDEX(Summary!$C$6:$C$8,MATCH($P68,Summary!$B$6:$B$8,0)),0) -> 0 | V68: =IF(AND($K68="Y",$F68<>"Y",OR($T68="",$T68=Summary!$C$11)),$C68*IF($H68<>"",$H68,$E68)*INDEX(Summary!$C$6:$C$8,MATCH($P68,Summary!$B$6:$B$8,0)),0) -> 60 | W68: Estimate
A69: T01 | B69: Stock ZN6 TL70 6-speed | C69: 1 | D69: 0 | E69: 0 | F69: Y | G69: N | I69: =IF(AND($K69="Y",$F69<>"Y",OR($T69="",$T69=Summary!$C$11)),$C69*IF($H69<>"",$H69,($D69+$E69)/2)*INDEX(Summary!$C$6:$C$8,MATCH($P69,Summary!$B$6:$B$8,0)),0) -> 0 | J69: Have | K69: Y | L69: Gearbox: ZN6 TL70 | M69: Gearbox | N69: Comes with the car. | O69: ea | P69: CAD | Q69: Have | R69: — | S69: 2 NA swap | T69: ZN6 TL70 | U69: =IF(AND($K69="Y",$F69<>"Y",OR($T69="",$T69=Summary!$C$11)),$C69*IF($H69<>"",$H69,$D69)*INDEX(Summary!$C$6:$C$8,MATCH($P69,Summary!$B$6:$B$8,0)),0) -> 0 | V69: =IF(AND($K69="Y",$F69<>"Y",OR($T69="",$T69=Summary!$C$11)),$C69*IF($H69<>"",$H69,$E69)*INDEX(Summary!$C$6:$C$8,MATCH($P69,Summary!$B$6:$B$8,0)),0) -> 0 | W69: Notes
A70: T02 | B70: MAKE: 6061-T6 plate blank ~16 × 16 in × 1 in | C70: 1 | D70: 215 | E70: 425 | F70: N | G70: Y | I70: =IF(AND($K70="Y",$F70<>"Y",OR($T70="",$T70=Summary!$C$11)),$C70*IF($H70<>"",$H70,($D70+$E70)/2)*INDEX(Summary!$C$6:$C$8,MATCH($P70,Summary!$B$6:$B$8,0)),0) -> 0 | J70: Need | K70: Y | L70: Gearbox: ZN6 TL70 | M70: Adapter plate | N70: Same plate idea; TL70 bell pattern on the gearbox side (no CAD exists — measure). | O70: ea | P70: CAD | Q70: Make | R70: Metal Supermarkets | S70: 2 NA swap | T70: ZN6 TL70 | U70: =IF(AND($K70="Y",$F70<>"Y",OR($T70="",$T70=Summary!$C$11)),$C70*IF($H70<>"",$H70,$D70)*INDEX(Summary!$C$6:$C$8,MATCH($P70,Summary!$B$6:$B$8,0)),0) -> 0 | V70: =IF(AND($K70="Y",$F70<>"Y",OR($T70="",$T70=Summary!$C$11)),$C70*IF($H70<>"",$H70,$E70)*INDEX(Summary!$C$6:$C$8,MATCH($P70,Summary!$B$6:$B$8,0)),0) -> 0 | W70: Estimate
A71: T03 | B71: Dowels (4) + bolts/nuts (~16) + test plate | C71: 1 | D71: 85 | E71: 170 | F71: N | G71: N | I71: =IF(AND($K71="Y",$F71<>"Y",OR($T71="",$T71=Summary!$C$11)),$C71*IF($H71<>"",$H71,($D71+$E71)/2)*INDEX(Summary!$C$6:$C$8,MATCH($P71,Summary!$B$6:$B$8,0)),0) -> 0 | J71: Need | K71: Y | L71: Gearbox: ZN6 TL70 | M71: Adapter plate | O71: lot | P71: CAD | Q71: Buy | R71: McMaster / CEED | S71: 2 NA swap | T71: ZN6 TL70 | U71: =IF(AND($K71="Y",$F71<>"Y",OR($T71="",$T71=Summary!$C$11)),$C71*IF($H71<>"",$H71,$D71)*INDEX(Summary!$C$6:$C$8,MATCH($P71,Summary!$B$6:$B$8,0)),0) -> 0 | V71: =IF(AND($K71="Y",$F71<>"Y",OR($T71="",$T71=Summary!$C$11)),$C71*IF($H71<>"",$H71,$E71)*INDEX(Summary!$C$6:$C$8,MATCH($P71,Summary!$B$6:$B$8,0)),0) -> 0 | W71: Estimate
A72: T04 | B72: Flywheel: re-drill stock ZN6 flywheel to the 07K pattern + pilot pocket + balance | C72: 1 | D72: 150 | E72: 400 | F72: N | G72: N | I72: =IF(AND($K72="Y",$F72<>"Y",OR($T72="",$T72=Summary!$C$11)),$C72*IF($H72<>"",$H72,($D72+$E72)/2)*INDEX(Summary!$C$6:$C$8,MATCH($P72,Summary!$B$6:$B$8,0)),0) -> 0 | J72: Need | K72: Y | L72: Gearbox: ZN6 TL70 | M72: Flywheel / clutch | N72: Or an Audi SMF machined for the ZN6 clutch. Shop work. | O72: ea | P72: CAD | Q72: Buy | R72: Machine/balance shop | S72: 2 NA swap | T72: ZN6 TL70 | U72: =IF(AND($K72="Y",$F72<>"Y",OR($T72="",$T72=Summary!$C$11)),$C72*IF($H72<>"",$H72,$D72)*INDEX(Summary!$C$6:$C$8,MATCH($P72,Summary!$B$6:$B$8,0)),0) -> 0 | V72: =IF(AND($K72="Y",$F72<>"Y",OR($T72="",$T72=Summary!$C$11)),$C72*IF($H72<>"",$H72,$E72)*INDEX(Summary!$C$6:$C$8,MATCH($P72,Summary!$B$6:$B$8,0)),0) -> 0 | W72: Notes
A73: T05 | B73: ZN6 clutch kit (stock, comes with car) — upgrade later for 280 lb-ft | C73: 1 | D73: 0 | E73: 850 | F73: Y | G73: N | I73: =IF(AND($K73="Y",$F73<>"Y",OR($T73="",$T73=Summary!$C$11)),$C73*IF($H73<>"",$H73,($D73+$E73)/2)*INDEX(Summary!$C$6:$C$8,MATCH($P73,Summary!$B$6:$B$8,0)),0) -> 0 | J73: To decide | K73: Y | L73: Gearbox: ZN6 TL70 | M73: Flywheel / clutch | O73: ea | P73: CAD | Q73: Have | R73: — | S73: 2 NA swap | T73: ZN6 TL70 | U73: =IF(AND($K73="Y",$F73<>"Y",OR($T73="",$T73=Summary!$C$11)),$C73*IF($H73<>"",$H73,$D73)*INDEX(Summary!$C$6:$C$8,MATCH($P73,Summary!$B$6:$B$8,0)),0) -> 0 | V73: =IF(AND($K73="Y",$F73<>"Y",OR($T73="",$T73=Summary!$C$11)),$C73*IF($H73<>"",$H73,$E73)*INDEX(Summary!$C$6:$C$8,MATCH($P73,Summary!$B$6:$B$8,0)),0) -> 0 | W73: Notes
A74: T06 | B74: Pilot bearing for the TL70 input nose (in the custom flywheel) | C74: 1 | D74: 20 | E74: 55 | F74: N | G74: N | I74: =IF(AND($K74="Y",$F74<>"Y",OR($T74="",$T74=Summary!$C$11)),$C74*IF($H74<>"",$H74,($D74+$E74)/2)*INDEX(Summary!$C$6:$C$8,MATCH($P74,Summary!$B$6:$B$8,0)),0) -> 0 | J74: Need | K74: Y | L74: Gearbox: ZN6 TL70 | M74: Flywheel / clutch | O74: ea | P74: CAD | Q74: Buy | R74: Toyota/Subaru OEM | S74: 2 NA swap | T74: ZN6 TL70 | U74: =IF(AND($K74="Y",$F74<>"Y",OR($T74="",$T74=Summary!$C$11)),$C74*IF($H74<>"",$H74,$D74)*INDEX(Summary!$C$6:$C$8,MATCH($P74,Summary!$B$6:$B$8,0)),0) -> 0 | V74: =IF(AND($K74="Y",$F74<>"Y",OR($T74="",$T74=Summary!$C$11)),$C74*IF($H74<>"",$H74,$E74)*INDEX(Summary!$C$6:$C$8,MATCH($P74,Summary!$B$6:$B$8,0)),0) -> 0 | W74: Estimate
A75: T07 | B75: Starter: ZN6 stock (bolts to the TL70 bell) | C75: 1 | D75: 0 | E75: 0 | F75: Y | G75: N | I75: =IF(AND($K75="Y",$F75<>"Y",OR($T75="",$T75=Summary!$C$11)),$C75*IF($H75<>"",$H75,($D75+$E75)/2)*INDEX(Summary!$C$6:$C$8,MATCH($P75,Summary!$B$6:$B$8,0)),0) -> 0 | J75: Have | K75: Y | L75: Gearbox: ZN6 TL70 | M75: Starter | O75: ea | P75: CAD | Q75: Have | R75: — | S75: 2 NA swap | T75: ZN6 TL70 | U75: =IF(AND($K75="Y",$F75<>"Y",OR($T75="",$T75=Summary!$C$11)),$C75*IF($H75<>"",$H75,$D75)*INDEX(Summary!$C$6:$C$8,MATCH($P75,Summary!$B$6:$B$8,0)),0) -> 0 | V75: =IF(AND($K75="Y",$F75<>"Y",OR($T75="",$T75=Summary!$C$11)),$C75*IF($H75<>"",$H75,$E75)*INDEX(Summary!$C$6:$C$8,MATCH($P75,Summary!$B$6:$B$8,0)),0) -> 0 | W75: Estimate
A76: T08 | B76: ZN6 fork, slave, release bearing — stock | C76: 1 | D76: 0 | E76: 0 | F76: Y | G76: N | I76: =IF(AND($K76="Y",$F76<>"Y",OR($T76="",$T76=Summary!$C$11)),$C76*IF($H76<>"",$H76,($D76+$E76)/2)*INDEX(Summary!$C$6:$C$8,MATCH($P76,Summary!$B$6:$B$8,0)),0) -> 0 | J76: Have | K76: Y | L76: Gearbox: ZN6 TL70 | M76: Clutch release | O76: ea | P76: CAD | Q76: Have | R76: — | S76: 2 NA swap | T76: ZN6 TL70 | U76: =IF(AND($K76="Y",$F76<>"Y",OR($T76="",$T76=Summary!$C$11)),$C76*IF($H76<>"",$H76,$D76)*INDEX(Summary!$C$6:$C$8,MATCH($P76,Summary!$B$6:$B$8,0)),0) -> 0 | V76: =IF(AND($K76="Y",$F76<>"Y",OR($T76="",$T76=Summary!$C$11)),$C76*IF($H76<>"",$H76,$E76)*INDEX(Summary!$C$6:$C$8,MATCH($P76,Summary!$B$6:$B$8,0)),0) -> 0 | W76: Estimate
A77: L01 | B77: Custom one-piece driveshaft (shop): tube + 2 U-joints + yoke/flange to suit gearbox output + ZN6 diff flange, balanced | C77: 1 | D77: 710 | E77: 1280 | F77: N | G77: N | I77: =IF(AND($K77="Y",$F77<>"Y",OR($T77="",$T77=Summary!$C$11)),$C77*IF($H77<>"",$H77,($D77+$E77)/2)*INDEX(Summary!$C$6:$C$8,MATCH($P77,Summary!$B$6:$B$8,0)),0) -> 995 | J77: Need | K77: Y | L77: Driveline | M77: Driveshaft | N77: Do the length / critical-speed math; let the shop build it. | O77: ea | P77: CAD | Q77: Buy | R77: Driveshaft shop (Ottawa) | S77: 2 NA swap | U77: =IF(AND($K77="Y",$F77<>"Y",OR($T77="",$T77=Summary!$C$11)),$C77*IF($H77<>"",$H77,$D77)*INDEX(Summary!$C$6:$C$8,MATCH($P77,Summary!$B$6:$B$8,0)),0) -> 710 | V77: =IF(AND($K77="Y",$F77<>"Y",OR($T77="",$T77=Summary!$C$11)),$C77*IF($H77<>"",$H77,$E77)*INDEX(Summary!$C$6:$C$8,MATCH($P77,Summary!$B$6:$B$8,0)),0) -> 1280 | W77: Notes
A78: L02 | B78: Diff flange bolts (ZN6, new) | C78: 1 | D78: 14 | E78: 35 | F78: N | G78: N | I78: =IF(AND($K78="Y",$F78<>"Y",OR($T78="",$T78=Summary!$C$11)),$C78*IF($H78<>"",$H78,($D78+$E78)/2)*INDEX(Summary!$C$6:$C$8,MATCH($P78,Summary!$B$6:$B$8,0)),0) -> 24.5 | J78: Need | K78: Y | L78: Driveline | M78: Driveshaft | O78: set | P78: CAD | Q78: Buy | R78: Toyota/Subaru | S78: 2 NA swap | U78: =IF(AND($K78="Y",$F78<>"Y",OR($T78="",$T78=Summary!$C$11)),$C78*IF($H78<>"",$H78,$D78)*INDEX(Summary!$C$6:$C$8,MATCH($P78,Summary!$B$6:$B$8,0)),0) -> 14 | V78: =IF(AND($K78="Y",$F78<>"Y",OR($T78="",$T78=Summary!$C$11)),$C78*IF($H78<>"",$H78,$E78)*INDEX(Summary!$C$6:$C$8,MATCH($P78,Summary!$B$6:$B$8,0)),0) -> 35 | W78: Estimate
A79: L03 | B79: ZN6 Torsen diff + axles — stock | C79: 1 | D79: 0 | E79: 0 | F79: Y | G79: N | I79: =IF(AND($K79="Y",$F79<>"Y",OR($T79="",$T79=Summary!$C$11)),$C79*IF($H79<>"",$H79,($D79+$E79)/2)*INDEX(Summary!$C$6:$C$8,MATCH($P79,Summary!$B$6:$B$8,0)),0) -> 0 | J79: Have | K79: Y | L79: Driveline | M79: Differential | O79: ea | P79: CAD | Q79: Have | R79: — | S79: 2 NA swap | U79: =IF(AND($K79="Y",$F79<>"Y",OR($T79="",$T79=Summary!$C$11)),$C79*IF($H79<>"",$H79,$D79)*INDEX(Summary!$C$6:$C$8,MATCH($P79,Summary!$B$6:$B$8,0)),0) -> 0 | V79: =IF(AND($K79="Y",$F79<>"Y",OR($T79="",$T79=Summary!$C$11)),$C79*IF($H79<>"",$H79,$E79)*INDEX(Summary!$C$6:$C$8,MATCH($P79,Summary!$B$6:$B$8,0)),0) -> 0 | W79: Estimate
A80: L04 | B80: Driveshaft safety loop (track) | C80: 1 | D80: 55 | E80: 130 | F80: N | G80: N | I80: =IF(AND($K80="Y",$F80<>"Y",OR($T80="",$T80=Summary!$C$11)),$C80*IF($H80<>"",$H80,($D80+$E80)/2)*INDEX(Summary!$C$6:$C$8,MATCH($P80,Summary!$B$6:$B$8,0)),0) -> 0 | J80: Optional | K80: N | L80: Driveline | M80: Driveshaft | O80: ea | P80: CAD | Q80: Buy | R80: Various | S80: 3 Turbo | U80: =IF(AND($K80="Y",$F80<>"Y",OR($T80="",$T80=Summary!$C$11)),$C80*IF($H80<>"",$H80,$D80)*INDEX(Summary!$C$6:$C$8,MATCH($P80,Summary!$B$6:$B$8,0)),0) -> 0 | V80: =IF(AND($K80="Y",$F80<>"Y",OR($T80="",$T80=Summary!$C$11)),$C80*IF($H80<>"",$H80,$E80)*INDEX(Summary!$C$6:$C$8,MATCH($P80,Summary!$B$6:$B$8,0)),0) -> 0 | W80: Estimate
A81: M01 | B81: MAKE: steel plate 1/4 in + 3/16 in for mount brackets (2) | C81: 1 | D81: 40 | E81: 90 | F81: N | G81: Y | I81: =IF(AND($K81="Y",$F81<>"Y",OR($T81="",$T81=Summary!$C$11)),$C81*IF($H81<>"",$H81,($D81+$E81)/2)*INDEX(Summary!$C$6:$C$8,MATCH($P81,Summary!$B$6:$B$8,0)),0) -> 65 | J81: Need | K81: Y | L81: Mounts & chassis | M81: Engine mounts | N81: TIG weld at Brunsfield. | O81: lot | P81: CAD | Q81: Make | R81: Metal Supermarkets | S81: 2 NA swap | U81: =IF(AND($K81="Y",$F81<>"Y",OR($T81="",$T81=Summary!$C$11)),$C81*IF($H81<>"",$H81,$D81)*INDEX(Summary!$C$6:$C$8,MATCH($P81,Summary!$B$6:$B$8,0)),0) -> 40 | V81: =IF(AND($K81="Y",$F81<>"Y",OR($T81="",$T81=Summary!$C$11)),$C81*IF($H81<>"",$H81,$E81)*INDEX(Summary!$C$6:$C$8,MATCH($P81,Summary!$B$6:$B$8,0)),0) -> 90 | W81: Estimate
A82: M02 | B82: Rubber/poly isolators (2) — OEM-style or universal | C82: 2 | D82: 35 | E82: 85 | F82: N | G82: N | I82: =IF(AND($K82="Y",$F82<>"Y",OR($T82="",$T82=Summary!$C$11)),$C82*IF($H82<>"",$H82,($D82+$E82)/2)*INDEX(Summary!$C$6:$C$8,MATCH($P82,Summary!$B$6:$B$8,0)),0) -> 120 | J82: Need | K82: Y | L82: Mounts & chassis | M82: Engine mounts | N82: e.g. Energy Suspension universal or reuse 07K front mount bushings. | O82: ea | P82: CAD | Q82: Buy | R82: Summit / Energy Suspension | S82: 2 NA swap | U82: =IF(AND($K82="Y",$F82<>"Y",OR($T82="",$T82=Summary!$C$11)),$C82*IF($H82<>"",$H82,$D82)*INDEX(Summary!$C$6:$C$8,MATCH($P82,Summary!$B$6:$B$8,0)),0) -> 70 | V82: =IF(AND($K82="Y",$F82<>"Y",OR($T82="",$T82=Summary!$C$11)),$C82*IF($H82<>"",$H82,$E82)*INDEX(Summary!$C$6:$C$8,MATCH($P82,Summary!$B$6:$B$8,0)),0) -> 170 | W82: Estimate
A83: M03 | B83: Mount hardware: M10/M12 10.9 bolts, nyloc nuts, washers | C83: 1 | D83: 30 | E83: 55 | F83: N | G83: N | I83: =IF(AND($K83="Y",$F83<>"Y",OR($T83="",$T83=Summary!$C$11)),$C83*IF($H83<>"",$H83,($D83+$E83)/2)*INDEX(Summary!$C$6:$C$8,MATCH($P83,Summary!$B$6:$B$8,0)),0) -> 42.5 | J83: Need | K83: Y | L83: Mounts & chassis | M83: Engine mounts | O83: lot | P83: CAD | Q83: Buy | R83: Fastenal | S83: 2 NA swap | U83: =IF(AND($K83="Y",$F83<>"Y",OR($T83="",$T83=Summary!$C$11)),$C83*IF($H83<>"",$H83,$D83)*INDEX(Summary!$C$6:$C$8,MATCH($P83,Summary!$B$6:$B$8,0)),0) -> 30 | V83: =IF(AND($K83="Y",$F83<>"Y",OR($T83="",$T83=Summary!$C$11)),$C83*IF($H83<>"",$H83,$E83)*INDEX(Summary!$C$6:$C$8,MATCH($P83,Summary!$B$6:$B$8,0)),0) -> 55 | W83: Estimate
A84: M04 | B84: MAKE: trans crossmember — 1.5 in × 0.120 steel tube + 3/16 plate | C84: 1 | D84: 40 | E84: 80 | F84: N | G84: Y | I84: =IF(AND($K84="Y",$F84<>"Y",OR($T84="",$T84=Summary!$C$11)),$C84*IF($H84<>"",$H84,($D84+$E84)/2)*INDEX(Summary!$C$6:$C$8,MATCH($P84,Summary!$B$6:$B$8,0)),0) -> 60 | J84: Need | K84: Y | L84: Mounts & chassis | M84: Trans mount | O84: lot | P84: CAD | Q84: Make | R84: Metal Supermarkets | S84: 2 NA swap | U84: =IF(AND($K84="Y",$F84<>"Y",OR($T84="",$T84=Summary!$C$11)),$C84*IF($H84<>"",$H84,$D84)*INDEX(Summary!$C$6:$C$8,MATCH($P84,Summary!$B$6:$B$8,0)),0) -> 40 | V84: =IF(AND($K84="Y",$F84<>"Y",OR($T84="",$T84=Summary!$C$11)),$C84*IF($H84<>"",$H84,$E84)*INDEX(Summary!$C$6:$C$8,MATCH($P84,Summary!$B$6:$B$8,0)),0) -> 80 | W84: Estimate
A85: M05 | B85: Trans mount isolator (poly, universal) | C85: 1 | D85: 45 | E85: 100 | F85: N | G85: N | I85: =IF(AND($K85="Y",$F85<>"Y",OR($T85="",$T85=Summary!$C$11)),$C85*IF($H85<>"",$H85,($D85+$E85)/2)*INDEX(Summary!$C$6:$C$8,MATCH($P85,Summary!$B$6:$B$8,0)),0) -> 72.5 | J85: Need | K85: Y | L85: Mounts & chassis | M85: Trans mount | O85: ea | P85: CAD | Q85: Buy | R85: Energy Suspension / Vibra-Technics | S85: 2 NA swap | U85: =IF(AND($K85="Y",$F85<>"Y",OR($T85="",$T85=Summary!$C$11)),$C85*IF($H85<>"",$H85,$D85)*INDEX(Summary!$C$6:$C$8,MATCH($P85,Summary!$B$6:$B$8,0)),0) -> 45 | V85: =IF(AND($K85="Y",$F85<>"Y",OR($T85="",$T85=Summary!$C$11)),$C85*IF($H85<>"",$H85,$E85)*INDEX(Summary!$C$6:$C$8,MATCH($P85,Summary!$B$6:$B$8,0)),0) -> 100 | W85: Estimate
A86: M06 | B86: TIG filler ER70S-2 (1 lb) + argon | C86: 1 | D86: 20 | E86: 60 | F86: N | G86: N | I86: =IF(AND($K86="Y",$F86<>"Y",OR($T86="",$T86=Summary!$C$11)),$C86*IF($H86<>"",$H86,($D86+$E86)/2)*INDEX(Summary!$C$6:$C$8,MATCH($P86,Summary!$B$6:$B$8,0)),0) -> 40 | J86: To decide | K86: Y | L86: Mounts & chassis | M86: Welding | N86: Brunsfield may supply gas → set Have. | O86: lot | P86: CAD | Q86: Buy | R86: Praxair / Brunsfield | S86: 2 NA swap | U86: =IF(AND($K86="Y",$F86<>"Y",OR($T86="",$T86=Summary!$C$11)),$C86*IF($H86<>"",$H86,$D86)*INDEX(Summary!$C$6:$C$8,MATCH($P86,Summary!$B$6:$B$8,0)),0) -> 20 | V86: =IF(AND($K86="Y",$F86<>"Y",OR($T86="",$T86=Summary!$C$11)),$C86*IF($H86<>"",$H86,$E86)*INDEX(Summary!$C$6:$C$8,MATCH($P86,Summary!$B$6:$B$8,0)),0) -> 60 | W86: Estimate
A87: M07 | B87: Cutting discs, flap discs, drill bits | C87: 1 | D87: 30 | E87: 60 | F87: N | G87: N | I87: =IF(AND($K87="Y",$F87<>"Y",OR($T87="",$T87=Summary!$C$11)),$C87*IF($H87<>"",$H87,($D87+$E87)/2)*INDEX(Summary!$C$6:$C$8,MATCH($P87,Summary!$B$6:$B$8,0)),0) -> 45 | J87: Need | K87: Y | L87: Mounts & chassis | M87: Welding | O87: lot | P87: CAD | Q87: Buy | R87: Canadian Tire | S87: 2 NA swap | U87: =IF(AND($K87="Y",$F87<>"Y",OR($T87="",$T87=Summary!$C$11)),$C87*IF($H87<>"",$H87,$D87)*INDEX(Summary!$C$6:$C$8,MATCH($P87,Summary!$B$6:$B$8,0)),0) -> 30 | V87: =IF(AND($K87="Y",$F87<>"Y",OR($T87="",$T87=Summary!$C$11)),$C87*IF($H87<>"",$H87,$E87)*INDEX(Summary!$C$6:$C$8,MATCH($P87,Summary!$B$6:$B$8,0)),0) -> 60 | W87: Estimate
A88: M08 | B88: Tunnel / firewall clearance sheet metal (16 ga steel), if needed | C88: 1 | D88: 0 | E88: 60 | F88: N | G88: Y | I88: =IF(AND($K88="Y",$F88<>"Y",OR($T88="",$T88=Summary!$C$11)),$C88*IF($H88<>"",$H88,($D88+$E88)/2)*INDEX(Summary!$C$6:$C$8,MATCH($P88,Summary!$B$6:$B$8,0)),0) -> 30 | J88: To decide | K88: Y | L88: Mounts & chassis | M88: Tunnel | N88: Longer engine + RX-8 shifter position. $0 if it clears. | O88: lot | P88: CAD | Q88: Make | R88: Metal Supermarkets | S88: 2 NA swap | U88: =IF(AND($K88="Y",$F88<>"Y",OR($T88="",$T88=Summary!$C$11)),$C88*IF($H88<>"",$H88,$D88)*INDEX(Summary!$C$6:$C$8,MATCH($P88,Summary!$B$6:$B$8,0)),0) -> 0 | V88: =IF(AND($K88="Y",$F88<>"Y",OR($T88="",$T88=Summary!$C$11)),$C88*IF($H88<>"",$H88,$E88)*INDEX(Summary!$C$6:$C$8,MATCH($P88,Summary!$B$6:$B$8,0)),0) -> 60 | W88: Estimate
A89: M09 | B89: Shifter relocation / extension (RX-8 shifter vs ZN6 tunnel hole) | C89: 1 | D89: 0 | E89: 80 | F89: N | G89: Y | I89: =IF(AND($K89="Y",$F89<>"Y",OR($T89="",$T89=Summary!$C$11)),$C89*IF($H89<>"",$H89,($D89+$E89)/2)*INDEX(Summary!$C$6:$C$8,MATCH($P89,Summary!$B$6:$B$8,0)),0) -> 40 | J89: To decide | K89: Y | L89: Mounts & chassis | M89: Shifter | N89: MAKE a bracket or extension if the shifter lands wrong. | O89: ea | P89: CAD | Q89: Make | R89: — | S89: 2 NA swap | T89: RX-8 | U89: =IF(AND($K89="Y",$F89<>"Y",OR($T89="",$T89=Summary!$C$11)),$C89*IF($H89<>"",$H89,$D89)*INDEX(Summary!$C$6:$C$8,MATCH($P89,Summary!$B$6:$B$8,0)),0) -> 0 | V89: =IF(AND($K89="Y",$F89<>"Y",OR($T89="",$T89=Summary!$C$11)),$C89*IF($H89<>"",$H89,$E89)*INDEX(Summary!$C$6:$C$8,MATCH($P89,Summary!$B$6:$B$8,0)),0) -> 80 | W89: Estimate
A90: M10 | B90: Front subframe / steering rack clearance mods (notch + plate) | C90: 1 | D90: 0 | E90: 100 | F90: N | G90: Y | I90: =IF(AND($K90="Y",$F90<>"Y",OR($T90="",$T90=Summary!$C$11)),$C90*IF($H90<>"",$H90,($D90+$E90)/2)*INDEX(Summary!$C$6:$C$8,MATCH($P90,Summary!$B$6:$B$8,0)),0) -> 50 | J90: To decide | K90: Y | L90: Mounts & chassis | M90: Subframe | N90: Depends on the oil pan design. $0 if it clears. | O90: lot | P90: CAD | Q90: Make | R90: — | S90: 2 NA swap | U90: =IF(AND($K90="Y",$F90<>"Y",OR($T90="",$T90=Summary!$C$11)),$C90*IF($H90<>"",$H90,$D90)*INDEX(Summary!$C$6:$C$8,MATCH($P90,Summary!$B$6:$B$8,0)),0) -> 0 | V90: =IF(AND($K90="Y",$F90<>"Y",OR($T90="",$T90=Summary!$C$11)),$C90*IF($H90<>"",$H90,$E90)*INDEX(Summary!$C$6:$C$8,MATCH($P90,Summary!$B$6:$B$8,0)),0) -> 100 | W90: Estimate
A91: M11 | B91: Primer + chassis paint for fabricated parts | C91: 1 | D91: 20 | E91: 40 | F91: N | G91: N | I91: =IF(AND($K91="Y",$F91<>"Y",OR($T91="",$T91=Summary!$C$11)),$C91*IF($H91<>"",$H91,($D91+$E91)/2)*INDEX(Summary!$C$6:$C$8,MATCH($P91,Summary!$B$6:$B$8,0)),0) -> 30 | J91: Need | K91: Y | L91: Mounts & chassis | M91: Paint | O91: lot | P91: CAD | Q91: Buy | R91: Canadian Tire | S91: 2 NA swap | U91: =IF(AND($K91="Y",$F91<>"Y",OR($T91="",$T91=Summary!$C$11)),$C91*IF($H91<>"",$H91,$D91)*INDEX(Summary!$C$6:$C$8,MATCH($P91,Summary!$B$6:$B$8,0)),0) -> 20 | V91: =IF(AND($K91="Y",$F91<>"Y",OR($T91="",$T91=Summary!$C$11)),$C91*IF($H91<>"",$H91,$E91)*INDEX(Summary!$C$6:$C$8,MATCH($P91,Summary!$B$6:$B$8,0)),0) -> 40 | W91: Estimate
A92: U01 | B92: Garrett G25-550 (standard rotation; try clocking housings first) | C92: 1 | D92: 2415 | E92: 3265 | F92: N | G92: N | I92: =IF(AND($K92="Y",$F92<>"Y",OR($T92="",$T92=Summary!$C$11)),$C92*IF($H92<>"",$H92,($D92+$E92)/2)*INDEX(Summary!$C$6:$C$8,MATCH($P92,Summary!$B$6:$B$8,0)),0) -> 2840 | J92: Need | K92: Y | L92: Turbo | M92: Turbo — Option B | N92: Reverse-rotation version costs more and housings don't interchange. | O92: ea | P92: CAD | Q92: Buy | R92: Garrett dealer / ATP | S92: 3 Turbo | U92: =IF(AND($K92="Y",$F92<>"Y",OR($T92="",$T92=Summary!$C$11)),$C92*IF($H92<>"",$H92,$D92)*INDEX(Summary!$C$6:$C$8,MATCH($P92,Summary!$B$6:$B$8,0)),0) -> 2415 | V92: =IF(AND($K92="Y",$F92<>"Y",OR($T92="",$T92=Summary!$C$11)),$C92*IF($H92<>"",$H92,$E92)*INDEX(Summary!$C$6:$C$8,MATCH($P92,Summary!$B$6:$B$8,0)),0) -> 3265 | W92: Estimate | X92: https://www.garrettmotion.com/racing-and-performance/performance-turbos/
A93: U02 | B93: Turbine housing V-band inlet + outlet clamps/flanges | C93: 1 | D93: 85 | E93: 170 | F93: N | G93: N | I93: =IF(AND($K93="Y",$F93<>"Y",OR($T93="",$T93=Summary!$C$11)),$C93*IF($H93<>"",$H93,($D93+$E93)/2)*INDEX(Summary!$C$6:$C$8,MATCH($P93,Summary!$B$6:$B$8,0)),0) -> 127.5 | J93: Need | K93: Y | L93: Turbo | M93: Turbo — Option B | N93: G25 V-band housing: 2 clamps + 2 weld flanges. | O93: set | P93: CAD | Q93: Buy | R93: ATP / Vibrant | S93: 3 Turbo | U93: =IF(AND($K93="Y",$F93<>"Y",OR($T93="",$T93=Summary!$C$11)),$C93*IF($H93<>"",$H93,$D93)*INDEX(Summary!$C$6:$C$8,MATCH($P93,Summary!$B$6:$B$8,0)),0) -> 85 | V93: =IF(AND($K93="Y",$F93<>"Y",OR($T93="",$T93=Summary!$C$11)),$C93*IF($H93<>"",$H93,$E93)*INDEX(Summary!$C$6:$C$8,MATCH($P93,Summary!$B$6:$B$8,0)),0) -> 170 | W93: Estimate
A94: U03 | B94: Compressor inlet/outlet: hose adapter + V-band or silicone | C94: 1 | D94: 30 | E94: 85 | F94: N | G94: N | I94: =IF(AND($K94="Y",$F94<>"Y",OR($T94="",$T94=Summary!$C$11)),$C94*IF($H94<>"",$H94,($D94+$E94)/2)*INDEX(Summary!$C$6:$C$8,MATCH($P94,Summary!$B$6:$B$8,0)),0) -> 57.5 | J94: Need | K94: Y | L94: Turbo | M94: Turbo — Option B | O94: set | P94: CAD | Q94: Buy | R94: ATP / Vibrant | S94: 3 Turbo | U94: =IF(AND($K94="Y",$F94<>"Y",OR($T94="",$T94=Summary!$C$11)),$C94*IF($H94<>"",$H94,$D94)*INDEX(Summary!$C$6:$C$8,MATCH($P94,Summary!$B$6:$B$8,0)),0) -> 30 | V94: =IF(AND($K94="Y",$F94<>"Y",OR($T94="",$T94=Summary!$C$11)),$C94*IF($H94<>"",$H94,$E94)*INDEX(Summary!$C$6:$C$8,MATCH($P94,Summary!$B$6:$B$8,0)),0) -> 85 | W94: Estimate
A95: U04 | B95: ALT: Byiabed 07K → TT-RS turbo adapter plate | C95: 1 | D95: 640 | E95: 640 | F95: N | G95: N | I95: =IF(AND($K95="Y",$F95<>"Y",OR($T95="",$T95=Summary!$C$11)),$C95*IF($H95<>"",$H95,($D95+$E95)/2)*INDEX(Summary!$C$6:$C$8,MATCH($P95,Summary!$B$6:$B$8,0)),0) -> 0 | J95: Option | K95: N | L95: Turbo | M95: Turbo — Option A | N95: Option A: factory RS3/TT-RS turbo + manifold in one. Transverse layout — mock up first. | O95: ea | P95: CAD | Q95: Buy | R95: Byiabed | S95: 3 Turbo | U95: =IF(AND($K95="Y",$F95<>"Y",OR($T95="",$T95=Summary!$C$11)),$C95*IF($H95<>"",$H95,$D95)*INDEX(Summary!$C$6:$C$8,MATCH($P95,Summary!$B$6:$B$8,0)),0) -> 0 | V95: =IF(AND($K95="Y",$F95<>"Y",OR($T95="",$T95=Summary!$C$11)),$C95*IF($H95<>"",$H95,$E95)*INDEX(Summary!$C$6:$C$8,MATCH($P95,Summary!$B$6:$B$8,0)),0) -> 0 | W95: Notes | X95: https://byiabed.com/07K-25-Rabbit-to-TT-RS-Turbocharger-adapter-plate_p_143.html
A96: U05 | B96: ALT: used RS3 / TT-RS K16 turbo | C96: 1 | D96: 710 | E96: 1420 | F96: N | G96: N | I96: =IF(AND($K96="Y",$F96<>"Y",OR($T96="",$T96=Summary!$C$11)),$C96*IF($H96<>"",$H96,($D96+$E96)/2)*INDEX(Summary!$C$6:$C$8,MATCH($P96,Summary!$B$6:$B$8,0)),0) -> 0 | J96: Option | K96: N | L96: Turbo | M96: Turbo — Option A | O96: ea | P96: CAD | Q96: Buy | R96: Used | S96: 3 Turbo | U96: =IF(AND($K96="Y",$F96<>"Y",OR($T96="",$T96=Summary!$C$11)),$C96*IF($H96<>"",$H96,$D96)*INDEX(Summary!$C$6:$C$8,MATCH($P96,Summary!$B$6:$B$8,0)),0) -> 0 | V96: =IF(AND($K96="Y",$F96<>"Y",OR($T96="",$T96=Summary!$C$11)),$C96*IF($H96<>"",$H96,$E96)*INDEX(Summary!$C$6:$C$8,MATCH($P96,Summary!$B$6:$B$8,0)),0) -> 0 | W96: Estimate
A97: U06 | B97: MAKE: 07K header flange — 1/2 in 304 or mild steel, laser-cut from the CGTrader model | C97: 1 | D97: 55 | E97: 130 | F97: N | G97: Y | I97: =IF(AND($K97="Y",$F97<>"Y",OR($T97="",$T97=Summary!$C$11)),$C97*IF($H97<>"",$H97,($D97+$E97)/2)*INDEX(Summary!$C$6:$C$8,MATCH($P97,Summary!$B$6:$B$8,0)),0) -> 92.5 | J97: Need | K97: Y | L97: Turbo | M97: Manifold | N97: SendCutSend can cut 1/2 in steel; CEED can't. Or mill it at Brunsfield from plate. | O97: ea | P97: CAD | Q97: Make | R97: SendCutSend / Metal Supermarkets | S97: 3 Turbo | U97: =IF(AND($K97="Y",$F97<>"Y",OR($T97="",$T97=Summary!$C$11)),$C97*IF($H97<>"",$H97,$D97)*INDEX(Summary!$C$6:$C$8,MATCH($P97,Summary!$B$6:$B$8,0)),0) -> 55 | V97: =IF(AND($K97="Y",$F97<>"Y",OR($T97="",$T97=Summary!$C$11)),$C97*IF($H97<>"",$H97,$E97)*INDEX(Summary!$C$6:$C$8,MATCH($P97,Summary!$B$6:$B$8,0)),0) -> 130 | W97: Notes | X97: https://www.cgtrader.com/3d-print-models/hobby-diy/automotive/vw-07k-exhaust-header-flange-3d-model
A98: U07 | B98: 304 sch10 weld els 1.5 in (5× 90°, 5× 45°) | C98: 10 | D98: 11 | E98: 20 | F98: N | G98: N | I98: =IF(AND($K98="Y",$F98<>"Y",OR($T98="",$T98=Summary!$C$11)),$C98*IF($H98<>"",$H98,($D98+$E98)/2)*INDEX(Summary!$C$6:$C$8,MATCH($P98,Summary!$B$6:$B$8,0)),0) -> 155 | J98: Need | K98: Y | L98: Turbo | M98: Manifold | N98: 1.68 in ID matches the ported flange. | O98: ea | P98: CAD | Q98: Buy | R98: Vibrant / Ace Race Parts | S98: 3 Turbo | U98: =IF(AND($K98="Y",$F98<>"Y",OR($T98="",$T98=Summary!$C$11)),$C98*IF($H98<>"",$H98,$D98)*INDEX(Summary!$C$6:$C$8,MATCH($P98,Summary!$B$6:$B$8,0)),0) -> 110 | V98: =IF(AND($K98="Y",$F98<>"Y",OR($T98="",$T98=Summary!$C$11)),$C98*IF($H98<>"",$H98,$E98)*INDEX(Summary!$C$6:$C$8,MATCH($P98,Summary!$B$6:$B$8,0)),0) -> 200 | W98: Estimate
A99: U08 | B99: 304 straight tube 1.5 in sch10, 1 m | C99: 1 | D99: 35 | E99: 65 | F99: N | G99: N | I99: =IF(AND($K99="Y",$F99<>"Y",OR($T99="",$T99=Summary!$C$11)),$C99*IF($H99<>"",$H99,($D99+$E99)/2)*INDEX(Summary!$C$6:$C$8,MATCH($P99,Summary!$B$6:$B$8,0)),0) -> 50 | J99: Need | K99: Y | L99: Turbo | M99: Manifold | O99: ea | P99: CAD | Q99: Buy | R99: Vibrant / Ace Race Parts | S99: 3 Turbo | U99: =IF(AND($K99="Y",$F99<>"Y",OR($T99="",$T99=Summary!$C$11)),$C99*IF($H99<>"",$H99,$D99)*INDEX(Summary!$C$6:$C$8,MATCH($P99,Summary!$B$6:$B$8,0)),0) -> 35 | V99: =IF(AND($K99="Y",$F99<>"Y",OR($T99="",$T99=Summary!$C$11)),$C99*IF($H99<>"",$H99,$E99)*INDEX(Summary!$C$6:$C$8,MATCH($P99,Summary!$B$6:$B$8,0)),0) -> 65 | W99: Estimate
A100: U09 | B100: 5-into-1 merge collector (304) or MAKE | C100: 1 | D100: 55 | E100: 170 | F100: N | G100: N | I100: =IF(AND($K100="Y",$F100<>"Y",OR($T100="",$T100=Summary!$C$11)),$C100*IF($H100<>"",$H100,($D100+$E100)/2)*INDEX(Summary!$C$6:$C$8,MATCH($P100,Summary!$B$6:$B$8,0)),0) -> 112.5 | J100: To decide | K100: Y | L100: Turbo | M100: Manifold | O100: ea | P100: CAD | Q100: Buy | R100: Ace Race Parts / Burns | S100: 3 Turbo | U100: =IF(AND($K100="Y",$F100<>"Y",OR($T100="",$T100=Summary!$C$11)),$C100*IF($H100<>"",$H100,$D100)*INDEX(Summary!$C$6:$C$8,MATCH($P100,Summary!$B$6:$B$8,0)),0) -> 55 | V100: =IF(AND($K100="Y",$F100<>"Y",OR($T100="",$T100=Summary!$C$11)),$C100*IF($H100<>"",$H100,$E100)*INDEX(Summary!$C$6:$C$8,MATCH($P100,Summary!$B$6:$B$8,0)),0) -> 170 | W100: Estimate
A101: U10 | B101: Turbo inlet flange (T4 or V-band to suit G25 housing) | C101: 1 | D101: 30 | E101: 70 | F101: N | G101: N | I101: =IF(AND($K101="Y",$F101<>"Y",OR($T101="",$T101=Summary!$C$11)),$C101*IF($H101<>"",$H101,($D101+$E101)/2)*INDEX(Summary!$C$6:$C$8,MATCH($P101,Summary!$B$6:$B$8,0)),0) -> 50 | J101: Need | K101: Y | L101: Turbo | M101: Manifold | O101: ea | P101: CAD | Q101: Buy | R101: ATP / Vibrant | S101: 3 Turbo | U101: =IF(AND($K101="Y",$F101<>"Y",OR($T101="",$T101=Summary!$C$11)),$C101*IF($H101<>"",$H101,$D101)*INDEX(Summary!$C$6:$C$8,MATCH($P101,Summary!$B$6:$B$8,0)),0) -> 30 | V101: =IF(AND($K101="Y",$F101<>"Y",OR($T101="",$T101=Summary!$C$11)),$C101*IF($H101<>"",$H101,$E101)*INDEX(Summary!$C$6:$C$8,MATCH($P101,Summary!$B$6:$B$8,0)),0) -> 70 | W101: Estimate
...

Sheet CNC
A1: 07K ZN6 — CNC mill BOM (HTMCNC-style, 450 x 750 x 110 mm work area)
A2: Same rules as the BOM tab. Blue column H = your real price (CAD). Lines with NO price are undecided: fill D/E with an estimate or H with the real price once you pick a listing. Decided so far (Oct 4, 2026): motor/driver/supply kit (Amazon), extrusion (Amazon). Have: Arduino UNO, filament. Candidate AliExpress listings are in the Link column; prices for those are NOT entered on purpose.
A4: ID | B4: Part | C4: Qty | D4: Est. low | E4: Est. high | F4: Have? | G4: Make? | H4: MY cost | I4: Working (CAD) | J4: Status | K4: Incl. | L4: System | M4: Sub-assembly | N4: Spec / notes | O4: Unit | P4: Cur | Q4: Source | R4: Vendor / ref | S4: Phase | T4: Route | U4: Ext low (CAD) | V4: Ext high (CAD) | W4: Basis | X4: Link
A5: C01 | B5: 2040 T-slot extrusion, 1000 mm, black — VEVOR 5-pack | C5: 1 | F5: N | G5: N | H5: 57.99 | I5: =IF(AND($K5="Y",$F5<>"Y",OR($T5="",$T5=Summary!$C$11)),$C5*IF($H5<>"",$H5,($D5+$E5)/2)*INDEX(Summary!$C$6:$C$8,MATCH($P5,Summary!$B$6:$B$8,0)),0) -> 57.99 | J5: Need | K5: Y | L5: CNC: Frame | M5: Extrusion | N5: Cut plan: two bars → 700 + 200 + 100; three bars stay 600. Cut 2–3 mm long, file square. Decided Oct 4: Amazon. | O5: pack | P5: CAD | Q5: Buy | R5: Amazon B0F47W71ZD | S5: CNC build | U5: =IF(AND($K5="Y",$F5<>"Y",OR($T5="",$T5=Summary!$C$11)),$C5*IF($H5<>"",$H5,$D5)*INDEX(Summary!$C$6:$C$8,MATCH($P5,Summary!$B$6:$B$8,0)),0) -> 57.99 | V5: =IF(AND($K5="Y",$F5<>"Y",OR($T5="",$T5=Summary!$C$11)),$C5*IF($H5<>"",$H5,$E5)*INDEX(Summary!$C$6:$C$8,MATCH($P5,Summary!$B$6:$B$8,0)),0) -> 57.99 | W5: Verified | X5: https://www.amazon.ca/dp/B0F47W71ZD
A6: C02 | B6: 2080 T-slot extrusion, 1000 mm, silver — 2-pack (Y rails) | C6: 1 | F6: N | G6: N | H6: 106.99 | I6: =IF(AND($K6="Y",$F6<>"Y",OR($T6="",$T6=Summary!$C$11)),$C6*IF($H6<>"",$H6,($D6+$E6)/2)*INDEX(Summary!$C$6:$C$8,MATCH($P6,Summary!$B$6:$B$8,0)),0) -> 106.99 | J6: Need | K6: Y | L6: CNC: Frame | M6: Extrusion | N6: Check the variant selector is on 1000 mm silver before buying. Decided Oct 4: Amazon. Alt: Spool3D 2080 V-slot 1000 mm. | O6: pack | P6: CAD | Q6: Buy | R6: Amazon B09MWBZRGH | S6: CNC build | U6: =IF(AND($K6="Y",$F6<>"Y",OR($T6="",$T6=Summary!$C$11)),$C6*IF($H6<>"",$H6,$D6)*INDEX(Summary!$C$6:$C$8,MATCH($P6,Summary!$B$6:$B$8,0)),0) -> 106.99 | V6: =IF(AND($K6="Y",$F6<>"Y",OR($T6="",$T6=Summary!$C$11)),$C6*IF($H6<>"",$H6,$E6)*INDEX(Summary!$C$6:$C$8,MATCH($P6,Summary!$B$6:$B$8,0)),0) -> 106.99 | W6: Verified | X6: https://www.amazon.ca/dp/B09MWBZRGH
A7: C03 | B7: Corner bracket 28x20x28 (2028), with T-nuts + M5 bolts | C7: 18 | F7: N | G7: N | I7: =IF(AND($K7="Y",$F7<>"Y",OR($T7="",$T7=Summary!$C$11)),$C7*IF($H7<>"",$H7,($D7+$E7)/2)*INDEX(Summary!$C$6:$C$8,MATCH($P7,Summary!$B$6:$B$8,0)),0) -> 0 | J7: Need | K7: Y | L7: CNC: Frame | M7: Hardware | N7: Author's BOM: 18. Sold in 10-packs → buy 2 packs. | O7: ea | P7: CAD | Q7: Buy | R7: AliExpress 1005007660268625 | S7: CNC build | U7: =IF(AND($K7="Y",$F7<>"Y",OR($T7="",$T7=Summary!$C$11)),$C7*IF($H7<>"",$H7,$D7)*INDEX(Summary!$C$6:$C$8,MATCH($P7,Summary!$B$6:$B$8,0)),0) -> 0 | V7: =IF(AND($K7="Y",$F7<>"Y",OR($T7="",$T7=Summary!$C$11)),$C7*IF($H7<>"",$H7,$E7)*INDEX(Summary!$C$6:$C$8,MATCH($P7,Summary!$B$6:$B$8,0)),0) -> 0 | W7: Notes | X7: https://www.aliexpress.com/item/1005007660268625.html
A8: C04 | B8: Corner bracket 20x20x20, with T-nuts + M5 bolts | C8: 8 | F8: N | G8: N | I8: =IF(AND($K8="Y",$F8<>"Y",OR($T8="",$T8=Summary!$C$11)),$C8*IF($H8<>"",$H8,($D8+$E8)/2)*INDEX(Summary!$C$6:$C$8,MATCH($P8,Summary!$B$6:$B$8,0)),0) -> 0 | J8: Need | K8: Y | L8: CNC: Frame | M8: Hardware | N8: Author's BOM: 8. | O8: ea | P8: CAD | Q8: Buy | R8: AliExpress 1005002491882309 | S8: CNC build | U8: =IF(AND($K8="Y",$F8<>"Y",OR($T8="",$T8=Summary!$C$11)),$C8*IF($H8<>"",$H8,$D8)*INDEX(Summary!$C$6:$C$8,MATCH($P8,Summary!$B$6:$B$8,0)),0) -> 0 | V8: =IF(AND($K8="Y",$F8<>"Y",OR($T8="",$T8=Summary!$C$11)),$C8*IF($H8<>"",$H8,$E8)*INDEX(Summary!$C$6:$C$8,MATCH($P8,Summary!$B$6:$B$8,0)),0) -> 0 | W8: Notes | X8: https://www.aliexpress.com/item/1005002491882309.html
A9: C05 | B9: M5 sliding T-nut | C9: 100 | F9: N | G9: N | I9: =IF(AND($K9="Y",$F9<>"Y",OR($T9="",$T9=Summary!$C$11)),$C9*IF($H9<>"",$H9,($D9+$E9)/2)*INDEX(Summary!$C$6:$C$8,MATCH($P9,Summary!$B$6:$B$8,0)),0) -> 0 | J9: Need | K9: Y | L9: CNC: Frame | M9: Hardware | N9: 20-series, 6 mm slot. | O9: ea | P9: CAD | Q9: Buy | R9: AliExpress 1005007883028035 | S9: CNC build | U9: =IF(AND($K9="Y",$F9<>"Y",OR($T9="",$T9=Summary!$C$11)),$C9*IF($H9<>"",$H9,$D9)*INDEX(Summary!$C$6:$C$8,MATCH($P9,Summary!$B$6:$B$8,0)),0) -> 0 | V9: =IF(AND($K9="Y",$F9<>"Y",OR($T9="",$T9=Summary!$C$11)),$C9*IF($H9<>"",$H9,$E9)*INDEX(Summary!$C$6:$C$8,MATCH($P9,Summary!$B$6:$B$8,0)),0) -> 0 | W9: Notes | X9: https://www.aliexpress.com/item/1005007883028035.html
A10: C06 | B10: M5 hammer-head T-nut | C10: 100 | F10: N | G10: N | I10: =IF(AND($K10="Y",$F10<>"Y",OR($T10="",$T10=Summary!$C$11)),$C10*IF($H10<>"",$H10,($D10+$E10)/2)*INDEX(Summary!$C$6:$C$8,MATCH($P10,Summary!$B$6:$B$8,0)),0) -> 0 | J10: Need | K10: Y | L10: CNC: Frame | M10: Hardware | N10: Drop-in type for adding parts after assembly. | O10: ea | P10: CAD | Q10: Buy | R10: AliExpress 32814359094 | S10: CNC build | U10: =IF(AND($K10="Y",$F10<>"Y",OR($T10="",$T10=Summary!$C$11)),$C10*IF($H10<>"",$H10,$D10)*INDEX(Summary!$C$6:$C$8,MATCH($P10,Summary!$B$6:$B$8,0)),0) -> 0 | V10: =IF(AND($K10="Y",$F10<>"Y",OR($T10="",$T10=Summary!$C$11)),$C10*IF($H10<>"",$H10,$E10)*INDEX(Summary!$C$6:$C$8,MATCH($P10,Summary!$B$6:$B$8,0)),0) -> 0 | W10: Notes | X10: https://www.aliexpress.com/item/32814359094.html
A11: C07 | B11: M4 sliding T-nut | C11: 50 | F11: N | G11: N | I11: =IF(AND($K11="Y",$F11<>"Y",OR($T11="",$T11=Summary!$C$11)),$C11*IF($H11<>"",$H11,($D11+$E11)/2)*INDEX(Summary!$C$6:$C$8,MATCH($P11,Summary!$B$6:$B$8,0)),0) -> 0 | J11: Need | K11: Y | L11: CNC: Frame | M11: Hardware | O11: ea | P11: CAD | Q11: Buy | R11: AliExpress 1005007883028035 | S11: CNC build | U11: =IF(AND($K11="Y",$F11<>"Y",OR($T11="",$T11=Summary!$C$11)),$C11*IF($H11<>"",$H11,$D11)*INDEX(Summary!$C$6:$C$8,MATCH($P11,Summary!$B$6:$B$8,0)),0) -> 0 | V11: =IF(AND($K11="Y",$F11<>"Y",OR($T11="",$T11=Summary!$C$11)),$C11*IF($H11<>"",$H11,$E11)*INDEX(Summary!$C$6:$C$8,MATCH($P11,Summary!$B$6:$B$8,0)),0) -> 0 | W11: Notes | X11: https://www.aliexpress.com/item/1005007883028035.html
A12: C08 | B12: M4 hammer-head T-nut | C12: 50 | F12: N | G12: N | I12: =IF(AND($K12="Y",$F12<>"Y",OR($T12="",$T12=Summary!$C$11)),$C12*IF($H12<>"",$H12,($D12+$E12)/2)*INDEX(Summary!$C$6:$C$8,MATCH($P12,Summary!$B$6:$B$8,0)),0) -> 0 | J12: Need | K12: Y | L12: CNC: Frame | M12: Hardware | O12: ea | P12: CAD | Q12: Buy | R12: AliExpress 32814359094 | S12: CNC build | U12: =IF(AND($K12="Y",$F12<>"Y",OR($T12="",$T12=Summary!$C$11)),$C12*IF($H12<>"",$H12,$D12)*INDEX(Summary!$C$6:$C$8,MATCH($P12,Summary!$B$6:$B$8,0)),0) -> 0 | V12: =IF(AND($K12="Y",$F12<>"Y",OR($T12="",$T12=Summary!$C$11)),$C12*IF($H12<>"",$H12,$E12)*INDEX(Summary!$C$6:$C$8,MATCH($P12,Summary!$B$6:$B$8,0)),0) -> 0 | W12: Notes | X12: https://www.aliexpress.com/item/32814359094.html
A13: C09 | B13: Socket-head bolt kit (author's list) | C13: 1 | F13: N | G13: N | I13: =IF(AND($K13="Y",$F13<>"Y",OR($T13="",$T13=Summary!$C$11)),$C13*IF($H13<>"",$H13,($D13+$E13)/2)*INDEX(Summary!$C$6:$C$8,MATCH($P13,Summary!$B$6:$B$8,0)),0) -> 0 | J13: Need | K13: Y | L13: CNC: Frame | M13: Hardware | N13: M3x12 ×10, M3x16 ×5, M3x30 ×5, M4x10 ×5, M4x12 ×5, M4x14 ×60, M4x25 ×10, M5x12 ×50, M5x16 ×40, M5x20 ×40, M5x30 ×40, M5x50 ×25, M5x60 ×35, M5x70 ×5. Cheapest as an assorted M4/M5 kit. | O13: kit | P13: CAD | Q13: Buy | R13: Amazon / AliExpress | S13: CNC build | U13: =IF(AND($K13="Y",$F13<>"Y",OR($T13="",$T13=Summary!$C$11)),$C13*IF($H13<>"",$H13,$D13)*INDEX(Summary!$C$6:$C$8,MATCH($P13,Summary!$B$6:$B$8,0)),0) -> 0 | V13: =IF(AND($K13="Y",$F13<>"Y",OR($T13="",$T13=Summary!$C$11)),$C13*IF($H13<>"",$H13,$E13)*INDEX(Summary!$C$6:$C$8,MATCH($P13,Summary!$B$6:$B$8,0)),0) -> 0 | W13: Notes
A14: C10 | B14: HGR15 linear rail 1000 mm + 2 HGH15CA blocks (Y) | C14: 2 | F14: N | G14: N | I14: =IF(AND($K14="Y",$F14<>"Y",OR($T14="",$T14=Summary!$C$11)),$C14*IF($H14<>"",$H14,($D14+$E14)/2)*INDEX(Summary!$C$6:$C$8,MATCH($P14,Summary!$B$6:$B$8,0)),0) -> 0 | J14: Need | K14: Y | L14: CNC: Motion | M14: Linear rails | N14: Y scaled to 750 mm travel: 600 + 400. Buy as a 2-rail + 4-block set. | O14: ea | P14: CAD | Q14: Buy | R14: AliExpress 1005004825209262 | S14: CNC build | U14: =IF(AND($K14="Y",$F14<>"Y",OR($T14="",$T14=Summary!$C$11)),$C14*IF($H14<>"",$H14,$D14)*INDEX(Summary!$C$6:$C$8,MATCH($P14,Summary!$B$6:$B$8,0)),0) -> 0 | V14: =IF(AND($K14="Y",$F14<>"Y",OR($T14="",$T14=Summary!$C$11)),$C14*IF($H14<>"",$H14,$E14)*INDEX(Summary!$C$6:$C$8,MATCH($P14,Summary!$B$6:$B$8,0)),0) -> 0 | W14: Notes | X14: https://www.aliexpress.com/item/1005004825209262.html
A15: C11 | B15: HGR15 linear rail 600 mm + 2 HGH15CA blocks (X) | C15: 2 | F15: N | G15: N | I15: =IF(AND($K15="Y",$F15<>"Y",OR($T15="",$T15=Summary!$C$11)),$C15*IF($H15<>"",$H15,($D15+$E15)/2)*INDEX(Summary!$C$6:$C$8,MATCH($P15,Summary!$B$6:$B$8,0)),0) -> 0 | J15: Need | K15: Y | L15: CNC: Motion | M15: Linear rails | N15: Same listing, 600 mm option. | O15: ea | P15: CAD | Q15: Buy | R15: AliExpress 1005004825209262 | S15: CNC build | U15: =IF(AND($K15="Y",$F15<>"Y",OR($T15="",$T15=Summary!$C$11)),$C15*IF($H15<>"",$H15,$D15)*INDEX(Summary!$C$6:$C$8,MATCH($P15,Summary!$B$6:$B$8,0)),0) -> 0 | V15: =IF(AND($K15="Y",$F15<>"Y",OR($T15="",$T15=Summary!$C$11)),$C15*IF($H15<>"",$H15,$E15)*INDEX(Summary!$C$6:$C$8,MATCH($P15,Summary!$B$6:$B$8,0)),0) -> 0 | W15: Notes | X15: https://www.aliexpress.com/item/1005004825209262.html
A16: C12 | B16: HGR15 linear rail 300 mm + 2 HGH15CA blocks (Z) | C16: 2 | F16: N | G16: N | I16: =IF(AND($K16="Y",$F16<>"Y",OR($T16="",$T16=Summary!$C$11)),$C16*IF($H16<>"",$H16,($D16+$E16)/2)*INDEX(Summary!$C$6:$C$8,MATCH($P16,Summary!$B$6:$B$8,0)),0) -> 0 | J16: Need | K16: Y | L16: CNC: Motion | M16: Linear rails | N16: Same listing, 300 mm option; fixed-length alt 1005012673253692. | O16: ea | P16: CAD | Q16: Buy | R16: AliExpress 1005004825209262 | S16: CNC build | U16: =IF(AND($K16="Y",$F16<>"Y",OR($T16="",$T16=Summary!$C$11)),$C16*IF($H16<>"",$H16,$D16)*INDEX(Summary!$C$6:$C$8,MATCH($P16,Summary!$B$6:$B$8,0)),0) -> 0 | V16: =IF(AND($K16="Y",$F16<>"Y",OR($T16="",$T16=Summary!$C$11)),$C16*IF($H16<>"",$H16,$E16)*INDEX(Summary!$C$6:$C$8,MATCH($P16,Summary!$B$6:$B$8,0)),0) -> 0 | W16: Notes | X16: https://www.aliexpress.com/item/1005004825209262.html
A17: C13 | B17: SFU1605 ballscrew 900 mm, flange nut, ends machined (Y) | C17: 2 | F17: N | G17: N | I17: =IF(AND($K17="Y",$F17<>"Y",OR($T17="",$T17=Summary!$C$11)),$C17*IF($H17<>"",$H17,($D17+$E17)/2)*INDEX(Summary!$C$6:$C$8,MATCH($P17,Summary!$B$6:$B$8,0)),0) -> 0 | J17: Need | K17: Y | L17: CNC: Motion | M17: Ballscrews | N17: C7 rolled. Y = 500 + 400. Check critical speed for 900 mm (author's note). | O17: ea | P17: CAD | Q17: Buy | R17: AliExpress 1005007791178337 | S17: CNC build | U17: =IF(AND($K17="Y",$F17<>"Y",OR($T17="",$T17=Summary!$C$11)),$C17*IF($H17<>"",$H17,$D17)*INDEX(Summary!$C$6:$C$8,MATCH($P17,Summary!$B$6:$B$8,0)),0) -> 0 | V17: =IF(AND($K17="Y",$F17<>"Y",OR($T17="",$T17=Summary!$C$11)),$C17*IF($H17<>"",$H17,$E17)*INDEX(Summary!$C$6:$C$8,MATCH($P17,Summary!$B$6:$B$8,0)),0) -> 0 | W17: Notes | X17: https://www.aliexpress.com/item/1005007791178337.html
A18: C14 | B18: SFU1605 ballscrew 600 mm, flange nut, ends machined (X) | C18: 1 | F18: N | G18: N | I18: =IF(AND($K18="Y",$F18<>"Y",OR($T18="",$T18=Summary!$C$11)),$C18*IF($H18<>"",$H18,($D18+$E18)/2)*INDEX(Summary!$C$6:$C$8,MATCH($P18,Summary!$B$6:$B$8,0)),0) -> 0 | J18: Need | K18: Y | L18: CNC: Motion | M18: Ballscrews | O18: ea | P18: CAD | Q18: Buy | R18: AliExpress 1005007791178337 | S18: CNC build | U18: =IF(AND($K18="Y",$F18<>"Y",OR($T18="",$T18=Summary!$C$11)),$C18*IF($H18<>"",$H18,$D18)*INDEX(Summary!$C$6:$C$8,MATCH($P18,Summary!$B$6:$B$8,0)),0) -> 0 | V18: =IF(AND($K18="Y",$F18<>"Y",OR($T18="",$T18=Summary!$C$11)),$C18*IF($H18<>"",$H18,$E18)*INDEX(Summary!$C$6:$C$8,MATCH($P18,Summary!$B$6:$B$8,0)),0) -> 0 | W18: Notes | X18: https://www.aliexpress.com/item/1005007791178337.html
A19: C15 | B19: SFU1605 ballscrew 300 mm, flange nut, ends machined (Z) | C19: 1 | F19: N | G19: N | I19: =IF(AND($K19="Y",$F19<>"Y",OR($T19="",$T19=Summary!$C$11)),$C19*IF($H19<>"",$H19,($D19+$E19)/2)*INDEX(Summary!$C$6:$C$8,MATCH($P19,Summary!$B$6:$B$8,0)),0) -> 0 | J19: Need | K19: Y | L19: CNC: Motion | M19: Ballscrews | N19: Fixed-length listing with 105 orders. | O19: ea | P19: CAD | Q19: Buy | R19: AliExpress 32995243964 | S19: CNC build | U19: =IF(AND($K19="Y",$F19<>"Y",OR($T19="",$T19=Summary!$C$11)),$C19*IF($H19<>"",$H19,$D19)*INDEX(Summary!$C$6:$C$8,MATCH($P19,Summary!$B$6:$B$8,0)),0) -> 0 | V19: =IF(AND($K19="Y",$F19<>"Y",OR($T19="",$T19=Summary!$C$11)),$C19*IF($H19<>"",$H19,$E19)*INDEX(Summary!$C$6:$C$8,MATCH($P19,Summary!$B$6:$B$8,0)),0) -> 0 | W19: Notes | X19: https://www.aliexpress.com/item/32995243964.html
A20: C16 | B20: 7001 angular contact bearing, P5, DB pair (12x28x8) | C20: 4 | F20: N | G20: N | I20: =IF(AND($K20="Y",$F20<>"Y",OR($T20="",$T20=Summary!$C$11)),$C20*IF($H20<>"",$H20,($D20+$E20)/2)*INDEX(Summary!$C$6:$C$8,MATCH($P20,Summary!$B$6:$B$8,0)),0) -> 0 | J20: Need | K20: Y | L20: CNC: Motion | M20: Bearing blocks | N20: One pair per printed ballscrew bearing block. | O20: pair | P20: CAD | Q20: Buy | R20: AliExpress 32794645480 | S20: CNC build | U20: =IF(AND($K20="Y",$F20<>"Y",OR($T20="",$T20=Summary!$C$11)),$C20*IF($H20<>"",$H20,$D20)*INDEX(Summary!$C$6:$C$8,MATCH($P20,Summary!$B$6:$B$8,0)),0) -> 0 | V20: =IF(AND($K20="Y",$F20<>"Y",OR($T20="",$T20=Summary!$C$11)),$C20*IF($H20<>"",$H20,$E20)*INDEX(Summary!$C$6:$C$8,MATCH($P20,Summary!$B$6:$B$8,0)),0) -> 0 | W20: Notes | X20: https://www.aliexpress.com/item/32794645480.html
A21: C17 | B21: 6000-2RS bearing (10x26x8) | C21: 4 | F21: N | G21: N | I21: =IF(AND($K21="Y",$F21<>"Y",OR($T21="",$T21=Summary!$C$11)),$C21*IF($H21<>"",$H21,($D21+$E21)/2)*INDEX(Summary!$C$6:$C$8,MATCH($P21,Summary!$B$6:$B$8,0)),0) -> 0 | J21: Need | K21: Y | L21: CNC: Motion | M21: Bearing blocks | N21: Floating-end bearings. | O21: ea | P21: CAD | Q21: Buy | R21: AliExpress 1005006093979302 | S21: CNC build | U21: =IF(AND($K21="Y",$F21<>"Y",OR($T21="",$T21=Summary!$C$11)),$C21*IF($H21<>"",$H21,$D21)*INDEX(Summary!$C$6:$C$8,MATCH($P21,Summary!$B$6:$B$8,0)),0) -> 0 | V21: =IF(AND($K21="Y",$F21<>"Y",OR($T21="",$T21=Summary!$C$11)),$C21*IF($H21<>"",$H21,$E21)*INDEX(Summary!$C$6:$C$8,MATCH($P21,Summary!$B$6:$B$8,0)),0) -> 0 | W21: Notes | X21: https://www.aliexpress.com/item/1005006093979302.html
A22: C18 | B22: M12x1 locknut (ballscrew end) | C22: 4 | F22: N | G22: N | I22: =IF(AND($K22="Y",$F22<>"Y",OR($T22="",$T22=Summary!$C$11)),$C22*IF($H22<>"",$H22,($D22+$E22)/2)*INDEX(Summary!$C$6:$C$8,MATCH($P22,Summary!$B$6:$B$8,0)),0) -> 0 | J22: Need | K22: Y | L22: CNC: Motion | M22: Bearing blocks | N22: Also included in BK12 support kits. | O22: ea | P22: CAD | Q22: Buy | R22: AliExpress | S22: CNC build | U22: =IF(AND($K22="Y",$F22<>"Y",OR($T22="",$T22=Summary!$C$11)),$C22*IF($H22<>"",$H22,$D22)*INDEX(Summary!$C$6:$C$8,MATCH($P22,Summary!$B$6:$B$8,0)),0) -> 0 | V22: =IF(AND($K22="Y",$F22<>"Y",OR($T22="",$T22=Summary!$C$11)),$C22*IF($H22<>"",$H22,$E22)*INDEX(Summary!$C$6:$C$8,MATCH($P22,Summary!$B$6:$B$8,0)),0) -> 0 | W22: Notes
A23: C19 | B23: Shaft coupler 8 mm to 10 mm, jaw type D19 L25 | C23: 4 | F23: N | G23: N | I23: =IF(AND($K23="Y",$F23<>"Y",OR($T23="",$T23=Summary!$C$11)),$C23*IF($H23<>"",$H23,($D23+$E23)/2)*INDEX(Summary!$C$6:$C$8,MATCH($P23,Summary!$B$6:$B$8,0)),0) -> 0 | J23: Need | K23: Y | L23: CNC: Motion | M23: Drive | N23: Motor shaft 8 mm → screw end 10 mm. | O23: ea | P23: CAD | Q23: Buy | R23: AliExpress 1005007121900242 | S23: CNC build | U23: =IF(AND($K23="Y",$F23<>"Y",OR($T23="",$T23=Summary!$C$11)),$C23*IF($H23<>"",$H23,$D23)*INDEX(Summary!$C$6:$C$8,MATCH($P23,Summary!$B$6:$B$8,0)),0) -> 0 | V23: =IF(AND($K23="Y",$F23<>"Y",OR($T23="",$T23=Summary!$C$11)),$C23*IF($H23<>"",$H23,$E23)*INDEX(Summary!$C$6:$C$8,MATCH($P23,Summary!$B$6:$B$8,0)),0) -> 0 | W23: Notes | X23: https://www.aliexpress.com/item/1005007121900242.html
A24: C20 | B24: Motor / driver / supply kit: 4× NEMA 23 2.2 Nm, 4× TB6600, 36 V 350 W, Mach3 USB card | C24: 1 | F24: N | G24: N | H24: 185 | I24: =IF(AND($K24="Y",$F24<>"Y",OR($T24="",$T24=Summary!$C$11)),$C24*IF($H24<>"",$H24,($D24+$E24)/2)*INDEX(Summary!$C$6:$C$8,MATCH($P24,Summary!$B$6:$B$8,0)),0) -> 185 | J24: Need | K24: Y | L24: CNC: Electronics | M24: Motion control | N24: Decided Oct 4. Set TB6600 to ~2.5 A, 1/8–1/16 microstep. Treat the Mach3 USB card as a spare; GRBL runs on the UNO. Check motor body length vs the printed Y and Z mounts. | O24: kit | P24: CAD | Q24: Buy | R24: Amazon B0BTJTXHNN | S24: CNC build | U24: =IF(AND($K24="Y",$F24<>"Y",OR($T24="",$T24=Summary!$C$11)),$C24*IF($H24<>"",$H24,$D24)*INDEX(Summary!$C$6:$C$8,MATCH($P24,Summary!$B$6:$B$8,0)),0) -> 185 | V24: =IF(AND($K24="Y",$F24<>"Y",OR($T24="",$T24=Summary!$C$11)),$C24*IF($H24<>"",$H24,$E24)*INDEX(Summary!$C$6:$C$8,MATCH($P24,Summary!$B$6:$B$8,0)),0) -> 185 | W24: Verified | X24: https://www.amazon.ca/dp/B0BTJTXHNN
A25: C21 | B25: Arduino UNO | C25: 1 | F25: Y | G25: N | I25: =IF(AND($K25="Y",$F25<>"Y",OR($T25="",$T25=Summary!$C$11)),$C25*IF($H25<>"",$H25,($D25+$E25)/2)*INDEX(Summary!$C$6:$C$8,MATCH($P25,Summary!$B$6:$B$8,0)),0) -> 0 | J25: Have | K25: Y | L25: CNC: Electronics | M25: Motion control | N25: Flash GRBL 1.1. | O25: ea | P25: CAD | Q25: Have | R25: — | S25: CNC build | U25: =IF(AND($K25="Y",$F25<>"Y",OR($T25="",$T25=Summary!$C$11)),$C25*IF($H25<>"",$H25,$D25)*INDEX(Summary!$C$6:$C$8,MATCH($P25,Summary!$B$6:$B$8,0)),0) -> 0 | V25: =IF(AND($K25="Y",$F25<>"Y",OR($T25="",$T25=Summary!$C$11)),$C25*IF($H25<>"",$H25,$E25)*INDEX(Summary!$C$6:$C$8,MATCH($P25,Summary!$B$6:$B$8,0)),0) -> 0 | W25: Notes
A26: C22 | B26: CNC Shield V3 (shield only, no stepsticks) | C26: 1 | F26: N | G26: N | I26: =IF(AND($K26="Y",$F26<>"Y",OR($T26="",$T26=Summary!$C$11)),$C26*IF($H26<>"",$H26,($D26+$E26)/2)*INDEX(Summary!$C$6:$C$8,MATCH($P26,Summary!$B$6:$B$8,0)),0) -> 0 | J26: Need | K26: Y | L26: CNC: Electronics | M26: Motion control | N26: TB6600 step/dir wired to the shield's driver sockets. | O26: ea | P26: CAD | Q26: Buy | R26: AliExpress 1005006478108991 | S26: CNC build | U26: =IF(AND($K26="Y",$F26<>"Y",OR($T26="",$T26=Summary!$C$11)),$C26*IF($H26<>"",$H26,$D26)*INDEX(Summary!$C$6:$C$8,MATCH($P26,Summary!$B$6:$B$8,0)),0) -> 0 | V26: =IF(AND($K26="Y",$F26<>"Y",OR($T26="",$T26=Summary!$C$11)),$C26*IF($H26<>"",$H26,$E26)*INDEX(Summary!$C$6:$C$8,MATCH($P26,Summary!$B$6:$B$8,0)),0) -> 0 | W26: Notes | X26: https://www.aliexpress.com/item/1005006478108991.html
A27: C23 | B27: Limit switch, micro / endstop | C27: 6 | F27: N | G27: N | I27: =IF(AND($K27="Y",$F27<>"Y",OR($T27="",$T27=Summary!$C$11)),$C27*IF($H27<>"",$H27,($D27+$E27)/2)*INDEX(Summary!$C$6:$C$8,MATCH($P27,Summary!$B$6:$B$8,0)),0) -> 0 | J27: Need | K27: Y | L27: CNC: Electronics | M27: Switches | N27: 2 per axis. 5-packs. | O27: ea | P27: CAD | Q27: Buy | R27: AliExpress 1005001599112235 | S27: CNC build | U27: =IF(AND($K27="Y",$F27<>"Y",OR($T27="",$T27=Summary!$C$11)),$C27*IF($H27<>"",$H27,$D27)*INDEX(Summary!$C$6:$C$8,MATCH($P27,Summary!$B$6:$B$8,0)),0) -> 0 | V27: =IF(AND($K27="Y",$F27<>"Y",OR($T27="",$T27=Summary!$C$11)),$C27*IF($H27<>"",$H27,$E27)*INDEX(Summary!$C$6:$C$8,MATCH($P27,Summary!$B$6:$B$8,0)),0) -> 0 | W27: Notes | X27: https://www.aliexpress.com/item/1005001599112235.html
A28: C24 | B28: E-stop button, NC | C28: 1 | F28: N | G28: N | I28: =IF(AND($K28="Y",$F28<>"Y",OR($T28="",$T28=Summary!$C$11)),$C28*IF($H28<>"",$H28,($D28+$E28)/2)*INDEX(Summary!$C$6:$C$8,MATCH($P28,Summary!$B$6:$B$8,0)),0) -> 0 | J28: Need | K28: Y | L28: CNC: Electronics | M28: Switches | O28: ea | P28: CAD | Q28: Buy | R28: AliExpress | S28: CNC build | U28: =IF(AND($K28="Y",$F28<>"Y",OR($T28="",$T28=Summary!$C$11)),$C28*IF($H28<>"",$H28,$D28)*INDEX(Summary!$C$6:$C$8,MATCH($P28,Summary!$B$6:$B$8,0)),0) -> 0 | V28: =IF(AND($K28="Y",$F28<>"Y",OR($T28="",$T28=Summary!$C$11)),$C28*IF($H28<>"",$H28,$E28)*INDEX(Summary!$C$6:$C$8,MATCH($P28,Summary!$B$6:$B$8,0)),0) -> 0 | W28: Notes
A29: C25 | B29: Shielded 4-wire cable, stepper motors | C29: 15 | F29: N | G29: N | I29: =IF(AND($K29="Y",$F29<>"Y",OR($T29="",$T29=Summary!$C$11)),$C29*IF($H29<>"",$H29,($D29+$E29)/2)*INDEX(Summary!$C$6:$C$8,MATCH($P29,Summary!$B$6:$B$8,0)),0) -> 0 | J29: Need | K29: Y | L29: CNC: Electronics | M29: Wiring | N29: Author used double-shielded; ground the shield at the box only. | O29: m | P29: CAD | Q29: Buy | R29: AliExpress | S29: CNC build | U29: =IF(AND($K29="Y",$F29<>"Y",OR($T29="",$T29=Summary!$C$11)),$C29*IF($H29<>"",$H29,$D29)*INDEX(Summary!$C$6:$C$8,MATCH($P29,Summary!$B$6:$B$8,0)),0) -> 0 | V29: =IF(AND($K29="Y",$F29<>"Y",OR($T29="",$T29=Summary!$C$11)),$C29*IF($H29<>"",$H29,$E29)*INDEX(Summary!$C$6:$C$8,MATCH($P29,Summary!$B$6:$B$8,0)),0) -> 0 | W29: Notes
A30: C26 | B30: Shielded 2-wire cable, limit switches | C30: 10 | F30: N | G30: N | I30: =IF(AND($K30="Y",$F30<>"Y",OR($T30="",$T30=Summary!$C$11)),$C30*IF($H30<>"",$H30,($D30+$E30)/2)*INDEX(Summary!$C$6:$C$8,MATCH($P30,Summary!$B$6:$B$8,0)),0) -> 0 | J30: Need | K30: Y | L30: CNC: Electronics | M30: Wiring | O30: m | P30: CAD | Q30: Buy | R30: AliExpress | S30: CNC build | U30: =IF(AND($K30="Y",$F30<>"Y",OR($T30="",$T30=Summary!$C$11)),$C30*IF($H30<>"",$H30,$D30)*INDEX(Summary!$C$6:$C$8,MATCH($P30,Summary!$B$6:$B$8,0)),0) -> 0 | V30: =IF(AND($K30="Y",$F30<>"Y",OR($T30="",$T30=Summary!$C$11)),$C30*IF($H30<>"",$H30,$E30)*INDEX(Summary!$C$6:$C$8,MATCH($P30,Summary!$B$6:$B$8,0)),0) -> 0 | W30: Notes
A31: C27 | B31: Drag chain 10x20 + end mounts | C31: 2 | F31: N | G31: N | I31: =IF(AND($K31="Y",$F31<>"Y",OR($T31="",$T31=Summary!$C$11)),$C31*IF($H31<>"",$H31,($D31+$E31)/2)*INDEX(Summary!$C$6:$C$8,MATCH($P31,Summary!$B$6:$B$8,0)),0) -> 0 | J31: Need | K31: Y | L31: CNC: Electronics | M31: Wiring | N31: X and Y runs. | O31: m | P31: CAD | Q31: Buy | R31: AliExpress | S31: CNC build | U31: =IF(AND($K31="Y",$F31<>"Y",OR($T31="",$T31=Summary!$C$11)),$C31*IF($H31<>"",$H31,$D31)*INDEX(Summary!$C$6:$C$8,MATCH($P31,Summary!$B$6:$B$8,0)),0) -> 0 | V31: =IF(AND($K31="Y",$F31<>"Y",OR($T31="",$T31=Summary!$C$11)),$C31*IF($H31<>"",$H31,$E31)*INDEX(Summary!$C$6:$C$8,MATCH($P31,Summary!$B$6:$B$8,0)),0) -> 0 | W31: Notes
A32: C28 | B32: Terminal blocks, ferrules, USB cable, hookup wire | C32: 1 | F32: N | G32: N | I32: =IF(AND($K32="Y",$F32<>"Y",OR($T32="",$T32=Summary!$C$11)),$C32*IF($H32<>"",$H32,($D32+$E32)/2)*INDEX(Summary!$C$6:$C$8,MATCH($P32,Summary!$B$6:$B$8,0)),0) -> 0 | J32: Need | K32: Y | L32: CNC: Electronics | M32: Wiring | O32: lot | P32: CAD | Q32: Buy | R32: Amazon / AliExpress | S32: CNC build | U32: =IF(AND($K32="Y",$F32<>"Y",OR($T32="",$T32=Summary!$C$11)),$C32*IF($H32<>"",$H32,$D32)*INDEX(Summary!$C$6:$C$8,MATCH($P32,Summary!$B$6:$B$8,0)),0) -> 0 | V32: =IF(AND($K32="Y",$F32<>"Y",OR($T32="",$T32=Summary!$C$11)),$C32*IF($H32<>"",$H32,$E32)*INDEX(Summary!$C$6:$C$8,MATCH($P32,Summary!$B$6:$B$8,0)),0) -> 0 | W32: Notes
A33: C29 | B33: Electronics mounting panel (plywood) — enclosure optional | C33: 1 | F33: N | G33: N | I33: =IF(AND($K33="Y",$F33<>"Y",OR($T33="",$T33=Summary!$C$11)),$C33*IF($H33<>"",$H33,($D33+$E33)/2)*INDEX(Summary!$C$6:$C$8,MATCH($P33,Summary!$B$6:$B$8,0)),0) -> 0 | J33: Optional | K33: Y | L33: CNC: Electronics | M33: Control box | N33: Author's metal enclosure + GX16 connectors cost ~US$500; an open panel does the job. | O33: ea | P33: CAD | Q33: Make | R33: — | S33: CNC build | U33: =IF(AND($K33="Y",$F33<>"Y",OR($T33="",$T33=Summary!$C$11)),$C33*IF($H33<>"",$H33,$D33)*INDEX(Summary!$C$6:$C$8,MATCH($P33,Summary!$B$6:$B$8,0)),0) -> 0 | V33: =IF(AND($K33="Y",$F33<>"Y",OR($T33="",$T33=Summary!$C$11)),$C33*IF($H33<>"",$H33,$E33)*INDEX(Summary!$C$6:$C$8,MATCH($P33,Summary!$B$6:$B$8,0)),0) -> 0 | W33: Notes
A34: C30 | B34: 12 V fan + DC-DC converter for the box | C34: 1 | F34: N | G34: N | I34: =IF(AND($K34="Y",$F34<>"Y",OR($T34="",$T34=Summary!$C$11)),$C34*IF($H34<>"",$H34,($D34+$E34)/2)*INDEX(Summary!$C$6:$C$8,MATCH($P34,Summary!$B$6:$B$8,0)),0) -> 0 | J34: Optional | K34: N | L34: CNC: Electronics | M34: Control box | N34: Only if the drivers go in a closed box. | O34: ea | P34: CAD | Q34: Buy | R34: AliExpress | S34: CNC build | U34: =IF(AND($K34="Y",$F34<>"Y",OR($T34="",$T34=Summary!$C$11)),$C34*IF($H34<>"",$H34,$D34)*INDEX(Summary!$C$6:$C$8,MATCH($P34,Summary!$B$6:$B$8,0)),0) -> 0 | V34: =IF(AND($K34="Y",$F34<>"Y",OR($T34="",$T34=Summary!$C$11)),$C34*IF($H34<>"",$H34,$E34)*INDEX(Summary!$C$6:$C$8,MATCH($P34,Summary!$B$6:$B$8,0)),0) -> 0 | W34: Notes
A35: C31 | B35: Ethernet CNC controller (grblHAL Teensy 4.1 + breakout) — EMI fix | C35: 1 | F35: N | G35: N | I35: =IF(AND($K35="Y",$F35<>"Y",OR($T35="",$T35=Summary!$C$11)),$C35*IF($H35<>"",$H35,($D35+$E35)/2)*INDEX(Summary!$C$6:$C$8,MATCH($P35,Summary!$B$6:$B$8,0)),0) -> 0 | J35: Option | K35: N | L35: CNC: Electronics | M35: Motion control | N35: Author could not fully stop USB/EMI false alarms on Arduino+GRBL. Upgrade path, not needed to start. | O35: ea | P35: CAD | Q35: Buy | R35: — | S35: CNC build | U35: =IF(AND($K35="Y",$F35<>"Y",OR($T35="",$T35=Summary!$C$11)),$C35*IF($H35<>"",$H35,$D35)*INDEX(Summary!$C$6:$C$8,MATCH($P35,Summary!$B$6:$B$8,0)),0) -> 0 | V35: =IF(AND($K35="Y",$F35<>"Y",OR($T35="",$T35=Summary!$C$11)),$C35*IF($H35<>"",$H35,$E35)*INDEX(Summary!$C$6:$C$8,MATCH($P35,Summary!$B$6:$B$8,0)),0) -> 0 | W35: Notes
A36: C32 | B36: Makita RT0701C trim router (65 mm body) | C36: 1 | F36: N | G36: N | I36: =IF(AND($K36="Y",$F36<>"Y",OR($T36="",$T36=Summary!$C$11)),$C36*IF($H36<>"",$H36,($D36+$E36)/2)*INDEX(Summary!$C$6:$C$8,MATCH($P36,Summary!$B$6:$B$8,0)),0) -> 0 | J36: To decide | K36: Y | L36: CNC: Spindle | M36: Router | N36: New vs used vs 65 mm clone. The printed mount is sized for the 65 mm Makita body; the Craftsman does not fit. | O36: ea | P36: CAD | Q36: Buy | R36: Home Depot / Amazon.ca / Marketplace | S36: CNC build | U36: =IF(AND($K36="Y",$F36<>"Y",OR($T36="",$T36=Summary!$C$11)),$C36*IF($H36<>"",$H36,$D36)*INDEX(Summary!$C$6:$C$8,MATCH($P36,Summary!$B$6:$B$8,0)),0) -> 0 | V36: =IF(AND($K36="Y",$F36<>"Y",OR($T36="",$T36=Summary!$C$11)),$C36*IF($H36<>"",$H36,$E36)*INDEX(Summary!$C$6:$C$8,MATCH($P36,Summary!$B$6:$B$8,0)),0) -> 0 | W36: Notes
A37: C33 | B37: 6 mm collet for RT0701C | C37: 1 | F37: N | G37: N | I37: =IF(AND($K37="Y",$F37<>"Y",OR($T37="",$T37=Summary!$C$11)),$C37*IF($H37<>"",$H37,($D37+$E37)/2)*INDEX(Summary!$C$6:$C$8,MATCH($P37,Summary!$B$6:$B$8,0)),0) -> 0 | J37: Need | K37: Y | L37: CNC: Spindle | M37: Router | N37: Router ships with 1/4 in only. | O37: ea | P37: CAD | Q37: Buy | R37: Amazon / AliExpress | S37: CNC build | U37: =IF(AND($K37="Y",$F37<>"Y",OR($T37="",$T37=Summary!$C$11)),$C37*IF($H37<>"",$H37,$D37)*INDEX(Summary!$C$6:$C$8,MATCH($P37,Summary!$B$6:$B$8,0)),0) -> 0 | V37: =IF(AND($K37="Y",$F37<>"Y",OR($T37="",$T37=Summary!$C$11)),$C37*IF($H37<>"",$H37,$E37)*INDEX(Summary!$C$6:$C$8,MATCH($P37,Summary!$B$6:$B$8,0)),0) -> 0 | W37: Notes
A38: C34 | B38: VFD spindle 1.5–2.2 kW ER20 + VFD (phase 2) | C38: 1 | F38: N | G38: N | I38: =IF(AND($K38="Y",$F38<>"Y",OR($T38="",$T38=Summary!$C$11)),$C38*IF($H38<>"",$H38,($D38+$E38)/2)*INDEX(Summary!$C$6:$C$8,MATCH($P38,Summary!$B$6:$B$8,0)),0) -> 0 | J38: Option | K38: N | L38: CNC: Spindle | M38: Upgrade | N38: Author moved to a 2.2 kW VFD spindle for runout; do this before the gearbox adapter plate. | O38: ea | P38: CAD | Q38: Buy | R38: AliExpress | S38: CNC build | U38: =IF(AND($K38="Y",$F38<>"Y",OR($T38="",$T38=Summary!$C$11)),$C38*IF($H38<>"",$H38,$D38)*INDEX(Summary!$C$6:$C$8,MATCH($P38,Summary!$B$6:$B$8,0)),0) -> 0 | V38: =IF(AND($K38="Y",$F38<>"Y",OR($T38="",$T38=Summary!$C$11)),$C38*IF($H38<>"",$H38,$E38)*INDEX(Summary!$C$6:$C$8,MATCH($P38,Summary!$B$6:$B$8,0)),0) -> 0 | W38: Notes
A39: C35 | B39: 80 mm spindle mount (if VFD spindle) | C39: 1 | F39: N | G39: N | I39: =IF(AND($K39="Y",$F39<>"Y",OR($T39="",$T39=Summary!$C$11)),$C39*IF($H39<>"",$H39,($D39+$E39)/2)*INDEX(Summary!$C$6:$C$8,MATCH($P39,Summary!$B$6:$B$8,0)),0) -> 0 | J39: Option | K39: N | L39: CNC: Spindle | M39: Upgrade | N39: Machine it on the CNC itself. | O39: ea | P39: CAD | Q39: Make | R39: — | S39: CNC build | U39: =IF(AND($K39="Y",$F39<>"Y",OR($T39="",$T39=Summary!$C$11)),$C39*IF($H39<>"",$H39,$D39)*INDEX(Summary!$C$6:$C$8,MATCH($P39,Summary!$B$6:$B$8,0)),0) -> 0 | V39: =IF(AND($K39="Y",$F39<>"Y",OR($T39="",$T39=Summary!$C$11)),$C39*IF($H39<>"",$H39,$E39)*INDEX(Summary!$C$6:$C$8,MATCH($P39,Summary!$B$6:$B$8,0)),0) -> 0 | W39: Notes
A40: C36 | B40: Filament, PETG / ASA, ~3 kg for all printed parts | C40: 3 | F40: Y | G40: N | I40: =IF(AND($K40="Y",$F40<>"Y",OR($T40="",$T40=Summary!$C$11)),$C40*IF($H40<>"",$H40,($D40+$E40)/2)*INDEX(Summary!$C$6:$C$8,MATCH($P40,Summary!$B$6:$B$8,0)),0) -> 0 | J40: Have | K40: Y | L40: CNC: Printed parts | M40: Printing | N40: Avoid PLA (creep under bolt preload). Thicken the router mount walls (author: biggest rigidity gain). | O40: kg | P40: CAD | Q40: Have | R40: — | S40: CNC build | U40: =IF(AND($K40="Y",$F40<>"Y",OR($T40="",$T40=Summary!$C$11)),$C40*IF($H40<>"",$H40,$D40)*INDEX(Summary!$C$6:$C$8,MATCH($P40,Summary!$B$6:$B$8,0)),0) -> 0 | V40: =IF(AND($K40="Y",$F40<>"Y",OR($T40="",$T40=Summary!$C$11)),$C40*IF($H40<>"",$H40,$E40)*INDEX(Summary!$C$6:$C$8,MATCH($P40,Summary!$B$6:$B$8,0)),0) -> 0 | W40: Notes
A41: C37 | B41: HTMCNC STL + STEP files (Cults3D) | C41: 1 | F41: N | G41: N | I41: =IF(AND($K41="Y",$F41<>"Y",OR($T41="",$T41=Summary!$C$11)),$C41*IF($H41<>"",$H41,($D41+$E41)/2)*INDEX(Summary!$C$6:$C$8,MATCH($P41,Summary!$B$6:$B$8,0)),0) -> 0 | J41: Need | K41: Y | L41: CNC: Printed parts | M41: Files | N41: Onshape model is free to view; files are paid. | O41: ea | P41: CAD | Q41: Buy | R41: Cults3D | S41: CNC build | U41: =IF(AND($K41="Y",$F41<>"Y",OR($T41="",$T41=Summary!$C$11)),$C41*IF($H41<>"",$H41,$D41)*INDEX(Summary!$C$6:$C$8,MATCH($P41,Summary!$B$6:$B$8,0)),0) -> 0 | V41: =IF(AND($K41="Y",$F41<>"Y",OR($T41="",$T41=Summary!$C$11)),$C41*IF($H41<>"",$H41,$E41)*INDEX(Summary!$C$6:$C$8,MATCH($P41,Summary!$B$6:$B$8,0)),0) -> 0 | W41: Notes | X41: https://cults3d.com/en/3d-model/tool/diy-3d-printed-cnc-machine-htmcnc
A42: C38 | B42: MDF spoilboard 18–19 mm, ~500 x 800 mm | C42: 1 | F42: N | G42: N | I42: =IF(AND($K42="Y",$F42<>"Y",OR($T42="",$T42=Summary!$C$11)),$C42*IF($H42<>"",$H42,($D42+$E42)/2)*INDEX(Summary!$C$6:$C$8,MATCH($P42,Summary!$B$6:$B$8,0)),0) -> 0 | J42: Need | K42: Y | L42: CNC: Bed | M42: Workholding | N42: Surface it with the machine once running. | O42: ea | P42: CAD | Q42: Buy | R42: Home Depot | S42: CNC build | U42: =IF(AND($K42="Y",$F42<>"Y",OR($T42="",$T42=Summary!$C$11)),$C42*IF($H42<>"",$H42,$D42)*INDEX(Summary!$C$6:$C$8,MATCH($P42,Summary!$B$6:$B$8,0)),0) -> 0 | V42: =IF(AND($K42="Y",$F42<>"Y",OR($T42="",$T42=Summary!$C$11)),$C42*IF($H42<>"",$H42,$E42)*INDEX(Summary!$C$6:$C$8,MATCH($P42,Summary!$B$6:$B$8,0)),0) -> 0 | W42: Notes
A43: C39 | B43: Threaded inserts M6 (or T-track) for hold-downs | C43: 1 | F43: N | G43: N | I43: =IF(AND($K43="Y",$F43<>"Y",OR($T43="",$T43=Summary!$C$11)),$C43*IF($H43<>"",$H43,($D43+$E43)/2)*INDEX(Summary!$C$6:$C$8,MATCH($P43,Summary!$B$6:$B$8,0)),0) -> 0 | J43: Need | K43: Y | L43: CNC: Bed | M43: Workholding | O43: lot | P43: CAD | Q43: Buy | R43: Amazon / AliExpress | S43: CNC build | U43: =IF(AND($K43="Y",$F43<>"Y",OR($T43="",$T43=Summary!$C$11)),$C43*IF($H43<>"",$H43,$D43)*INDEX(Summary!$C$6:$C$8,MATCH($P43,Summary!$B$6:$B$8,0)),0) -> 0 | V43: =IF(AND($K43="Y",$F43<>"Y",OR($T43="",$T43=Summary!$C$11)),$C43*IF($H43<>"",$H43,$E43)*INDEX(Summary!$C$6:$C$8,MATCH($P43,Summary!$B$6:$B$8,0)),0) -> 0 | W43: Notes
A44: C40 | B44: Clamps / hold-down set | C44: 1 | F44: N | G44: N | I44: =IF(AND($K44="Y",$F44<>"Y",OR($T44="",$T44=Summary!$C$11)),$C44*IF($H44<>"",$H44,($D44+$E44)/2)*INDEX(Summary!$C$6:$C$8,MATCH($P44,Summary!$B$6:$B$8,0)),0) -> 0 | J44: Need | K44: Y | L44: CNC: Bed | M44: Workholding | N44: Print the first set; machine aluminum ones later. | O44: set | P44: CAD | Q44: Make | R44: — | S44: CNC build | U44: =IF(AND($K44="Y",$F44<>"Y",OR($T44="",$T44=Summary!$C$11)),$C44*IF($H44<>"",$H44,$D44)*INDEX(Summary!$C$6:$C$8,MATCH($P44,Summary!$B$6:$B$8,0)),0) -> 0 | V44: =IF(AND($K44="Y",$F44<>"Y",OR($T44="",$T44=Summary!$C$11)),$C44*IF($H44<>"",$H44,$E44)*INDEX(Summary!$C$6:$C$8,MATCH($P44,Summary!$B$6:$B$8,0)),0) -> 0 | W44: Notes
A45: C41 | B45: Single-flute carbide endmill, 6 mm, aluminum | C45: 2 | F45: N | G45: N | I45: =IF(AND($K45="Y",$F45<>"Y",OR($T45="",$T45=Summary!$C$11)),$C45*IF($H45<>"",$H45,($D45+$E45)/2)*INDEX(Summary!$C$6:$C$8,MATCH($P45,Summary!$B$6:$B$8,0)),0) -> 0 | J45: Need | K45: Y | L45: CNC: Tooling | M45: Cutters | N45: Roughing + profiling the flanges and adapter. | O45: ea | P45: CAD | Q45: Buy | R45: AliExpress 1005001948417279 | S45: CNC build | U45: =IF(AND($K45="Y",$F45<>"Y",OR($T45="",$T45=Summary!$C$11)),$C45*IF($H45<>"",$H45,$D45)*INDEX(Summary!$C$6:$C$8,MATCH($P45,Summary!$B$6:$B$8,0)),0) -> 0 | V45: =IF(AND($K45="Y",$F45<>"Y",OR($T45="",$T45=Summary!$C$11)),$C45*IF($H45<>"",$H45,$E45)*INDEX(Summary!$C$6:$C$8,MATCH($P45,Summary!$B$6:$B$8,0)),0) -> 0 | W45: Notes | X45: https://www.aliexpress.com/item/1005001948417279.html
A46: C42 | B46: Single-flute carbide endmill, 3 mm or 1/8 in | C46: 2 | F46: N | G46: N | I46: =IF(AND($K46="Y",$F46<>"Y",OR($T46="",$T46=Summary!$C$11)),$C46*IF($H46<>"",$H46,($D46+$E46)/2)*INDEX(Summary!$C$6:$C$8,MATCH($P46,Summary!$B$6:$B$8,0)),0) -> 0 | J46: Need | K46: Y | L46: CNC: Tooling | M46: Cutters | N46: Small features, bung holes. | O46: ea | P46: CAD | Q46: Buy | R46: AliExpress 1005001948417279 | S46: CNC build | U46: =IF(AND($K46="Y",$F46<>"Y",OR($T46="",$T46=Summary!$C$11)),$C46*IF($H46<>"",$H46,$D46)*INDEX(Summary!$C$6:$C$8,MATCH($P46,Summary!$B$6:$B$8,0)),0) -> 0 | V46: =IF(AND($K46="Y",$F46<>"Y",OR($T46="",$T46=Summary!$C$11)),$C46*IF($H46<>"",$H46,$E46)*INDEX(Summary!$C$6:$C$8,MATCH($P46,Summary!$B$6:$B$8,0)),0) -> 0 | W46: Notes | X46: https://www.aliexpress.com/item/1005001948417279.html
A47: C43 | B47: Dial indicator + magnetic base | C47: 1 | F47: N | G47: N | I47: =IF(AND($K47="Y",$F47<>"Y",OR($T47="",$T47=Summary!$C$11)),$C47*IF($H47<>"",$H47,($D47+$E47)/2)*INDEX(Summary!$C$6:$C$8,MATCH($P47,Summary!$B$6:$B$8,0)),0) -> 0 | J47: To decide | K47: Y | L47: CNC: Tooling | M47: Setup | N47: Tramming, squareness, collet runout. Mark Have if you own one. | O47: ea | P47: CAD | Q47: Buy | R47: Amazon / Princess Auto | S47: CNC build | U47: =IF(AND($K47="Y",$F47<>"Y",OR($T47="",$T47=Summary!$C$11)),$C47*IF($H47<>"",$H47,$D47)*INDEX(Summary!$C$6:$C$8,MATCH($P47,Summary!$B$6:$B$8,0)),0) -> 0 | V47: =IF(AND($K47="Y",$F47<>"Y",OR($T47="",$T47=Summary!$C$11)),$C47*IF($H47<>"",$H47,$E47)*INDEX(Summary!$C$6:$C$8,MATCH($P47,Summary!$B$6:$B$8,0)),0) -> 0 | W47: Notes
A48: C44 | B48: Z touch plate / probe | C48: 1 | F48: N | G48: N | I48: =IF(AND($K48="Y",$F48<>"Y",OR($T48="",$T48=Summary!$C$11)),$C48*IF($H48<>"",$H48,($D48+$E48)/2)*INDEX(Summary!$C$6:$C$8,MATCH($P48,Summary!$B$6:$B$8,0)),0) -> 0 | J48: Optional | K48: Y | L48: CNC: Tooling | M48: Setup | O48: ea | P48: CAD | Q48: Buy | R48: AliExpress | S48: CNC build | U48: =IF(AND($K48="Y",$F48<>"Y",OR($T48="",$T48=Summary!$C$11)),$C48*IF($H48<>"",$H48,$D48)*INDEX(Summary!$C$6:$C$8,MATCH($P48,Summary!$B$6:$B$8,0)),0) -> 0 | V48: =IF(AND($K48="Y",$F48<>"Y",OR($T48="",$T48=Summary!$C$11)),$C48*IF($H48<>"",$H48,$E48)*INDEX(Summary!$C$6:$C$8,MATCH($P48,Summary!$B$6:$B$8,0)),0) -> 0 | W48: Notes
A49: C45 | B49: Air blast or mist setup (isopropyl / WD-40) for aluminum | C49: 1 | F49: N | G49: N | I49: =IF(AND($K49="Y",$F49<>"Y",OR($T49="",$T49=Summary!$C$11)),$C49*IF($H49<>"",$H49,($D49+$E49)/2)*INDEX(Summary!$C$6:$C$8,MATCH($P49,Summary!$B$6:$B$8,0)),0) -> 0 | J49: Optional | K49: Y | L49: CNC: Tooling | M49: Setup | N49: Stops chip welding on the single-flute cutters. | O49: ea | P49: CAD | Q49: Buy | R49: Amazon / AliExpress | S49: CNC build | U49: =IF(AND($K49="Y",$F49<>"Y",OR($T49="",$T49=Summary!$C$11)),$C49*IF($H49<>"",$H49,$D49)*INDEX(Summary!$C$6:$C$8,MATCH($P49,Summary!$B$6:$B$8,0)),0) -> 0 | V49: =IF(AND($K49="Y",$F49<>"Y",OR($T49="",$T49=Summary!$C$11)),$C49*IF($H49<>"",$H49,$E49)*INDEX(Summary!$C$6:$C$8,MATCH($P49,Summary!$B$6:$B$8,0)),0) -> 0 | W49: Notes
A50: C46 | B50: Grease for rails and ballscrews, zip ties, heat shrink | C50: 1 | F50: N | G50: N | I50: =IF(AND($K50="Y",$F50<>"Y",OR($T50="",$T50=Summary!$C$11)),$C50*IF($H50<>"",$H50,($D50+$E50)/2)*INDEX(Summary!$C$6:$C$8,MATCH($P50,Summary!$B$6:$B$8,0)),0) -> 0 | J50: Need | K50: Y | L50: CNC: Misc | M50: Consumables | O50: lot | P50: CAD | Q50: Buy | R50: Amazon | S50: CNC build | U50: =IF(AND($K50="Y",$F50<>"Y",OR($T50="",$T50=Summary!$C$11)),$C50*IF($H50<>"",$H50,$D50)*INDEX(Summary!$C$6:$C$8,MATCH($P50,Summary!$B$6:$B$8,0)),0) -> 0 | V50: =IF(AND($K50="Y",$F50<>"Y",OR($T50="",$T50=Summary!$C$11)),$C50*IF($H50<>"",$H50,$E50)*INDEX(Summary!$C$6:$C$8,MATCH($P50,Summary!$B$6:$B$8,0)),0) -> 0 | W50: Notes
H51: TOTAL | I51: =SUM(I5:I50) -> 349.98 | U51: =SUM(U5:U50) -> 349.98 | V51: =SUM(V5:V50) -> 349.98

Sheet How to use
A1: How to use this sheet
A2: 1. Go to the BOM tab. Work down the list one line at a time.
A3: 2. Have? — put Y if you already own the part (it then counts $0). Rows turn green.
A4: 3. Make? — put Y if you'll make it. Then change 'Est. unit low/high' (or 'MY unit cost') to the MATERIAL cost. Lines that say MAKE already have material prices.
A5: 4. MY unit cost — when you find the real price, type it here in the row's currency. It replaces the estimate in all totals, and the contingency stops applying to that line.
A6: 5. Include — N drops a line. Use it to switch between options (e.g. U01 Garrett vs U04/U05 RS3 turbo; O02 custom sump vs O09 Boost Brothers pan; G25–G27 own CSC parts vs G28 bought kit).
A7: 6. Status — Need / To decide / Option / Optional / Ordered / Have / Done. Yellow = To decide: look at these first.
A8: 7. Summary tab → Gearbox route: RX-8 (default) or ZN6 TL70. Lines for the other route turn orange and are excluded.
A9: 8. Summary tab → Contingency: 25% is applied only to lines you haven't confirmed. The more real prices you enter, the smaller it gets.
A10: 9. Columns L–X (System, Sub-assembly, Spec/notes, Vendor, Phase, Route, Basis, Link) are hidden to fit the screen. Click the + above column L (Google Sheets: the small arrow at the column edge) to expand them. The filter arrows on the header still filter by them.
A11: 10. Everything is in CAD. If you find a price in USD or GBP, convert it with the rates on the Summary tab (or change that row's Cur to USD/GBP and type the foreign price).
A12: Colours: blue = you edit it; yellow = key input; green row = you have it; grey row = excluded; orange row = other gearbox route.
... A14: 10. CNC tab — the parts list for the DIY CNC mill (HTMCNC-style, Y scaled to 750 mm). Same columns and colour rules as the BOM tab, plus pink Est. cells = no price decided yet. The Summary has its own CNC block; it is not added to the car's ALL-IN.
